Workbook

Sheet GORE
A1: PRESUPUESTO OFICIAL — PROYECTO LUZ EN CASA · GORE COQUIMBO
A2: Financiamiento FNDR Subtítulo 33 · 75 sistemas FV domiciliarios · Cofinanciamiento 50% / 50%
B5: Ítem / Descripción | C5: Ago 2026 | D5: Sep 2026 | E5: Oct 2026 | F5: Nov 2026 | G5: Dic 2026 | H5: Ene 2027 | I5: Feb 2027 | J5: TOTAL | L5: GORE | M5: FUNDACIÓN
A6: 1 | B6: Diagnóstico general y catastro básico de hogares en La Higuera | C6: =+'Valorización Componentes'!C4 | D6: =+'Valorización Componentes'!D4 | E6: =+'Valorización Componentes'!E4 | F6: =+'Valorización Componentes'!F4 | G6: =+'Valorización Componentes'!G4 | H6: =+'Valorización Componentes'!H4 | I6: =+'Valorización Componentes'!I4 | J6: =SUM(C4:I4) | L6: =+J4
B7: Levantamiento y revisión de antecedentes territoriales, sociales y energéticos 90 km radio desde La Serena
B8: Revisión preliminar de sectores, localidades y hogares potencialmente beneficiarios del programa.
B9: Elaboración del informe de diagnóstico general y universo inicial de hogares a catastrar.
A10: 2 | B10: Catastro georeferenciado uno a uno de viviendas | C10: =+'Valorización Componentes'!C22 | D10: =+'Valorización Componentes'!D22 | E10: =+'Valorización Componentes'!E22 | F10: =+'Valorización Componentes'!F22 | G10: =+'Valorización Componentes'!G22 | H10: =+'Valorización Componentes'!H22 | I10: =+'Valorización Componentes'!I22 | J10: =SUM(C8:I8) | L10: =+J8
B11: Planificación de rutas, sectores de visita y metodología de levantamiento georreferenciado.
B12: Aplicación de ficha de catastro vivienda a vivienda, incluyendo ubicación, condición habitacional y situación energética.
B13: Consolidación de base de datos georreferenciada, respaldo fotográfico y mapa de viviendas catastradas.
A14: 3 | B14: Verificación y sensibilización de usuarios catastrados. Incorporación de beneficiarios a programa de instalación. | C14: =+'Valorización Componentes'!C40 | D14: =+'Valorización Componentes'!D40 | E14: =+'Valorización Componentes'!E40 | F14: =+'Valorización Componentes'!F40 | G14: =+'Valorización Componentes'!G40 | H14: =+'Valorización Componentes'!H40 | I14: =+'Valorización Componentes'!I40 | J14: =SUM(C12:I12) | L14: =+J12
B15: Verificación en terreno de antecedentes levantados en el catastro y validación de cumplimiento de criterios de elegibilidad.
B16: Ejecución de jornadas de sensibilización sobre alcances del programa, condiciones de participación y responsabilidades del usuario.
B17: Elaboración de nómina final de beneficiarios e incorporación formal de usuarios al programa de instalación.
A18: 4 | B18: Capacitación de sistemas ERNC usuarios beneficiario. | C18: =+'Valorización Componentes'!C59 | D18: =+'Valorización Componentes'!D59 | E18: =+'Valorización Componentes'!E59 | F18: =+'Valorización Componentes'!F59 | G18: =+'Valorización Componentes'!G59 | H18: =+'Valorización Componentes'!H59 | I18: =+'Valorización Componentes'!I59 | J18: =SUM(C16:I16) | L18: =+J16
B19: Diseño de contenidos de capacitación sobre funcionamiento básico, seguridad y cuidados de sistemas ERNC domiciliarios.
B20: Realización de talleres prácticos para usuarios beneficiarios sobre operación diaria del sistema.
B21: Evaluación de comprensión de usuarios y entrega de material de apoyo para uso y cuidado del sistema.
A22: 5 | B22: Implementacion del un modelo de mantenimiento a 10 años | C22: =SUM(C21:C22) | D22: =SUM(D21:D22) | E22: =SUM(E21:E22) | F22: =SUM(F21:F22) | G22: =SUM(G21:G22) | H22: =SUM(H21:H22) | I22: =SUM(I21:I22) | J22: =SUM(C20:I20) | L22: =+J20
B23: Prograna de mantenimiento operativo | F23: =+'Valorización Componentes'!F77
B24: Programa de reposición | I24: =+'Valorización Componentes'!I77 | J24: =SUM(C22:I22) | M24: =+J22
A25: 6 | B25: Sistemas ERNC | C25: =+C24+C25 | D25: =+D24+D25 | E25: =+E24+E25 | F25: =+F24+F25 | G25: =+G24+G25 | H25: =+H24+H25 | I25: =+I24+I25 | J25: =SUM(C23:I23) | M25: =+J23 | N25: =2051000*70 | O25: =2051000*75
B26: Adquisición de Materiales | C26: =+SUM('Valorización Componentes'!C96:C100) | D26: =+SUM('Valorización Componentes'!D96:D100) | E26: =+SUM('Valorización Componentes'!E96:E100) | F26: =+SUM('Valorización Componentes'!F96:F100) | G26: =+SUM('Valorización Componentes'!G96:G100) | H26: =+SUM('Valorización Componentes'!H96:H100) | I26: =+SUM('Valorización Componentes'!I96:I100) | J26: =SUM(C24:I24)
B27: Logistica | C27: =+SUM('Valorización Componentes'!C102:C106) | D27: =+SUM('Valorización Componentes'!D102:D106) | E27: =+SUM('Valorización Componentes'!E102:E106) | F27: =+SUM('Valorización Componentes'!F102:F106) | G27: =+SUM('Valorización Componentes'!G102:G106) | H27: =+SUM('Valorización Componentes'!H102:H106) | I27: =+SUM('Valorización Componentes'!I102:I106) | J27: =SUM(C25:I25)
A28: 7 | B28: instalacion | C28: =+'Valorización Componentes'!C107 | D28: =+'Valorización Componentes'!D107 | E28: =+'Valorización Componentes'!E107 | F28: =+'Valorización Componentes'!F107 | G28: =+'Valorización Componentes'!G107 | H28: =+'Valorización Componentes'!H107 | I28: =+'Valorización Componentes'!I107 | J28: =SUM(C26:I26) | L28: =+J26
B29: Logistica y Abastecimiento
B30: Instalación de Equipos
B31: Te1
A32: 8 | B32: Formación y Asesoria a usuarios de electrodomésticos y uso. | C32: =+'Valorización Componentes'!C166 | D32: =+'Valorización Componentes'!D166 | E32: =+'Valorización Componentes'!E166 | F32: =+'Valorización Componentes'!F166 | G32: =+'Valorización Componentes'!G166 | H32: =+'Valorización Componentes'!H166 | I32: =+'Valorización Componentes'!I166 | J32: =SUM(C30:I30) | L32: =+J30
B33: Asesoría a usuarios sobre uso eficiente de electrodomésticos, priorización de consumos y prevención de sobrecargas.
B34: Acompañamiento inicial post-instalación para resolver dudas de uso, operación segura y buenas prácticas de consumo.
A35: 9 | B35: Cierre de proyecto - informes de instalación | C35: =+'Valorización Componentes'!C184 | D35: =+'Valorización Componentes'!D184 | E35: =+'Valorización Componentes'!E184 | F35: =+'Valorización Componentes'!F184 | G35: =+'Valorización Componentes'!G184 | H35: =+'Valorización Componentes'!H184 | I35: =+'Valorización Componentes'!I184 | J35: =SUM(C33:I33) | L35: =+J33
B36: Revisión y recopilación de actas de instalación, registros fotográficos, fichas técnicas y respaldos por vivienda.
B37: Elaboración de informes técnicos de instalación y puesta en marcha por sistema o grupo de beneficiarios.
B38: Preparación del informe final de cierre del proyecto, consolidando resultados, cumplimiento de metas y medios de verificación.
B39: TOTAL PROYECTO | C39: =SUM(C4:C33) | D39: =SUM(D4:D33) | E39: =SUM(E4:E33) | F39: =SUM(F4:F33) | G39: =SUM(G4:G33) | H39: =SUM(H4:H33) | I39: =SUM(I4:I33) | J39: =+J4+J8+J12+J16+J20+J22+J23+J26+J30+J33 | K39: =SUM(C37:I37)-J37 | L39: =SUM(L4:L33) | M39: =SUM(M4:M33)
L40: =L37/J37 | M40: =M37/J37
B41: CERRADO
B42: Ítem / Descripción | C42: Ago 2026 | D42: Sep 2026 | E42: Oct 2026 | F42: Nov 2026 | G42: Dic 2026 | H42: Ene 2027 | I42: Feb 2027 | J42: TOTAL | L42: GORE | M42: FUNDACIÓN
A43: 1 | B43: Diagnóstico general y catastro básico de hogares en La Higuera | C43: 7000000 | D43: 0 | E43: 0 | F43: 0 | G43: 0 | H43: 0 | I43: 0 | J43: =SUM(C41:I41) | L43: =+J41
B44: Levantamiento y revisión de antecedentes territoriales, sociales y energéticos 90 km radio desde La Serena
B45: Revisión preliminar de sectores, localidades y hogares potencialmente beneficiarios del programa.
B46: Elaboración del informe de diagnóstico general y universo inicial de hogares a catastrar.
A47: 2 | B47: Catastro georeferenciado uno a uno de viviendas | C47: 0 | D47: 11000000 | E47: 0 | F47: 0 | G47: 0 | H47: 0 | I47: 0 | J47: =SUM(C45:I45) | L47: =+J45
B48: Planificación de rutas, sectores de visita y metodología de levantamiento georreferenciado.
B49: Aplicación de ficha de catastro vivienda a vivienda, incluyendo ubicación, condición habitacional y situación energética.
B50: Consolidación de base de datos georreferenciada, respaldo fotográfico y mapa de viviendas catastradas.
A51: 3 | B51: Verificación y sensibilización de usuarios catastrados. Incorporación de beneficiarios a programa de energía. | C51: 0 | D51: 0 | E51: 9000000 | F51: 0 | G51: 0 | H51: 0 | I51: 0 | J51: =SUM(C49:I49) | L51: =+J49
B52: Verificación en terreno de antecedentes levantados en el catastro y validación de cumplimiento de criterios de elegibilidad.
B53: Ejecución de jornadas de sensibilización sobre alcances del programa, condiciones de participación y responsabilidades del usuario.
B54: Elaboración de nómina final de beneficiarios e incorporación formal de usuarios al programa de instalación.
A55: 4 | B55: Capacitación de sistemas ERNC usuarios beneficiario. | C55: 0 | D55: 0 | E55: 9000000 | F55: 0 | G55: 0 | H55: 0 | I55: 0 | J55: =SUM(C53:I53) | L55: =+J53
B56: Diseño de contenidos de capacitación sobre funcionamiento básico, seguridad y cuidados de sistemas ERNC domiciliarios.
B57: Realización de talleres prácticos para usuarios beneficiarios sobre operación diaria del sistema.
B58: Evaluación de comprensión de usuarios y entrega de material de apoyo para uso y cuidado del sistema.
A59: 5 | B59: Implementacion del un modelo de mantenimiento a 10 años | C59: =SUM(C58:C59) | D59: =SUM(D58:D59) | E59: =SUM(E58:E59) | F59: =SUM(F58:F59) | G59: =SUM(G58:G59) | H59: =SUM(H58:H59) | I59: =SUM(I58:I59) | J59: =SUM(C57:I57)
B60: Reposición y disposición final de bateria e inversor por vida util | F60: 27000000 | J60: =SUM(C58:I58) | L60: =+J58
B61: Reposición de 10% componentes principales x deterioro a 10 años | I61: 9000000 | J61: =SUM(C59:I59) | M61: =+J59
A62: 6 | B62: Sistemas ERNC | C62: =SUM(C61:C63) | D62: =SUM(D61:D63) | E62: =SUM(E61:E63) | F62: =SUM(F61:F63) | G62: =SUM(G61:G63) | H62: =SUM(H61:H63) | I62: =SUM(I61:I63) | J62: =SUM(C60:I60)
B63: Adquisición de materiales, equipos y componentes principales de los sistemas ERNC domiciliarios. | C63: 40000000 | D63: 0 | E63: 0 | F63: 66000000 | G63: 26500000 | H63: 0 | I63: 0 | J63: =SUM(C61:I61) | M63: =+J61
B64: Gestión logística, almacenamiento, control de inventario y distribución de equipos hacia zonas de instalación. | C64: 4000000 | D64: 0 | E64: 0 | F64: 13000000 | G64: 3000000 | H64: 0 | I64: 0 | J64: =SUM(C62:I62) | M64: =+J62
B65: Internación, recepción técnica y revisión de conformidad de equipos y materiales requeridos para la implementación. | G65: 1500000 | H65: 0 | I65: 0 | J65: =SUM(C63:I63) | M65: =+J63
A66: 7 | B66: instalacion | C66: 2500000 | D66: 2500000 | E66: 19000000 | F66: 26500000 | G66: 14000000 | H66: 3000000 | I66: 0 | J66: =SUM(C64:I64) | L66: =+J64
B67: Logística y abastecimiento de herramientas y materiales en terreno para cada vivienda beneficiaria. | J67: =SUM(C65:I65) | L67: =+J65
B68: Coordinación e instalación de equipos ERNC domiciliarios, incluyendo montaje, conexiones y puesta en marcha operativa. | J68: =SUM(C66:I66) | L68: =+J66
B69: Tramitación, elaboración y entrega de documentación TE1. | H69: =150000*75 | J69: =SUM(C67:I67)
A70: 8 | B70: Formación y Asesoria a usuarios de electrodomésticos y uso. | C70: 0 | D70: 0 | E70: 0 | F70: 0 | G70: 10000000 | H70: 10000000 | I70: 0 | J70: =SUM(C68:I68) | L70: =+J68
B71: Asesoría a usuarios sobre uso eficiente de electrodomésticos, priorización de consumos y prevención de sobrecargas.
B72: Acompañamiento inicial post-instalación para resolver dudas de uso, operación segura y buenas prácticas de consumo.
A73: 9 | B73: Cierre de proyecto - informes de instalación | C73: 0 | D73: 0 | E73: 0 | F73: 0 | G73: 0 | H73: 0 | I73: 11000000 | J73: =SUM(C71:I71) | L73: =+J71
B74: Revisión y recopilación de actas de instalación, registros fotográficos, fichas técnicas y respaldos por vivienda.
B75: Elaboración de informes técnicos de instalación y puesta en marcha por sistema o grupo de beneficiarios.
B76: Preparación del informe final de cierre del proyecto, consolidando resultados, cumplimiento de metas y medios de verificación.
B77: TOTAL PROYECTO | C77: 52707373 | D77: 12615500 | E77: 36727100 | F77: 1.3182129e+08 | G77: 52562306 | H77: 13165800 | I77: 19983461 | J77: =+J41+J45+J49+J53+J57+J60+J64+J68+J71 | K77: 0 | L77: =SUM(L41:L71) | M77: =SUM(M41:M71)
L78: =L75/J75 | M78: =M75/J75
B81: Ítem / Descripción | C81: Ago 2026 | D81: Sep 2026 | E81: Oct 2026 | F81: Nov 2026 | G81: Dic 2026 | H81: Ene 2027 | I81: Feb 2027 | J81: TOTAL | L81: GORE | M81: FUNDACIÓN
A82: 1 | B82: Diagnóstico general y catastro básico de hogares en La Higuera | C82: =+C41 | D82: =+D41 | E82: =+E41 | F82: =+F41 | G82: =+G41 | H82: =+H41 | I82: =+I41 | J82: =SUM(C80:I80) | L82: =+J80
A83: 2 | B83: Catastro georeferenciado uno a uno de viviendas | C83: =+C45 | D83: =+D45 | E83: =+E45 | F83: =+F45 | G83: =+G45 | H83: =+H45 | I83: =+I45 | J83: =SUM(C81:I81) | L83: =+J81
A84: 3 | B84: Verificación y sensibilización de usuarios catastrados. Incorporación de beneficiarios a programa de energía. | C84: =+C49 | D84: =+D49 | E84: =+E49 | F84: =+F49 | G84: =+G49 | H84: =+H49 | I84: =+I49 | J84: =SUM(C82:I82) | L84: =+J82
A85: 4 | B85: Capacitación de sistemas ERNC usuarios beneficiario. | C85: =+C53 | D85: =+D53 | E85: =+E53 | F85: =+F53 | G85: =+G53 | H85: =+H53 | I85: =+I53 | J85: =SUM(C83:I83) | L85: =+J83
A86: 5 | B86: Implementacion del un modelo de mantenimiento a 10 años | C86: =+C57 | D86: =+D57 | E86: =+E57 | F86: =+F57 | G86: =+G57 | H86: =+H57 | I86: =+I57 | J86: =SUM(C84:I84)
A87: 6 | B87: Sistemas ERNC | C87: =+C60 | D87: =+D60 | E87: =+E60 | F87: =+F60 | G87: =+G60 | H87: =+H60 | I87: =+I60 | J87: =SUM(C85:I85)
A88: 7 | B88: instalacion | C88: 2500000 | D88: 2500000 | E88: 19000000 | F88: 26500000 | G88: 14000000 | H88: 3000000 | I88: 0 | J88: =SUM(C86:I86) | L88: =+J86
A89: 8 | B89: Formación y Asesoria a usuarios de electrodomésticos y uso. | C89: 0 | D89: 0 | E89: 0 | F89: 0 | G89: 10000000 | H89: 10000000 | I89: 0 | J89: =SUM(C87:I87) | L89: =+J87
A90: 9 | B90: Cierre de proyecto - informes de instalación | C90: 0 | D90: 0 | E90: 0 | F90: 0 | G90: 0 | H90: 0 | I90: 11000000 | J90: =SUM(C88:I88) | L90: =+J88
B91: TOTAL PROYECTO | C91: 52707373 | D91: 12615500 | E91: 36727100 | F91: 1.3182129e+08 | G91: 52562306 | H91: 13165800 | I91: 19983461 | J91: =+J80+J81+J82+J83+J84+J85+J86+J87+J88 | K91: 0 | L91: =SUM(L80:L88) | M91: =SUM(M80:M88)
L92: =L89/J89 | M92: =M89/J89

Sheet Valorización Componentes
A1: VALORIZACIÓN POR COMPONENTE — LUZ EN CASA · GORE COQUIMBO | Valores BRUTO con IVA
J2: =+J202
B3: Ítem / Descripción | C3: Ago 2026 | D3: Sep 2026 | E3: Oct 2026 | F3: Nov 2026 | G3: Dic 2026 | H3: Ene 2027 | I3: Feb 2027 | J3: TOTAL
A4: 1 | B4: Diagnóstico general y catastro básico de hogares en La Higuera | C4: =SUM(C5:C21) | D4: =SUM(D5:D21) | E4: =SUM(E5:E21) | F4: =SUM(F5:F21) | G4: =SUM(G5:G21) | H4: =SUM(H5:H21) | I4: =SUM(I5:I21) | J4: =SUM(C4:I4) | K4: RRCC | L4: 1+2+3
B5: Planilla Actual | C5: =+'Flujo Bruto'!O21
B6: Descarga estructura | C6: =+'Flujo Bruto'!O22
B7: Encargado territorial RRHH | C7: =+'Flujo Bruto'!O29
B8: Arriendo vehículo diario - RRCC | C8: =+'Flujo Bruto'!O34
B9: Vehiculo RRCC | C9: =+'Flujo Bruto'!O30
B10: Traslados de personal | C10: =+'Flujo Bruto'!O50
B11: Alojamiento | C11: =+'Flujo Bruto'!O51
B12: Alimentación | C12: =+'Flujo Bruto'!O52
B13: Combustible arriendo diario | C13: =+'Flujo Bruto'!O53
B14: Combustible arriendo mensual | C14: =+'Flujo Bruto'!O54
B15: Peajes | C15: =+'Flujo Bruto'!O55
B16: Compras de Equipos, EEPP, Otros | C16: =+'Flujo Bruto'!O64
B17: Mensajerias (Correo de Chile) | C17: =+'Flujo Bruto'!O65
B18: Impresión de manuales | C18: =+'Flujo Bruto'!O66
B19: Mantención y reparación de Vehículos | C19: =+'Flujo Bruto'!O67
B20: Otros varios | C20: =+'Flujo Bruto'!O68
A22: 2 | B22: Catastro georeferenciado uno a uno de viviendas | C22: =SUM(C23:C39) | D22: =SUM(D23:D39) | E22: =SUM(E23:E39) | F22: =SUM(F23:F39) | G22: =SUM(G23:G39) | H22: =SUM(H23:H39) | I22: =SUM(I23:I39) | J22: =SUM(C22:I22) | K22: RRCC | L22: 1+2+3
B23: Planilla Actual | D23: 2400000
B24: Descarga estructura
B25: Encargado territorial RRHH | D25: 900000
B26: Arriendo vehículo diario - RRCC | D26: =Supuestos!G37*15
B27: Vehiculo RRCC
B28: Traslados de personal
B29: Alojamiento | D29: 1500000
B30: Alimentación | D30: 1500000
B31: Combustible arriendo diario | D31: 1000000
B32: Combustible arriendo mensual
B33: Peajes | D33: 400000
B34: Compras de Equipos, EEPP, Otros | D34: 1200000
B35: Mensajerias (Correo de Chile)
B36: Impresión de manuales
B37: Mantención y reparación de Vehículos
B38: Otros varios
A40: 3 | B40: Verificación y sensibilización de usuarios catastrados. Incorporación de beneficiarios a programa de energía. | C40: =SUM(C41:C57) | D40: =SUM(D41:D57) | E40: =SUM(E41:E57) | F40: =SUM(F41:F57) | G40: =SUM(G41:G57) | H40: =SUM(H41:H57) | I40: =SUM(I41:I57) | J40: =SUM(C40:I40) | K40: RRCC | L40: 1+2+3
B41: Planilla Actual
B42: Descarga estructura | E42: 8000000
B43: Encargado territorial RRHH | E43: 900000
B44: Arriendo vehículo diario - RRCC
B45: Vehiculo RRCC
B46: Traslados de personal
B47: Alojamiento
B48: Alimentación
B49: Combustible arriendo diario
B50: Combustible arriendo mensual
B51: Peajes
B52: Compras de Equipos, EEPP, Otros
B53: Mensajerias (Correo de Chile)
B54: Impresión de manuales
B55: Mantención y reparación de Vehículos
B56: Otros varios
A59: 4 | B59: Capacitación de sistemas ERNC usuarios beneficiario. | C59: =SUM(C60:C76) | D59: =SUM(D60:D76) | E59: =SUM(E60:E76) | F59: =SUM(F60:F76) | G59: =SUM(G60:G76) | H59: =SUM(H60:H76) | I59: =SUM(I60:I76) | J59: =SUM(C59:I59) | K59: RRCC
B60: Planilla Actual | E60: ='Flujo Bruto'!Q$21
B61: Descarga estructura | E61: 3000000
B62: Encargado territorial RRHH
B63: Arriendo vehículo diario - RRCC
B64: Vehiculo RRCC
B65: Traslados de personal
B66: Alojamiento
B67: Alimentación
B68: Combustible arriendo diario
B69: Combustible arriendo mensual
B70: Peajes
B71: Compras de Equipos, EEPP, Otros
B72: Mensajerias (Correo de Chile)
B73: Impresión de manuales
... B75: Otros varios
A77: 5 | B77: Implementacion del un modelo de mantenimiento a 16 años | C77: =SUM(C78:C94) | D77: =SUM(D78:D94) | E77: =SUM(E78:E94) | F77: =SUM(F78:F94) | G77: =SUM(G78:G94) | H77: =SUM(H78:H94) | I77: =SUM(I78:I94) | J77: =SUM(C77:I77) | K77: RRCC
B78: Planilla Actual | F78: 1400000 | I78: =0.1*75*900000*(1+0.035)^8
B79: Descarga estructura | F79: =(28500/3)*75*12*3
B80: Encargado territorial RRHH
B81: Arriendo vehículo diario - RRCC
B82: Vehiculo RRCC
B83: Traslados de personal
B84: Alojamiento
B85: Alimentación
B86: Combustible arriendo diario
B87: Combustible arriendo mensual
B88: Peajes
B89: Compras de Equipos, EEPP, Otros
B90: Mensajerias (Correo de Chile)
B91: Impresión de manuales
... B93: Otros varios
A95: 6 | B95: Compra | C95: =SUM(C96:C105) | D95: =SUM(D96:D105) | E95: =SUM(E96:E105) | F95: =SUM(F96:F105) | G95: =SUM(G96:G105) | H95: =SUM(H96:H105) | I95: =SUM(I96:I105) | J95: =SUM(C95:I95)
B96: Sistemas AC | C96: =+'Flujo Bruto'!O6 | D96: =+'Flujo Bruto'!P6 | E96: =+'Flujo Bruto'!Q6 | F96: =+'Flujo Bruto'!R6 | G96: =+'Flujo Bruto'!S6 | H96: =+'Flujo Bruto'!V6 | I96: =+'Flujo Bruto'!W6 | J96: =SUM(C96:I96)
B97: Paneles | C97: =+'Flujo Bruto'!O7 | D97: =+'Flujo Bruto'!P7 | E97: =+'Flujo Bruto'!Q7 | F97: =+'Flujo Bruto'!R7 | G97: =+'Flujo Bruto'!S7 | H97: =+'Flujo Bruto'!V7 | I97: =+'Flujo Bruto'!W7 | J97: =SUM(C97:I97)
B98: Lamparas | C98: =+'Flujo Bruto'!O8 | D98: =+'Flujo Bruto'!P8 | E98: =+'Flujo Bruto'!Q8 | F98: =+'Flujo Bruto'!R8 | G98: =+'Flujo Bruto'!S8 | H98: =+'Flujo Bruto'!V8 | I98: =+'Flujo Bruto'!W8 | J98: =SUM(C98:I98)
B99: Hardware Monitoreo | C99: =+'Flujo Bruto'!O9 | D99: =+'Flujo Bruto'!P9 | E99: =+'Flujo Bruto'!Q9 | F99: =+'Flujo Bruto'!R9 | G99: =+'Flujo Bruto'!S9 | H99: =+'Flujo Bruto'!V9 | I99: =+'Flujo Bruto'!W9 | J99: =SUM(C99:I99)
B100: Software Monitoreo | C100: =+'Flujo Bruto'!O10 | D100: =+'Flujo Bruto'!P10 | E100: =+'Flujo Bruto'!Q10 | F100: =+'Flujo Bruto'!R10 | G100: =+'Flujo Bruto'!S10 | H100: =+'Flujo Bruto'!V10 | I100: =+'Flujo Bruto'!W10 | J100: =SUM(C100:I100)
B102: Flete | C102: =+'Flujo Bruto'!O12 | D102: =+'Flujo Bruto'!P12 | E102: =+'Flujo Bruto'!Q12 | F102: =+'Flujo Bruto'!R12 | G102: =+'Flujo Bruto'!S12 | H102: =+'Flujo Bruto'!V12 | I102: =+'Flujo Bruto'!W12 | J102: =SUM(C102:I102)
B103: Transporte DESCONSOLIDADO | C103: =+'Flujo Bruto'!O13 | D103: =+'Flujo Bruto'!P13 | E103: =+'Flujo Bruto'!Q13 | F103: =+'Flujo Bruto'!R13 | G103: =+'Flujo Bruto'!S13 | H103: =+'Flujo Bruto'!V13 | I103: =+'Flujo Bruto'!W13 | J103: =SUM(C103:I103)
B104: Grúa en Origen | C104: =+'Flujo Bruto'!O14 | D104: =+'Flujo Bruto'!P14 | E104: =+'Flujo Bruto'!Q14 | F104: =+'Flujo Bruto'!R14 | G104: =+'Flujo Bruto'!S14 | H104: =+'Flujo Bruto'!V14 | I104: =+'Flujo Bruto'!W14 | J104: =SUM(C104:I104)
B105: Grúa en Punto Destino (6 Horas) | C105: =+'Flujo Bruto'!O15 | D105: =+'Flujo Bruto'!P15 | E105: =+'Flujo Bruto'!Q15 | F105: =+'Flujo Bruto'!R15 | G105: =+'Flujo Bruto'!S15 | H105: =+'Flujo Bruto'!V15 | I105: =+'Flujo Bruto'!W15 | J105: =SUM(C105:I105)
A107: 6 | B107: Instalación | C107: =SUM(C108:C130) | D107: =SUM(D111:D130) | E107: =SUM(E111:E130) | F107: =SUM(F111:F130) | G107: =SUM(G111:G130) | H107: =SUM(H111:H130) | I107: =SUM(I111:I130) | J107: =SUM(C107:I107) | K107: Técnico | L107: Desagregar 1 para que cuadre con el 50%
B108: Planilla Actual
B109: Descarga estructura
B110: Repuestos | C110: =+'Flujo Bruto'!O11 | D110: =+'Flujo Bruto'!P11 | E110: =+'Flujo Bruto'!Q11 | F110: =+'Flujo Bruto'!R11 | G110: =+'Flujo Bruto'!S11 | H110: =+'Flujo Bruto'!V11 | I110: =+'Flujo Bruto'!W11 | J110: =SUM(C110:I110)
...

Sheet Carátula
A1: CARÁTULA — LUZ EN CASA · GORE COQUIMBO
A3: LUZ EN CASA · GORE COQUIMBO
A4: Fundación acciona.org · Financiamiento FNDR · 75 sistemas FV domiciliarios
B6: Proyecto | D6: Luz en Casa — Electrificación rural fotovoltaica
B7: Financiador | D7: Gobierno Regional de Coquimbo (GORE) — FNDR Subt. 33
B8: Ejecutor | D8: Fundación acciona.org
B9: Responsable | D9: Agustín Delgado Godoy — Project Manager
B10: N° equipos | D10: 75 sistemas SHS AC (Zimpertec GmbH, Alemania)
B11: Período ejecución | D11: Julio 2026 – Febrero 2027 (instalaciones)
B12: Cierre administrativo | D12: Junio 2027
B13: Aporte GORE | D13: $170.000.000 CLP (tope convenio)
B14: Total proyecto NETO | D14: $278.551.000 CLP
B15: Total proyecto BRUTO | D15: $338.684.840 CLP (con IVA 19%)
A18: ÍNDICE DE PESTAÑAS — Haz clic en el nombre para ir directamente
B20: Pestaña (clic para ir) | C20: Categoría | D20: Descripción y contenido | E20: Notas / Responsable
B21: → Supuestos | C21: Modelo financiero | D21: Parámetros base del modelo: cantidad de equipos (75), tasa de cambio USD/CLP, precios unitarios, factores de distribución mensual (0.3 / 0.5 / 0.2). Celda de control central del modelo. | E21: Edición: Agustín D.
B22: → Flujo Neto | C22: Modelo financiero | D22: Presupuesto mensual en valores NETO (sin IVA). 10 grupos de gasto (ítems 1–10), distribución mes a mes Ago 2026–Feb 2027. Total NETO: $278.551.000. Fuente de Analítica y General GORE. | E22: Solo lectura — fórmulas vinculadas a Supuestos
B23: → Flujo Bruto | C23: Modelo financiero | D23: Presupuesto mensual en valores BRUTO (con IVA 19%). Misma estructura que Flujo Neto. Total BRUTO: $338.684.840. Fuente de Cashflow y General GORE. | E23: Solo lectura — fórmulas vinculadas a Supuestos
B24: → General GORE | C24: Modelo financiero | D24: Resumen ejecutivo del proyecto para presentación GORE. Cuadro de fuentes y usos, aporte FNDR vs Fundación, total por partida presupuestaria. | E24: Agustín D. / GORE
B25: → Carta Gantt | C25: Planificación | D25: Cronograma de 9 fases (jul 2026–jun 2027): gestión, compra, importación, contratación, materiales, logística, instalación (75 uds en 3 lotes), rendición y cierre. 42 actividades y 5 hitos. | E25: v1.5 — Actualizar al firmar convenio
B26: → Antecedentes Programa | C26: Contexto | D26: Descripción del programa Luz en Casa: historia, piloto 2021, expansión regional, forma de trabajo, descripción técnica de equipos SHS AC, alcance de instalación y proceso formal TE-1. | E26: Referencia — no editar
B27: → Planilla SISREC | C27: Rendición | D27: Plantilla mensual de rendición electrónica (SISREC). Una fila por documento (factura / boleta / BH). Campos: N° doc, RUT proveedor, glosa, analítica, tipo doc, montos NETO/IVA/BRUTO, estado. | E27: Apoyo Financiero — completar mensualmente
B28: → Rendición GORE | C28: Rendición | D28: Formato de informe de rendición hacia GORE Coquimbo. Carta conductora, conciliación bancaria, cuadro de gastos acumulados vs cuota. | E28: Apoyo Financiero / Agustín D.
B29: → Tabla Calculo Sueldo | C29: Auxiliar | D29: Tabla auxiliar de costo empresa para personal en planilla. Cotizaciones previsionales, AFP, salud, seguro cesantía. Alimenta ítem 3.1 Planilla Actual del Flujo Neto. | E29: Referencia — no editar directamente
B30: → Guía Maestra | C30: Diagnóstico | D30: Mapa completo del modelo: pestañas, roles, editabilidad, dependencias. Tabla ítem a código analítica a cashflow. Control de totales y reglas de edición. | E30: Lectura obligatoria antes de editar
B31: → Diagnóstico Vínculos | C31: Diagnóstico | D31: Auditoría de vínculos rotos entre pestañas. Lista de celdas con errores, causa y acción correctiva. | E31: Actualizar en cada versión
... B33: → Cashflow | C33: Auxiliar | D33: Cashflow mensual del proyecto. Cobros y pagos por categoría. Vinculado a Flujo Bruto. Columna de desviación inactiva hasta ingresar valores de Budget. | E33: Sistema ACCIONA — no editar
A36: CONTROL DE REVISIONES
B38: Versión | C38: Fecha | D38: Autor | E38: Descripción del cambio
B39: v1.0 | C39: 17/02/2026 | D39: Agustín D. | E39: Versión inicial. Supuestos, Flujo Neto, Flujo Bruto, General GORE. 60 equipos. TC USD 950.
B40: v1.1 | C40: Feb 2026 | D40: Agustín D. | E40: Incorporación Analítica y Cashflow del sistema ACCIONA. Vínculos con Flujo Bruto.
B41: v1.2 | C41: Mar 2026 | D41: Agustín D. | E41: Tabla Calculo Sueldo. Ajuste planilla personal. Revisión ítems 3. y 4.
B42: v1.3 | C42: Abr 2026 | D42: Agustín D. | E42: Incorporación Planilla SISREC, Rendición GORE, Diagnóstico Vínculos, Guía Maestra.
B43: v1.4 | C43: 13/05/2026 | D43: Agustín D. | E43: Ajuste a 75 equipos. TC USD 1.000. Actualización Flujo Neto/Bruto. Carta Gantt ene 2026–jun 2027 (referencial).
B44: v1.5 | C44: 13/05/2026 | D44: Agustín D. | E44: Carta Gantt reconstruida: inicio jul 2026, fin instalaciones feb 2027, 9 fases, 42 actividades, 5 hitos.
B45: v1.6 | C45: 14/05/2026 | D45: Agustín D. | E45: Carátula con índice de pestañas, hyperlinks, control de revisiones y registro de mejoras.
B46: v2.0 | C46: 14/05/2026 | D46: Agustín D. | E46: Carátula rediseñada: hyperlinks corregidos, Total BRUTO agregado, RUT y nombre de archivo eliminados, versión migrada a 2.0.
B47: v2.1 | C47: __/__/____ | D47: ____________ | E47: Completar al publicar próxima versión
A50: REGISTRO DE MEJORAS PENDIENTES
B52: ID | C52: Prioridad | D52: Descripción de la mejora | E52: Estado
B53: M-01 | C53: CRÍTICA | D53: Analítica fila 21 (25.1 Alquiler vehículos): agregar referencia a FN fila 32 (5.2 Vehículo RRCC) en las 24 columnas de mes. Impacto: $5.600.000 NETO no reflejado en Analítica. | E53: Pendiente — corrección manual Excel
B54: M-02 | C54: ALTA | D54: Ingresar valores Budget en Analítica col AH y Cashflow col AD para activar análisis desviación Real vs Budget. Elimina 25 errores de división. | E54: Pendiente — requiere datos de convenio
B55: M-03 | C55: ALTA | D55: Reemplazar errores de metadatos en Analítica H1-H2 y Cashflow C1-C3 por texto fijo: PAIS=CL, DATO=18 Luz en Casa IV, CTRO COSTE=APR Propio. | E55: Pendiente
B56: M-04 | C56: ALTA | D56: Confirmar valor final convenio GORE (75 equipos) y validar coherencia entre Supuestos E5 y General GORE C14. | E56: Pendiente — sujeto a firma convenio
B57: M-05 | C57: MEDIA | D57: Ajustar columna inicio Carta Gantt con fecha real de suscripción del convenio GORE. Actualmente asume julio 2026. | E57: Pendiente — sujeto a firma convenio
B58: M-06 | C58: MEDIA | D58: Agregar dropdown de validación en Planilla SISREC: Tipo Documento y Estado SISREC (Pendiente / Ingresado / Aprobado / Observado). | E58: Pendiente
B59: M-07 | C59: MEDIA | D59: Revisar ítems 4.6 Encargado Territorial y 4.7 Apoyo Financiero en Supuestos: tienen valor unitario pero cantidad 0 en Flujo Neto. Confirmar activación. | E59: Pendiente — consultar con Rodrigo S.
B60: M-08 | C60: MEDIA | D60: Ítem 3.2 Descarga Estructura ($2.000.000): aparece en Supuestos sin distribución mensual en Flujo Neto. Definir mes de imputación. | E60: Pendiente
B61: M-09 | C61: BAJA | D61: Estandarizar colores de pestañas por categoría en futuras versiones. | E61: Aplicado en v2.0 — mantener en actualizaciones
B62: M-10 | C62: BAJA | D62: Agregar fila de total acumulado en Planilla SISREC con porcentaje de avance sobre monto GORE y semáforo (verde menor a 80% / amarillo 80-95% / rojo mayor a 95%). | E62: Pendiente
A64: Fundación acciona.org · Proyecto Luz en Casa GORE Coquimbo · Documento de uso interno · v2.0 · 2026-05-14

Sheet General GORE
A1: RESUMEN GENERAL — PROYECTO LUZ EN CASA · GORE COQUIMBO
A2: Fundación acciona.org (Grupo ACCIONA) · Financiamiento FNDR Subtítulo 33 · Región de Coquimbo
A3: 1. EQUIPOS SUMINISTRADOS — ZIMPERTEC GmbH & Co. KG (Alemania)
B4: Componente | C4: Modelo | D4: Especificación principal | E4: Qty por kit | F4: Total proyecto (60 kits) | G4: Observaciones
B5: Sistema Solar Domiciliario AC (SHS AC) | C5: AC-LS-AC25.6V/50Ah/ 1.28kWh/220V/50Hz/ 0.9kW-HP/Termcon-a | D5: Inversor 900W · Batería LFP 25.6V/50Ah/1.28kWh · Controlador PWM 40A · Salida DC 24V/10A · Gabinete gris acciona.org | E5: 1 | F5: 60 | G5: Gabinete especial para acciona.org · optimizado para cargas AC básicas y picos de motor
B6: Panel solar fotovoltaico | C6: SP-500-66M-S4-0.35 | D6: 500 Wp · Monocristalino · 66 celdas en serie · Cableado S4 terminal 0.35 m | E6: 2 | F6: 120 | G6: 2 paneles por kit · orientación optimizada en cubierta
B7: Luminaria LED | C7: SFL-12-24/05CW | D7: 5W · 12/24 VDC · Cool White · Cert. CE y ROHS | E7: 3 | F7: 180 | G7: 3 puntos iluminación DC por vivienda · máx. 20 m cableado interior
B8: Alcance instalación por vivienda: 3 luminarias LED DC (12/24V) + 1 toma corriente AC (220V/50Hz) · máx 20 m cableado · TE-1 voluntaria SEC · Acta recepción conforme
A9: 2. SUPUESTOS FINANCIEROS — COSTO UNITARIO POR INSTALACIÓN
B10: Concepto | C10: Valor NETO (CLP) | D10: Valor BRUTO (CLP) | E10: Referencia Supuestos | F10: Notas
B11: Costo equipos + traslados asociados (GORE) | D11: =Supuestos!F74 | E11: Supuestos!F71 | F11: Sistemas AC + Paneles + Lámparas + Flete + Transp.descons. + Grúas
B12: Costo personal, logística, materiales, vehículos, viajes | C12: =Supuestos!I4 | D12: =Supuestos!F75 | E12: Supuestos!F72 | F12: Calculado como: K5 (unitario resto de ítems)
B13: TOTAL COSTO UNITARIO (NETO) | C13: ='Flujo Neto'!AJ69/'General GORE'!C27 | E13: Supuestos!I5 | F13: Suma unitaria NETO
B14: TOTAL COSTO UNITARIO (BRUTO) | D14: =C20/'General GORE'!C27 | E14: Flujo Bruto!AJ68 | F14: Unitario BRUTO = total proyecto / 60 equipos
A15: 3. VALIDADOR FINANCIERO — TOPE MÁXIMO GORE $170.000.000 (50% del proyecto)
B16: Concepto | C16: Valor CLP | D16: % del Total Bruto | E16: Estado | F16: Referencia / Fórmula
B17: Aporte GORE (tope máximo reembolsable) | C17: 170000000 | D17: =C17/'Flujo Bruto'!AJ69 | E17: =IF(C17<='Flujo Bruto'!AJ69,"✓ GORE ≤ Total proyecto","⚠ GORE > Total proyecto") | F17: Hardcoded · ref. Rodrigo Soto
B18: Aporte Fundación acciona.org (50% complementario) | C18: 170000000 | D18: =C18/'Flujo Bruto'!AJ69 | E18: =IF(C17=C18,"✓ Aporte simétrico","⚠ Aportes asimétricos") | F18: Hardcoded · $170MM = $170MM
B19: Total comprometido (GORE + Fundación) | C19: =C17+C18 | D19: =C19/C19 | E19: ✓ $340.000.000 total | F19: C17 + C18
B20: Costo total real del proyecto (Flujo Bruto) | C20: ='Flujo Bruto'!AJ69 | D20: ='Flujo Bruto'!AJ69/C19 | E20: =IF('Flujo Bruto'!AJ69<=C19,"✓ Dentro del tope","⚠ EXCEDE tope $340MM") | F20: Flujo Bruto!AJ66 (total 60 equipos) | G20: =+C20-C19
B21: Costo unitario real BRUTO (por instalación) | C21: =D14 | D21: =C21/(C19/C27) | E21: =IF(C21<=C19/60,"✓ Dentro del tope unit.","⚠ Supera tope unitario")
B22: Costo equipos+traslados GORE (K3 × 60 equipos) | C22: =Supuestos!F74*Supuestos!E2 | D22: =C22/'Flujo Bruto'!AJ69 | E22: =IF(C22<=C17,"✓ Equip. dentro aporte GORE","⚠ Equip. supera aporte") | F22: K3 × E2 (Supuestos)
B23: Saldo GORE disponible para otros ítems (GORE - equip.) | C23: =C17-C22 | D23: =C23/C17 | E23: =IF(C23>=0,"✓ GORE cubre equipos","⚠ GORE insuficiente para equipos") | F23: C17 - C22
A24: ⚠ VALIDACIÓN: Los valores en amarillo se calculan desde Flujo Bruto (dinámicos). Los valores en verde ya cumplen la condición. Si algún estado dice "⚠", revisar Supuestos antes de presentar al GORE.
A25: 4. PARÁMETROS CLAVE DEL PROYECTO
B26: Parámetro | C26: Valor actual | D26: Fuente | E26: Editar en | F26: Notas
B27: N° equipos a comprar | C27: =Supuestos!E2 | D27: Supuestos!E2 | E27: Supuestos!E2 | F27: Cantidad de kits FV completos
B28: Tasa de cambio USD/CLP | C28: =Supuestos!E3 | D28: Supuestos!E3 | E28: Supuestos!E3 | F28: Solo para referencia en Supuestos
B29: N° cuadrillas de instalación | C29: =Supuestos!E4 | D29: Supuestos!E4 | E29: Supuestos!E4 | F29: Afecta herramientas (ítem 2.3)
B30: Costo unitario equipos GORE (K3) | C30: =Supuestos!F74 | D30: Supuestos!K3 | E30: ⛔ Calculado | F30: Fórmula: K4 + (K43+K46+K47)/E2
B31: Tiempo importación (meses) | C31: 4-5 meses | D31: Minuta Proyecto | E31: —
B32: Modelo pago usuarios | C32: Caja Vecina BancoEstado | D32: Minuta Proyecto | E32: — | F32: ~30.000 sucursales acceso rural
B33: Cantidad de equipos financiables (C11/C12) | C33: =C17/Supuestos!F74 | D33: Calculado | E33: — | F33: GORE $170MM ÷ K3 unitario
B34: Cantidad de equipos finales | C34: 75 | D34: Supuestos | E34: — | F34: [VERIFICAR] ajustar según convenio
B35: Costo total compra (75 × K3) | C35: =75*Supuestos!F74 | D35: Calculado | E35: — | F35: 75 equipos × K3 unitario
A37: ℹ Para antecedentes y contexto del programa, ver pestaña → Antecedentes Programa

Sheet AUMENTO MONTO
A1: AUMENTO DE MONTO — Fuente Oficial · Actualizado 5 de Junio 2026
A2: Luz en Casa · GORE Coquimbo · Fundación acciona.org
B4: MONTO | C4: Unidad
A5: TOTAL COSTO UNITARIO (BRUTO) | B5: 4625776.3 | C5: CLP
A6: CANTIDAD INSTALACIONES | B6: 75 | C6: UN
A7: COSTO PROYECTO | B7: =PRODUCT(B3:B4) | C7: CLP
A9: TOTAL COSTO UNITARIO (BRUTO) | B9: 4267000 | C9: CLP | D9: <----- | E9: VALOR AJUSTADO EN PESTAÑA GORE
A10: CANTIDAD INSTALACIONES | B10: 75 | C10: UN
A11: COSTO PROYECTO | B11: =PRODUCT(B7:B8) | C11: CLP
A13: NUEVA PROPUESTA
A14: GORE | B14: 280000000 | C14: CLP
A15: FUNDACIÓN ACCIONA | B15: 280000000 | C15: CLP
A16: TOTAL | B16: =SUM(B12:B13) | C16: CLP
A18: TOTAL COSTO UNITARIO (BRUTO) | B18: =+B7 | C18: CLP
A19: Cantidad Instalaciones | B19: =B14/B16 | C19: UN
A21: Cantidad Extra | B21: =B8-B17

Sheet Flujo Bruto
A1: FLUJO BRUTO (PRECIOS BRUTO CON IVA) — LUZ EN CASA · GORE COQUIMBO
D4: PRECIOS BRUTO | P4: Voluntariado | Q4: Voluntariado | R4: Voluntariado
B5: Forma pago | C5: Nivel | D5: Item | H5: 46023 | I5: 46054 | J5: 46082 | K5: 46113 | L5: 46143 | M5: 46174 | N5: 46204 | O5: 46235 | P5: 46266 | Q5: 46296 | R5: 46327 | S5: 46357 | T5: 2026 | V5: 46388 | W5: 46419 | X5: 46447 | Y5: 46478 | Z5: 46508 | AA5: 46539 | AB5: 46569 | AC5: 46600 | AD5: 46631 | AE5: 46661 | AF5: 46692 | AG5: 46722 | AH5: 2026 | AJ5: TOTAL
C6: 1 | D6: Compras activables ZIMPERTEC | E6: =+Supuestos!E8 | F6: =+F76 | H6: =+SUM(H6:H15) | I6: =+SUM(I6:I15) | J6: =+SUM(J6:J15) | K6: =+SUM(K6:K15) | L6: =+SUM(L6:L15) | M6: =+SUM(M6:M15) | N6: =+SUM(N6:N15) | O6: =+SUM(O6:O15) | ... S6: =+SUM(S6:S15) | T6: =SUM(H5:S5) | V6: =+SUM(V6:V15) | W6: =+SUM(W6:W15) | X6: =+SUM(X6:X15) | Y6: =+SUM(Y6:Y15) | Z6: =+SUM(Z6:Z15) | AA6: =+SUM(AA6:AA15) | AB6: =+SUM(AB6:AB15) | AC6: =+SUM(AC6:AC15) | ... AG6: =+SUM(AG6:AG15) | AH6: =SUM(V5:AG5) | AJ6: =+AH5+T5
B7: Factura | C7: 1.1 | D7: Sistemas AC | E7: =+Supuestos!G9 | F7: =+F77 | H7: =+$E6*H77 | I7: =+$E6*I77 | J7: =+$E6*J77 | K7: =+$E6*K77 | L7: =+$E6*L77 | M7: =+$E6*M77 | N7: =+$E6*N77 | O7: =+$E6*O77 | ... S7: =+$E6*S77 | T7: =SUM(H6:S6) | V7: =+$E6*V77 | W7: =+$E6*W77 | X7: =+$E6*X77 | Y7: =+$E6*Y77 | Z7: =+$E6*Z77 | AA7: =+$E6*AA77 | AB7: =+$E6*AB77 | AC7: =+$E6*AC77 | ... AG7: =+$E6*AG77 | AH7: =SUM(V6:AG6) | AJ7: =+AH6+T6
B8: Factura | C8: 1.2 | D8: Paneles | E8: =+Supuestos!G10 | F8: =+F78 | H8: =+$E7*H78 | I8: =+$E7*I78 | J8: =+$E7*J78 | K8: =+$E7*K78 | L8: =+$E7*L78 | M8: =+$E7*M78 | N8: =+$E7*N78 | O8: =+$E7*O78 | ... S8: =+$E7*S78 | T8: =SUM(H7:S7) | V8: =+$E7*V78 | W8: =+$E7*W78 | X8: =+$E7*X78 | Y8: =+$E7*Y78 | Z8: =+$E7*Z78 | AA8: =+$E7*AA78 | AB8: =+$E7*AB78 | AC8: =+$E7*AC78 | ... AG8: =+$E7*AG78 | AH8: =SUM(V7:AG7) | AJ8: =+AH7+T7
B9: Factura | C9: 1.3 | D9: Lamparas | E9: =+Supuestos!G11 | F9: =+F79 | H9: =+$E8*H79 | I9: =+$E8*I79 | J9: =+$E8*J79 | K9: =+$E8*K79 | L9: =+$E8*L79 | M9: =+$E8*M79 | N9: =+$E8*N79 | O9: =+$E8*O79 | ... S9: =+$E8*S79 | T9: =SUM(H8:S8) | V9: =+$E8*V79 | W9: =+$E8*W79 | X9: =+$E8*X79 | Y9: =+$E8*Y79 | Z9: =+$E8*Z79 | AA9: =+$E8*AA79 | AB9: =+$E8*AB79 | AC9: =+$E8*AC79 | ... AG9: =+$E8*AG79 | AH9: =SUM(V8:AG8) | AJ9: =+AH8+T8
B10: Factura | C10: 1.4 | D10: Hardware Monitoreo | E10: =+Supuestos!G12 | F10: =+F80 | H10: =+$E9*H80 | I10: =+$E9*I80 | J10: =+$E9*J80 | K10: =+$E9*K80 | L10: =+$E9*L80 | M10: =+$E9*M80 | N10: =+$E9*N80 | O10: =+$E9*O80 | ... S10: =+$E9*S80 | T10: =SUM(H9:S9) | V10: =+$E9*V80 | W10: =+$E9*W80 | X10: =+$E9*X80 | Y10: =+$E9*Y80 | Z10: =+$E9*Z80 | AA10: =+$E9*AA80 | AB10: =+$E9*AB80 | AC10: =+$E9*AC80 | ... AG10: =+$E9*AG80 | AH10: =SUM(V9:AG9) | AJ10: =+AH9+T9
B11: Factura | C11: 1.5 | D11: Software Monitoreo | E11: =+Supuestos!G13 | F11: =+F81 | H11: =+$E10*H81 | I11: =+$E10*I81 | J11: =+$E10*J81 | K11: =+$E10*K81 | L11: =+$E10*L81 | M11: =+$E10*M81 | N11: =+$E10*N81 | O11: =+$E10*O81 | ... S11: =+$E10*S81 | V11: =+$E10*V81 | W11: =+$E10*W81 | X11: =+$E10*X81 | Y11: =+$E10*Y81 | Z11: =+$E10*Z81 | AA11: =+$E10*AA81 | AB11: =+$E10*AB81 | AC11: =+$E10*AC81 | ... AG11: =+$E10*AG81 | AJ11: =+AH10+T10
B12: Factura | C12: 1.6 | D12: Repuestos | E12: =+Supuestos!G14 | F12: =+F82 | H12: =+$E11*H82 | I12: =+$E11*I82 | J12: =+$E11*J82 | K12: =+$E11*K82 | L12: =+$E11*L82 | M12: =+$E11*M82 | N12: =+$E11*N82 | O12: =+$E11*O82 | ... S12: =+$E11*S82 | T12: =SUM(H11:S11) | V12: =+$E11*V82 | W12: =+$E11*W82 | X12: =+$E11*X82 | Y12: =+$E11*Y82 | Z12: =+$E11*Z82 | AA12: =+$E11*AA82 | AB12: =+$E11*AB82 | AC12: =+$E11*AC82 | ... AG12: =+$E11*AG82 | AH12: =SUM(V11:AG11) | AJ12: =+AH11+T11
B13: Factura | C13: 1.7 | D13: Flete | E13: =+Supuestos!G15 | F13: =+F83 | H13: =+$E12*H83 | I13: =+$E12*I83 | J13: =+$E12*J83 | K13: =+$E12*K83 | L13: =+$E12*L83 | M13: =+$E12*M83 | N13: =+$E12*N83 | O13: =+$E12*O83 | ... S13: =+$E12*S83 | T13: =SUM(H12:S12) | V13: =+$E12*V83 | W13: =+$E12*W83 | X13: =+$E12*X83 | Y13: =+$E12*Y83 | Z13: =+$E12*Z83 | AA13: =+$E12*AA83 | AB13: =+$E12*AB83 | AC13: =+$E12*AC83 | ... AG13: =+$E12*AG83 | AH13: =SUM(V12:AG12) | AJ13: =+AH12+T12
B14: Factura | C14: 7.2 | D14: Transporte DESCONSOLIDADO | E14: =+Supuestos!G16 | F14: =+F84 | H14: =+$E13*H84 | I14: =+$E13*I84 | J14: =+$E13*J84 | K14: =+$E13*K84 | L14: =+$E13*L84 | M14: =+$E13*M84 | N14: =+$E13*N84 | O14: =+$E13*O84 | ... S14: =+$E13*S84 | T14: =SUM(H13:S13) | V14: =+$E13*V84 | W14: =+$E13*W84 | X14: =+$E13*X84 | Y14: =+$E13*Y84 | Z14: =+$E13*Z84 | AA14: =+$E13*AA84 | AB14: =+$E13*AB84 | AC14: =+$E13*AC84 | ... AG14: =+$E13*AG84 | AH14: =SUM(V13:AG13) | AJ14: =+AH13+T13
B15: Factura | C15: 7.5 | D15: Grúa en Origen | E15: =+Supuestos!G17 | F15: =+F85 | H15: =+$E14*H85 | I15: =+$E14*I85 | J15: =+$E14*J85 | K15: =+$E14*K85 | L15: =+$E14*L85 | M15: =+$E14*M85 | N15: =+$E14*N85 | O15: =+$E14*O85 | ... S15: =+$E14*S85 | T15: =SUM(H14:S14) | V15: =+$E14*V85 | W15: =+$E14*W85 | X15: =+$E14*X85 | Y15: =+$E14*Y85 | Z15: =+$E14*Z85 | AA15: =+$E14*AA85 | AB15: =+$E14*AB85 | AC15: =+$E14*AC85 | ... AG15: =+$E14*AG85 | AH15: =SUM(V14:AG14) | AJ15: =+AH14+T14
B16: Factura | C16: 7.6 | D16: Grúa en Punto Destino (6 Horas) | E16: =+Supuestos!G18 | F16: =+F86 | H16: =+$E15*H86 | I16: =+$E15*I86 | J16: =+$E15*J86 | K16: =+$E15*K86 | L16: =+$E15*L86 | M16: =+$E15*M86 | N16: =+$E15*N86 | O16: =+$E15*O86 | ... S16: =+$E15*S86 | T16: =SUM(H15:S15) | V16: =+$E15*V86 | W16: =+$E15*W86 | X16: =+$E15*X86 | Y16: =+$E15*Y86 | Z16: =+$E15*Z86 | AA16: =+$E15*AA86 | AB16: =+$E15*AB86 | AC16: =+$E15*AC86 | ... AG16: =+$E15*AG86 | AH16: =SUM(V15:AG15) | AJ16: =+AH15+T15
C17: 2 | D17: Insumos Instalación | E17: =+Supuestos!E19 | F17: =+F87 | H17: =+SUM(H17:H19) | I17: =+SUM(I17:I19) | J17: =+SUM(J17:J19) | K17: =+SUM(K17:K19) | L17: =+SUM(L17:L19) | M17: =+SUM(M17:M19) | N17: =+SUM(N17:N19) | O17: =+SUM(O17:O19) | ... S17: =+SUM(S17:S19) | T17: =SUM(H16:S16) | V17: =+SUM(V17:V19) | W17: =+SUM(W17:W19) | X17: =+SUM(X17:X19) | Y17: =+SUM(Y17:Y19) | Z17: =+SUM(Z17:Z19) | AA17: =+SUM(AA17:AA19) | AB17: =+SUM(AB17:AB19) | AC17: =+SUM(AC17:AC19) | ... AG17: =+SUM(AG17:AG19) | AH17: =SUM(V16:AG16) | AJ17: =+AH16+T16
B18: Factura | C18: 2.1 | D18: Estructura | E18: =+Supuestos!G20 | F18: =+F88 | H18: =+$E17*H88 | I18: =+$E17*I88 | J18: =+$E17*J88 | K18: =+$E17*K88 | L18: =+$E17*L88 | M18: =+$E17*M88 | N18: =+$E17*N88 | O18: =+$E17*O88 | ... S18: =+$E17*S88 | T18: =SUM(H17:S17) | V18: =+$E17*V88 | W18: =+$E17*W88 | X18: =+$E17*X88 | Y18: =+$E17*Y88 | Z18: =+$E17*Z88 | AA18: =+$E17*AA88 | AB18: =+$E17*AB88 | AC18: =+$E17*AC88 | ... AG18: =+$E17*AG88 | AH18: =SUM(V17:AG17) | AJ18: =+AH17+T17
B19: Factura o Boleta | C19: 2.2 | D19: Materiales instalación | E19: =+Supuestos!G21 | F19: =+F89 | H19: =+$E18*H89 | I19: =+$E18*I89 | J19: =+$E18*J89 | K19: =+$E18*K89 | L19: =+$E18*L89 | M19: =+$E18*M89 | N19: =+$E18*N89 | O19: =+$E18*O89 | ... S19: =+$E18*S89 | T19: =SUM(H18:S18) | V19: =+$E18*V89 | W19: =+$E18*W89 | X19: =+$E18*X89 | Y19: =+$E18*Y89 | Z19: =+$E18*Z89 | AA19: =+$E18*AA89 | AB19: =+$E18*AB89 | AC19: =+$E18*AC89 | ... AG19: =+$E18*AG89 | AH19: =SUM(V18:AG18) | AJ19: =+AH18+T18
B20: Factura o Boleta | C20: 2.3 | D20: Herramientas | E20: =+Supuestos!G22 | F20: =+F90 | H20: =+$E19*H90 | I20: =+$E19*I90 | J20: =+$E19*J90 | K20: =+$E19*K90 | L20: =+$E19*L90 | M20: =+$E19*M90 | N20: =+$E19*N90 | O20: =+$E19*O90 | ... S20: =+$E19*S90 | T20: =SUM(H19:S19) | V20: =+$E19*V90 | W20: =+$E19*W90 | X20: =+$E19*X90 | Y20: =+$E19*Y90 | Z20: =+$E19*Z90 | AA20: =+$E19*AA90 | AB20: =+$E19*AB90 | AC20: =+$E19*AC90 | ... AG20: =+$E19*AG90 | AH20: =SUM(V19:AG19) | AJ20: =+AH19+T19
C21: 3. | D21: Personal y Servicios | E21: =+Supuestos!E23 | F21: =+F91 | H21: =+H21+H22 | I21: =+I21+I22 | J21: =+J21+J22 | K21: =+K21+K22 | L21: =+L21+L22 | M21: =+M21+M22 | N21: =+N21+N22 | O21: =+O21+O22 | ... S21: =+S21+S22 | T21: =SUM(H20:S20) | V21: =+V21+V22 | W21: =+W21+W22 | X21: =+X21+X22 | Y21: =+Y21+Y22 | Z21: =+Z21+Z22 | AA21: =+AA21+AA22 | AB21: =+AB21+AB22 | AC21: =+AC21+AC22 | ... AG21: =+AG21+AG22 | AH21: =SUM(V20:AG20) | AJ21: =+AH20+T20
B22: Costo Empresa | C22: 3.1 | D22: Planilla Actual | E22: =+Supuestos!E24 | F22: =+F92 | H22: =+$E21*H92 | I22: =+$E21*I92 | J22: =+$E21*J92 | K22: =+$E21*K92 | L22: =+$E21*L92 | M22: =+$E21*M92 | N22: =+$E21*N92 | O22: =+$E21*O92 | ... S22: =+$E21*S92 | T22: =SUM(H21:S21) | V22: =+$E21*V92 | W22: =+$E21*W92 | X22: =+$E21*X92 | Y22: =+$E21*Y92 | Z22: =+$E21*Z92 | AA22: =+$E21*AA92 | AB22: =+$E21*AB92 | AC22: =+$E21*AC92 | ... AG22: =+$E21*AG92 | AH22: =SUM(V21:AG21) | AJ22: =+AH21+T21
C23: 3.2 | D23: Descarga estructura | E23: =+Supuestos!E25 | H23: =+$E22*H93 | I23: =+$E22*I93 | J23: =+$E22*J93 | K23: =+$E22*K93 | L23: =+$E22*L93 | M23: =+$E22*M93 | N23: =+$E22*N93 | O23: =+$E22*O93 | ... S23: =+$E22*S93 | T23: =SUM(H22:S22) | V23: =+$E22*V93 | W23: =+$E22*W93 | X23: =+$E22*X93 | Y23: =+$E22*Y93 | Z23: =+$E22*Z93 | AA23: =+$E22*AA93 | AB23: =+$E22*AB93 | AC23: =+$E22*AC93 | ... AG23: =+$E22*AG93 | AH23: =SUM(V22:AG22) | AJ23: =+AH22+T22
C24: 4. | D24: Servicios Profesionales | E24: =+Supuestos!E26 | F24: =+F94 | H24: =+SUM(H24:H31) | I24: =+SUM(I24:I31) | J24: =+SUM(J24:J31) | K24: =+SUM(K24:K31) | L24: =+SUM(L24:L31) | M24: =+SUM(M24:M31) | N24: =+SUM(N24:N31) | O24: =+SUM(O24:O31) | ... S24: =+SUM(S24:S31) | T24: =SUM(H23:S23) | V24: =+SUM(V24:V31) | W24: =+SUM(W24:W31) | X24: =+SUM(X24:X31) | Y24: =+SUM(Y24:Y31) | Z24: =+SUM(Z24:Z31) | AA24: =+SUM(AA24:AA31) | AB24: =+SUM(AB24:AB31) | AC24: =+SUM(AC24:AC31) | ... AG24: =+SUM(AG24:AG31) | AH24: =SUM(V23:AG23) | AJ24: =+AH23+T23
B25: Boleta Honorarios | C25: 4.1 | D25: Encargado de Logistica y Bodega | E25: =+Supuestos!E27 | F25: =+F95 | H25: =+$E24*H95 | I25: =+$E24*I95 | J25: =+$E24*J95 | K25: =+$E24*K95 | L25: =+$E24*L95 | M25: =+$E24*M95 | N25: =+$E24*N95 | O25: =+$E24*O95 | ... S25: =+$E24*S95 | T25: =SUM(H24:S24) | V25: =+$E24*V95 | W25: =+$E24*W95 | X25: =+$E24*X95 | Y25: =+$E24*Y95 | Z25: =+$E24*Z95 | AA25: =+$E24*AA95 | AB25: =+$E24*AB95 | AC25: =+$E24*AC95 | ... AG25: =+$E24*AG95 | AH25: =SUM(V24:AG24) | AJ25: =+AH24+T24
B26: Boleta Honorarios | C26: 4.2 | D26: Técnico pago por instalación - Plan A | E26: =+Supuestos!E28 | F26: =+F96 | H26: =+$E25*H96 | I26: =+$E25*I96 | J26: =+$E25*J96 | K26: =+$E25*K96 | L26: =+$E25*L96 | M26: =+$E25*M96 | N26: =+$E25*N96 | O26: =+$E25*O96 | ... S26: =+$E25*S96 | T26: =SUM(H25:S25) | V26: =+$E25*V96 | W26: =+$E25*W96 | X26: =+$E25*X96 | Y26: =+$E25*Y96 | Z26: =+$E25*Z96 | AA26: =+$E25*AA96 | AB26: =+$E25*AB96 | AC26: =+$E25*AC96 | ... AG26: =+$E25*AG96 | AH26: =SUM(V25:AG25) | AJ26: =+AH25+T25
B27: Boleta Honorarios | C27: 4.3 | D27: Técnico contrato mensual - Plan B | E27: =+Supuestos!E29 | F27: =+F97 | H27: =+$E26*H97 | I27: =+$E26*I97 | J27: =+$E26*J97 | K27: =+$E26*K97 | L27: =+$E26*L97 | M27: =+$E26*M97 | N27: =+$E26*N97 | O27: =+$E26*O97 | ... S27: =+$E26*S97 | T27: =SUM(H26:S26) | V27: =+$E26*V97 | W27: =+$E26*W97 | X27: =+$E26*X97 | Y27: =+$E26*Y97 | Z27: =+$E26*Z97 | AA27: =+$E26*AA97 | AB27: =+$E26*AB97 | AC27: =+$E26*AC97 | ... AG27: =+$E26*AG97 | AH27: =SUM(V26:AG26) | AJ27: =+AH26+T26
B28: Boleta Honorarios | C28: 4.4 | D28: Ayudante contrato mensual - Plan B | E28: =+Supuestos!E30 | F28: =+F98 | H28: =+$E27*H98 | I28: =+$E27*I98 | J28: =+$E27*J98 | K28: =+$E27*K98 | L28: =+$E27*L98 | M28: =+$E27*M98 | N28: =+$E27*N98 | O28: =+$E27*O98 | ... S28: =+$E27*S98 | T28: =SUM(H27:S27) | V28: =+$E27*V98 | W28: =+$E27*W98 | X28: =+$E27*X98 | Y28: =+$E27*Y98 | Z28: =+$E27*Z98 | AA28: =+$E27*AA98 | AB28: =+$E27*AB98 | AC28: =+$E27*AC98 | ... AG28: =+$E27*AG98 | AH28: =SUM(V27:AG27) | AJ28: =+AH27+T27
B29: Boleta Honorarios | C29: 4.5 | D29: Personal apoyo Planos TE1 | E29: =+Supuestos!E31 | F29: =+F99 | H29: =+$E28*H99 | I29: =+$E28*I99 | J29: =+$E28*J99 | K29: =+$E28*K99 | L29: =+$E28*L99 | M29: =+$E28*M99 | N29: =+$E28*N99 | O29: =+$E28*O99 | ... S29: =+$E28*S99 | T29: =SUM(H28:S28) | V29: =+$E28*V99 | W29: =+$E28*W99 | X29: =+$E28*X99 | Y29: =+$E28*Y99 | Z29: =+$E28*Z99 | AA29: =+$E28*AA99 | AB29: =+$E28*AB99 | AC29: =+$E28*AC99 | ... AG29: =+$E28*AG99 | AH29: =SUM(V28:AG28) | AJ29: =+AH28+T28
B30: Boleta Honorarios | C30: 4.6 | D30: Encargado territorial RRHH | E30: =+Supuestos!E32 | H30: =+$E29*H100 | I30: =+$E29*I100 | J30: =+$E29*J100 | K30: =+$E29*K100 | L30: =+$E29*L100 | M30: =+$E29*M100 | N30: =+$E29*N100 | O30: =+$E29*O100 | ... S30: =+$E29*S100 | T30: =SUM(H29:S29) | V30: =+$E29*V100 | W30: =+$E29*W100 | X30: =+$E29*X100 | Y30: =+$E29*Y100 | Z30: =+$E29*Z100 | AA30: =+$E29*AA100 | AB30: =+$E29*AB100 | AC30: =+$E29*AC100 | ... AG30: =+$E29*AG100 | AH30: =SUM(V29:AG29) | AJ30: =+AH29+T29
B31: Boleta Honorarios | C31: 4.7 | D31: Apoyo Financiero de proyecto | E31: =+Supuestos!E33 | H31: =+$E30*H101 | I31: =+$E30*I101 | J31: =+$E30*J101 | K31: =+$E30*K101 | L31: =+$E30*L101 | M31: =+$E30*M101 | N31: =+$E30*N101 | O31: =+$E30*O101 | ... S31: =+$E30*S101 | T31: =SUM(H30:S30) | V31: =+$E30*V101 | W31: =+$E30*W101 | X31: =+$E30*X101 | Y31: =+$E30*Y101 | Z31: =+$E30*Z101 | AA31: =+$E30*AA101 | AB31: =+$E30*AB101 | AC31: =+$E30*AC101 | ... AG31: =+$E30*AG101 | AH31: =SUM(V30:AG30) | AJ31: =+AH30+T30
B32: Boleta Honorarios | C32: 4.8 | E32: =+Supuestos!E34 | T32: =SUM(H31:S31) | AH32: =SUM(V31:AG31) | AJ32: =+AH31+T31
B33: Boleta Honorarios | T33: =SUM(H32:S32) | AH33: =SUM(V32:AG32) | AJ33: =+AH32+T32
C34: 5. | D34: Alquileres RRCC | E34: =+Supuestos!E36 | F34: =+F104 | H34: =+SUM(H34:H35) | I34: =+SUM(I34:I35) | J34: =+SUM(J34:J35) | K34: =+SUM(K34:K35) | L34: =+SUM(L34:L35) | M34: =+SUM(M34:M35) | N34: =+SUM(N34:N35) | O34: =+SUM(O34:O35) | ... S34: =+SUM(S34:S35) | T34: =SUM(H33:S33) | V34: =+SUM(V34:V35) | W34: =+SUM(W34:W35) | X34: =+SUM(X34:X35) | Y34: =+SUM(Y34:Y35) | Z34: =+SUM(Z34:Z35) | AA34: =+SUM(AA34:AA35) | AB34: =+SUM(AB34:AB35) | AC34: =+SUM(AC34:AC35) | ... AG34: =+SUM(AG34:AG35) | AH34: =SUM(V33:AG33) | AJ34: =+AH33+T33
B35: Factura | C35: 5.1 | D35: Arriendo vehículo diario - RRCC | E35: =+Supuestos!G37 | F35: =+F105 | H35: =+$E34*H105 | I35: =+$E34*I105 | J35: =+$E34*J105 | K35: =+$E34*K105 | L35: =+$E34*L105 | M35: =+$E34*M105 | N35: =+$E34*N105 | O35: =+$E34*O105 | ... S35: =+$E34*S105 | T35: =SUM(H34:S34) | V35: =+$E34*V105 | W35: =+$E34*W105 | X35: =+$E34*X105 | Y35: =+$E34*Y105 | Z35: =+$E34*Z105 | AA35: =+$E34*AA105 | AB35: =+$E34*AB105 | AC35: =+$E34*AC105 | ... AG35: =+$E34*AG105 | AH35: =SUM(V34:AG34) | AJ35: =+AH34+T34
B36: Factura | C36: 5.2 | D36: Vehiculo RRCC | E36: =+Supuestos!G38 | F36: =+F106 | H36: =+$E35*H106 | I36: =+$E35*I106 | J36: =+$E35*J106 | K36: =+$E35*K106 | L36: =+$E35*L106 | M36: =+$E35*M106 | N36: =+$E35*N106 | O36: =+$E35*O106 | ... S36: =+$E35*S106 | T36: =SUM(H35:S35) | V36: =+$E35*V106 | W36: =+$E35*W106 | X36: =+$E35*X106 | Y36: =+$E35*Y106 | Z36: =+$E35*Z106 | AA36: =+$E35*AA106 | AB36: =+$E35*AB106 | AC36: =+$E35*AC106 | ... AG36: =+$E35*AG106 | AH36: =SUM(V35:AG35) | AJ36: =+AH35+T35
C37: 6. | D37: Alquileres Gestión Técnica | E37: =+Supuestos!E39 | F37: =+F107 | H37: =+SUM(H37:H40) | I37: =+SUM(I37:I40) | J37: =+SUM(J37:J40) | K37: =+SUM(K37:K40) | L37: =+SUM(L37:L40) | M37: =+SUM(M37:M40) | N37: =+SUM(N37:N40) | O37: =+SUM(O37:O40) | ... S37: =+SUM(S37:S40) | T37: =SUM(H36:S36) | V37: =+SUM(V37:V40) | W37: =+SUM(W37:W40) | X37: =+SUM(X37:X40) | Y37: =+SUM(Y37:Y40) | Z37: =+SUM(Z37:Z40) | AA37: =+SUM(AA37:AA40) | AB37: =+SUM(AB37:AB40) | AC37: =+SUM(AC37:AC40) | ... AG37: =+SUM(AG37:AG40) | AH37: =SUM(V36:AG36) | AJ37: =+AH36+T36
B38: Factura | C38: 6.1 | D38: Bodega Terreno | E38: =+Supuestos!G40 | F38: =+F108 | H38: =+$E37*H108 | I38: =+$E37*I108 | J38: =+$E37*J108 | K38: =+$E37*K108 | L38: =+$E37*L108 | M38: =+$E37*M108 | N38: =+$E37*N108 | O38: =+$E37*O108 | ... S38: =+$E37*S108 | T38: =SUM(H37:S37) | V38: =+$E37*V108 | W38: =+$E37*W108 | X38: =+$E37*X108 | Y38: =+$E37*Y108 | Z38: =+$E37*Z108 | AA38: =+$E37*AA108 | AB38: =+$E37*AB108 | AC38: =+$E37*AC108 | ... AG38: =+$E37*AG108 | AH38: =SUM(V37:AG37) | AJ38: =+AH37+T37
B39: Factura | C39: 6.2 | D39: Arriendo vehículo diario - Área Técnica | E39: =+Supuestos!G41 | F39: =+F109 | H39: =+$E38*H109 | I39: =+$E38*I109 | J39: =+$E38*J109 | K39: =+$E38*K109 | L39: =+$E38*L109 | M39: =+$E38*M109 | N39: =+$E38*N109 | O39: =+$E38*O109 | ... S39: =+$E38*S109 | T39: =SUM(H38:S38) | V39: =+$E38*V109 | W39: =+$E38*W109 | X39: =+$E38*X109 | Y39: =+$E38*Y109 | Z39: =+$E38*Z109 | AA39: =+$E38*AA109 | AB39: =+$E38*AB109 | AC39: =+$E38*AC109 | ... AG39: =+$E38*AG109 | AH39: =SUM(V38:AG38) | AJ39: =+AH38+T38
B40: Factura | C40: 6.3 | D40: Vehiculo Instaladores | E40: =+Supuestos!G42 | F40: =+F110 | H40: =+$E39*H110 | I40: =+$E39*I110 | J40: =+$E39*J110 | K40: =+$E39*K110 | L40: =+$E39*L110 | M40: =+$E39*M110 | N40: =+$E39*N110 | O40: =+$E39*O110 | ... S40: =+$E39*S110 | T40: =SUM(H39:S39) | V40: =+$E39*V110 | W40: =+$E39*W110 | X40: =+$E39*X110 | Y40: =+$E39*Y110 | Z40: =+$E39*Z110 | AA40: =+$E39*AA110 | AB40: =+$E39*AB110 | AC40: =+$E39*AC110 | ... AG40: =+$E39*AG110 | AH40: =SUM(V39:AG39) | AJ40: =+AH39+T39
B41: Factura | C41: 6.4 | D41: Vehiculo Transporte (Maxus Deliver 9) | E41: =+Supuestos!G43 | F41: =+F111 | H41: =+$E40*H111 | I41: =+$E40*I111 | J41: =+$E40*J111 | K41: =+$E40*K111 | L41: =+$E40*L111 | M41: =+$E40*M111 | N41: =+$E40*N111 | O41: =+$E40*O111 | ... S41: =+$E40*S111 | T41: =SUM(H40:S40) | V41: =+$E40*V111 | W41: =+$E40*W111 | X41: =+$E40*X111 | Y41: =+$E40*Y111 | Z41: =+$E40*Z111 | AA41: =+$E40*AA111 | AB41: =+$E40*AB111 | AC41: =+$E40*AC111 | ... AG41: =+$E40*AG111 | AH41: =SUM(V40:AG40) | AJ41: =+AH40+T40
C42: 7. | D42: Transporte | E42: =+Supuestos!E44 | F42: =+F112 | H42: =+SUM(H42:H48) | I42: =+SUM(I42:I48) | J42: =+SUM(J42:J48) | K42: =+SUM(K42:K48) | L42: =+SUM(L42:L48) | M42: =+SUM(M42:M48) | N42: =+SUM(N42:N48) | O42: =+SUM(O42:O48) | ... S42: =+SUM(S42:S48) | T42: =SUM(H41:S41) | V42: =+SUM(V42:V48) | W42: =+SUM(W42:W48) | X42: =+SUM(X42:X48) | Y42: =+SUM(Y42:Y48) | Z42: =+SUM(Z42:Z48) | AA42: =+SUM(AA42:AA48) | AB42: =+SUM(AB42:AB48) | AC42: =+SUM(AC42:AC48) | ... AG42: =+SUM(AG42:AG48) | AH42: =SUM(V41:AG41) | AJ42: =+AH41+T41
B43: Factura | C43: 7.1 | D43: Transporte ZIMPERTEC | E43: =+Supuestos!G45 | F43: =+F113 | H43: =+$E42*H113 | I43: =+$E42*I113 | J43: =+$E42*J113 | K43: =+$E42*K113 | L43: =+$E42*L113 | M43: =+$E42*M113 | N43: =+$E42*N113 | O43: =+$E42*O113 | ... S43: =+$E42*S113 | T43: =SUM(H42:S42) | V43: =+$E42*V113 | W43: =+$E42*W113 | X43: =+$E42*X113 | Y43: =+$E42*Y113 | Z43: =+$E42*Z113 | AA43: =+$E42*AA113 | AB43: =+$E42*AB113 | AC43: =+$E42*AC113 | ... AG43: =+$E42*AG113 | AH43: =SUM(V42:AG42) | AJ43: =+AH42+T42
T44: =SUM(H43:S43) | AH44: =SUM(V43:AG43) | AJ44: =+AH43+T43
B45: Factura | C45: 7.3 | D45: Traslado Contenedor (ida y vuelta) | E45: =+Supuestos!G47 | F45: =+F115 | H45: =+$E44*H115 | I45: =+$E44*I115 | J45: =+$E44*J115 | K45: =+$E44*K115 | L45: =+$E44*L115 | M45: =+$E44*M115 | N45: =+$E44*N115 | O45: =+$E44*O115 | ... S45: =+$E44*S115 | T45: =SUM(H44:S44) | V45: =+$E44*V115 | W45: =+$E44*W115 | X45: =+$E44*X115 | Y45: =+$E44*Y115 | Z45: =+$E44*Z115 | AA45: =+$E44*AA115 | AB45: =+$E44*AB115 | AC45: =+$E44*AC115 | ... AG45: =+$E44*AG115 | AH45: =SUM(V44:AG44) | AJ45: =+AH44+T44
B46: Factura | C46: 7.4 | D46: Camión Transporte Origen - Punto Destino (RAMPLA ABIERTA) | E46: =+Supuestos!G48 | F46: =+F116 | H46: =+$E45*H116 | I46: =+$E45*I116 | J46: =+$E45*J116 | K46: =+$E45*K116 | L46: =+$E45*L116 | M46: =+$E45*M116 | N46: =+$E45*N116 | O46: =+$E45*O116 | ... S46: =+$E45*S116 | T46: =SUM(H45:S45) | V46: =+$E45*V116 | W46: =+$E45*W116 | X46: =+$E45*X116 | Y46: =+$E45*Y116 | Z46: =+$E45*Z116 | AA46: =+$E45*AA116 | AB46: =+$E45*AB116 | AC46: =+$E45*AC116 | ... AG46: =+$E45*AG116 | AH46: =SUM(V45:AG45) | AJ46: =+AH45+T45
T47: =SUM(H46:S46) | AH47: =SUM(V46:AG46) | AJ47: =+AH46+T46
T48: =SUM(H47:S47) | AH48: =SUM(V47:AG47) | AJ48: =+AH47+T47
B49: Factura | C49: 7.7 | D49: Camión Transporte Origen - Punto Destino (Camión cerrado) | E49: =+Supuestos!G51 | F49: =+F119 | H49: =+$E48*H119 | I49: =+$E48*I119 | J49: =+$E48*J119 | K49: =+$E48*K119 | L49: =+$E48*L119 | M49: =+$E48*M119 | N49: =+$E48*N119 | O49: =+$E48*O119 | ... S49: =+$E48*S119 | T49: =SUM(H48:S48) | V49: =+$E48*V119 | W49: =+$E48*W119 | X49: =+$E48*X119 | Y49: =+$E48*Y119 | Z49: =+$E48*Z119 | AA49: =+$E48*AA119 | AB49: =+$E48*AB119 | AC49: =+$E48*AC119 | ... AG49: =+$E48*AG119 | AH49: =SUM(V48:AG48) | AJ49: =+AH48+T48
C50: 8. | D50: Viajes RRCC | E50: =+Supuestos!E52 | F50: =+F120 | H50: =+SUM(H50:H55) | I50: =+SUM(I50:I55) | J50: =+SUM(J50:J55) | K50: =+SUM(K50:K55) | L50: =+SUM(L50:L55) | M50: =+SUM(M50:M55) | N50: =+SUM(N50:N55) | O50: =+SUM(O50:O55) | ... S50: =+SUM(S50:S55) | T50: =SUM(H49:S49) | V50: =+SUM(V50:V55) | W50: =+SUM(W50:W55) | X50: =+SUM(X50:X55) | Y50: =+SUM(Y50:Y55) | Z50: =+SUM(Z50:Z55) | AA50: =+SUM(AA50:AA55) | AB50: =+SUM(AB50:AB55) | AC50: =+SUM(AC50:AC55) | ... AG50: =+SUM(AG50:AG55) | AH50: =SUM(V49:AG49) | AJ50: =+AH49+T49
B51: Factura | C51: 8.1 | D51: Traslados de personal | E51: =+Supuestos!G53 | F51: =+F121 | H51: =+$E50*H121 | I51: =+$E50*I121 | J51: =+$E50*J121 | K51: =+$E50*K121 | L51: =+$E50*L121 | M51: =+$E50*M121 | N51: =+$E50*N121 | O51: =+$E50*O121 | ... S51: =+$E50*S121 | T51: =SUM(H50:S50) | V51: =+$E50*V121 | W51: =+$E50*W121 | X51: =+$E50*X121 | Y51: =+$E50*Y121 | Z51: =+$E50*Z121 | AA51: =+$E50*AA121 | AB51: =+$E50*AB121 | AC51: =+$E50*AC121 | ... AG51: =+$E50*AG121 | AH51: =SUM(V50:AG50) | AJ51: =+AH50+T50
B52: Factura o Boleta | C52: 8.2 | D52: Alojamiento | E52: =+Supuestos!G54 | F52: =+F122 | H52: =+$E51*H122 | I52: =+$E51*I122 | J52: =+$E51*J122 | K52: =+$E51*K122 | L52: =+$E51*L122 | M52: =+$E51*M122 | N52: =+$E51*N122 | O52: =+$E51*O122 | ... S52: =+$E51*S122 | T52: =SUM(H51:S51) | V52: =+$E51*V122 | W52: =+$E51*W122 | X52: =+$E51*X122 | Y52: =+$E51*Y122 | Z52: =+$E51*Z122 | AA52: =+$E51*AA122 | AB52: =+$E51*AB122 | AC52: =+$E51*AC122 | ... AG52: =+$E51*AG122 | AH52: =SUM(V51:AG51) | AJ52: =+AH51+T51
B53: Boleta | C53: 8.3 | D53: Alimentación | E53: =+Supuestos!G55 | F53: =+F123 | H53: =+$E52*H123 | I53: =+$E52*I123 | J53: =+$E52*J123 | K53: =+$E52*K123 | L53: =+$E52*L123 | M53: =+$E52*M123 | N53: =+$E52*N123 | O53: =+$E52*O123 | ... S53: =+$E52*S123 | T53: =SUM(H52:S52) | V53: =+$E52*V123 | W53: =+$E52*W123 | X53: =+$E52*X123 | Y53: =+$E52*Y123 | Z53: =+$E52*Z123 | AA53: =+$E52*AA123 | AB53: =+$E52*AB123 | AC53: =+$E52*AC123 | ... AG53: =+$E52*AG123 | AH53: =SUM(V52:AG52) | AJ53: =+AH52+T52
B54: Factura o Boleta | C54: 8.4 | D54: Combustible arriendo diario | E54: =+Supuestos!G56 | F54: =+F124 | H54: =+$E53*H124 | I54: =+$E53*I124 | J54: =+$E53*J124 | K54: =+$E53*K124 | L54: =+$E53*L124 | M54: =+$E53*M124 | N54: =+$E53*N124 | O54: =+$E53*O124 | ... S54: =+$E53*S124 | T54: =SUM(H53:S53) | V54: =+$E53*V124 | W54: =+$E53*W124 | X54: =+$E53*X124 | Y54: =+$E53*Y124 | Z54: =+$E53*Z124 | AA54: =+$E53*AA124 | AB54: =+$E53*AB124 | AC54: =+$E53*AC124 | ... AG54: =+$E53*AG124 | AH54: =SUM(V53:AG53) | AJ54: =+AH53+T53
B55: Factura o Boleta | C55: 8.5 | D55: Combustible arriendo mensual | E55: =+Supuestos!G57 | F55: =+F125 | H55: =+$E54*H125 | I55: =+$E54*I125 | J55: =+$E54*J125 | K55: =+$E54*K125 | L55: =+$E54*L125 | M55: =+$E54*M125 | N55: =+$E54*N125 | O55: =+$E54*O125 | ... S55: =+$E54*S125 | T55: =SUM(H54:S54) | V55: =+$E54*V125 | W55: =+$E54*W125 | X55: =+$E54*X125 | Y55: =+$E54*Y125 | Z55: =+$E54*Z125 | AA55: =+$E54*AA125 | AB55: =+$E54*AB125 | AC55: =+$E54*AC125 | ... AG55: =+$E54*AG125 | AH55: =SUM(V54:AG54) | AJ55: =+AH54+T54
B56: Boleta | C56: 8.6 | D56: Peajes | E56: =+Supuestos!G58 | F56: =+F126 | H56: =+$E55*H126 | I56: =+$E55*I126 | J56: =+$E55*J126 | K56: =+$E55*K126 | L56: =+$E55*L126 | M56: =+$E55*M126 | N56: =+$E55*N126 | O56: =+$E55*O126 | ... S56: =+$E55*S126 | T56: =SUM(H55:S55) | V56: =+$E55*V126 | W56: =+$E55*W126 | X56: =+$E55*X126 | Y56: =+$E55*Y126 | Z56: =+$E55*Z126 | AA56: =+$E55*AA126 | AB56: =+$E55*AB126 | AC56: =+$E55*AC126 | ... AG56: =+$E55*AG126 | AH56: =SUM(V55:AG55) | AJ56: =+AH55+T55
C57: 9. | D57: Viajes Gestión Técnica | E57: =+Supuestos!E59 | F57: =+F127 | H57: =+SUM(H57:H62) | I57: =+SUM(I57:I62) | J57: =+SUM(J57:J62) | K57: =+SUM(K57:K62) | L57: =+SUM(L57:L62) | M57: =+SUM(M57:M62) | N57: =+SUM(N57:N62) | O57: =+SUM(O57:O62) | ... S57: =+SUM(S57:S62) | T57: =SUM(H56:S56) | V57: =+SUM(V57:V62) | W57: =+SUM(W57:W62) | X57: =+SUM(X57:X62) | Y57: =+SUM(Y57:Y62) | Z57: =+SUM(Z57:Z62) | AA57: =+SUM(AA57:AA62) | AB57: =+SUM(AB57:AB62) | AC57: =+SUM(AC57:AC62) | ... AG57: =+SUM(AG57:AG62) | AH57: =SUM(V56:AG56) | AJ57: =+AH56+T56
B58: Factura | C58: 9.1 | D58: Traslados de personal | E58: =+Supuestos!G60 | F58: =+F128 | H58: =+$E57*H128 | I58: =+$E57*I128 | J58: =+$E57*J128 | K58: =+$E57*K128 | L58: =+$E57*L128 | M58: =+$E57*M128 | N58: =+$E57*N128 | O58: =+$E57*O128 | ... S58: =+$E57*S128 | T58: =SUM(H57:S57) | V58: =+$E57*V128 | W58: =+$E57*W128 | X58: =+$E57*X128 | Y58: =+$E57*Y128 | Z58: =+$E57*Z128 | AA58: =+$E57*AA128 | AB58: =+$E57*AB128 | AC58: =+$E57*AC128 | ... AG58: =+$E57*AG128 | AH58: =SUM(V57:AG57) | AJ58: =+AH57+T57
B59: Factura o Boleta | C59: 9.2 | D59: Alojamiento | E59: =+Supuestos!G61 | F59: =+F129 | H59: =+$E58*H129 | I59: =+$E58*I129 | J59: =+$E58*J129 | K59: =+$E58*K129 | L59: =+$E58*L129 | M59: =+$E58*M129 | N59: =+$E58*N129 | O59: =+$E58*O129 | ... S59: =+$E58*S129 | T59: =SUM(H58:S58) | V59: =+$E58*V129 | W59: =+$E58*W129 | X59: =+$E58*X129 | Y59: =+$E58*Y129 | Z59: =+$E58*Z129 | AA59: =+$E58*AA129 | AB59: =+$E58*AB129 | AC59: =+$E58*AC129 | ... AG59: =+$E58*AG129 | AH59: =SUM(V58:AG58) | AJ59: =+AH58+T58
B60: Boleta | C60: 9.3 | D60: Alimentación | E60: =+Supuestos!G62 | F60: =+F130 | H60: =+$E59*H130 | I60: =+$E59*I130 | J60: =+$E59*J130 | K60: =+$E59*K130 | L60: =+$E59*L130 | M60: =+$E59*M130 | N60: =+$E59*N130 | O60: =+$E59*O130 | ... S60: =+$E59*S130 | T60: =SUM(H59:S59) | V60: =+$E59*V130 | W60: =+$E59*W130 | X60: =+$E59*X130 | Y60: =+$E59*Y130 | Z60: =+$E59*Z130 | AA60: =+$E59*AA130 | AB60: =+$E59*AB130 | AC60: =+$E59*AC130 | ... AG60: =+$E59*AG130 | AH60: =SUM(V59:AG59) | AJ60: =+AH59+T59
B61: Factura o Boleta | C61: 9.4 | D61: Combustible arriendo diario | E61: =+Supuestos!G63 | F61: =+F131 | H61: =+$E60*H131 | I61: =+$E60*I131 | J61: =+$E60*J131 | K61: =+$E60*K131 | L61: =+$E60*L131 | M61: =+$E60*M131 | N61: =+$E60*N131 | O61: =+$E60*O131 | ... S61: =+$E60*S131 | T61: =SUM(H60:S60) | V61: =+$E60*V131 | W61: =+$E60*W131 | X61: =+$E60*X131 | Y61: =+$E60*Y131 | Z61: =+$E60*Z131 | AA61: =+$E60*AA131 | AB61: =+$E60*AB131 | AC61: =+$E60*AC131 | ... AG61: =+$E60*AG131 | AH61: =SUM(V60:AG60) | AJ61: =+AH60+T60
B62: Factura o Boleta | C62: 9.5 | D62: Combustible arriendo mensual | E62: =+Supuestos!G64 | F62: =+F132 | H62: =+$E61*H132 | I62: =+$E61*I132 | J62: =+$E61*J132 | K62: =+$E61*K132 | L62: =+$E61*L132 | M62: =+$E61*M132 | N62: =+$E61*N132 | O62: =+$E61*O132 | ... S62: =+$E61*S132 | T62: =SUM(H61:S61) | V62: =+$E61*V132 | W62: =+$E61*W132 | X62: =+$E61*X132 | Y62: =+$E61*Y132 | Z62: =+$E61*Z132 | AA62: =+$E61*AA132 | AB62: =+$E61*AB132 | AC62: =+$E61*AC132 | ... AG62: =+$E61*AG132 | AH62: =SUM(V61:AG61) | AJ62: =+AH61+T61
B63: Boleta | C63: 9.6 | D63: Peajes | E63: =+Supuestos!G65 | F63: =+F133 | H63: =+$E62*H133 | I63: =+$E62*I133 | J63: =+$E62*J133 | K63: =+$E62*K133 | L63: =+$E62*L133 | M63: =+$E62*M133 | N63: =+$E62*N133 | O63: =+$E62*O133 | ... S63: =+$E62*S133 | T63: =SUM(H62:S62) | V63: =+$E62*V133 | W63: =+$E62*W133 | X63: =+$E62*X133 | Y63: =+$E62*Y133 | Z63: =+$E62*Z133 | AA63: =+$E62*AA133 | AB63: =+$E62*AB133 | AC63: =+$E62*AC133 | ... AG63: =+$E62*AG133 | AH63: =SUM(V62:AG62) | AJ63: =+AH62+T62
C64: 10. | D64: Gastos Varios | E64: =+Supuestos!E66 | F64: =+F134 | H64: =+SUM(H64:H68) | I64: =+SUM(I64:I68) | J64: =+SUM(J64:J68) | K64: =+SUM(K64:K68) | L64: =+SUM(L64:L68) | M64: =+SUM(M64:M68) | N64: =+SUM(N64:N68) | O64: =+SUM(O64:O68) | ... S64: =+SUM(S64:S68) | T64: =SUM(H63:S63) | V64: =+SUM(V64:V68) | W64: =+SUM(W64:W68) | X64: =+SUM(X64:X68) | Y64: =+SUM(Y64:Y68) | Z64: =+SUM(Z64:Z68) | AA64: =+SUM(AA64:AA68) | AB64: =+SUM(AB64:AB68) | AC64: =+SUM(AC64:AC68) | ... AG64: =+SUM(AG64:AG68) | AH64: =SUM(V63:AG63) | AJ64: =+AH63+T63
B65: Boleta | C65: 10.1 | D65: Compras de Equipos, EEPP, Otros | E65: =+Supuestos!G67 | F65: =+F135 | H65: =+$E64*H135 | I65: =+$E64*I135 | J65: =+$E64*J135 | K65: =+$E64*K135 | L65: =+$E64*L135 | M65: =+$E64*M135 | N65: =+$E64*N135 | O65: =+$E64*O135 | ... S65: =+$E64*S135 | T65: =SUM(H64:S64) | V65: =+$E64*V135 | W65: =+$E64*W135 | X65: =+$E64*X135 | Y65: =+$E64*Y135 | Z65: =+$E64*Z135 | AA65: =+$E64*AA135 | AB65: =+$E64*AB135 | AC65: =+$E64*AC135 | ... AG65: =+$E64*AG135 | AH65: =SUM(V64:AG64) | AJ65: =+AH64+T64
B66: Boleta | C66: 10.2 | D66: Mensajerias (Correo de Chile) | E66: =+Supuestos!G68 | F66: =+F136 | H66: =+$E65*H136 | I66: =+$E65*I136 | J66: =+$E65*J136 | K66: =+$E65*K136 | L66: =+$E65*L136 | M66: =+$E65*M136 | N66: =+$E65*N136 | O66: =+$E65*O136 | ... S66: =+$E65*S136 | T66: =SUM(H65:S65) | V66: =+$E65*V136 | W66: =+$E65*W136 | X66: =+$E65*X136 | Y66: =+$E65*Y136 | Z66: =+$E65*Z136 | AA66: =+$E65*AA136 | AB66: =+$E65*AB136 | AC66: =+$E65*AC136 | ... AG66: =+$E65*AG136 | AH66: =SUM(V65:AG65) | AJ66: =+AH65+T65
B67: Factura + Boleta | C67: 10.3 | D67: Impresión de manuales | E67: =+Supuestos!G69 | F67: =+F137 | H67: =+$E66*H137 | I67: =+$E66*I137 | J67: =+$E66*J137 | K67: =+$E66*K137 | L67: =+$E66*L137 | M67: =+$E66*M137 | N67: =+$E66*N137 | O67: =+$E66*O137 | ... S67: =+$E66*S137 | T67: =SUM(H66:S66) | V67: =+$E66*V137 | W67: =+$E66*W137 | X67: =+$E66*X137 | Y67: =+$E66*Y137 | Z67: =+$E66*Z137 | AA67: =+$E66*AA137 | AB67: =+$E66*AB137 | AC67: =+$E66*AC137 | ... AG67: =+$E66*AG137 | AH67: =SUM(V66:AG66) | AJ67: =+AH66+T66
B68: Factura + Boleta | C68: 10.4 | D68: Mantención y reparación de Vehículos | E68: =+Supuestos!G70 | F68: =+F138 | H68: =+$E67*H138 | I68: =+$E67*I138 | J68: =+$E67*J138 | K68: =+$E67*K138 | L68: =+$E67*L138 | M68: =+$E67*M138 | N68: =+$E67*N138 | O68: =+$E67*O138 | ... S68: =+$E67*S138 | V68: =+$E67*V138 | W68: =+$E67*W138 | X68: =+$E67*X138 | Y68: =+$E67*Y138 | Z68: =+$E67*Z138 | AA68: =+$E67*AA138 | AB68: =+$E67*AB138 | AC68: =+$E67*AC138 | ... AG68: =+$E67*AG138 | AJ68: =+AH67+T67
B69: Boleta | C69: 10.5 | D69: Otros varios | E69: =+Supuestos!G71 | F69: =+F139 | H69: =+$E68*H139 | I69: =+$E68*I139 | J69: =+$E68*J139 | K69: =+$E68*K139 | L69: =+$E68*L139 | M69: =+$E68*M139 | N69: =+$E68*N139 | O69: =+$E68*O139 | ... R69: =+$E68*R139 | S69: =Supuestos!E2+$E68*S139 | T69: =SUM(H68:S68) | V69: =+$E68*V139 | W69: =+$E68*W139 | X69: =+$E68*X139 | Y69: =+$E68*Y139 | Z69: =+$E68*Z139 | AA69: =+$E68*AA139 | AB69: =+$E68*AB139 | AC69: =+$E68*AC139 | ... AG69: =+$E68*AG139 | AH69: =SUM(V68:AG68) | AJ69: =+AH68+T68
AJ70: =+AJ5+AJ16+AJ20+AJ23+AJ33+AJ36+AJ41+AJ49+AJ56+AJ63 | AK70: TOTAL | AL70: =AJ5 | AM70: Costo Equipos en La Serena
AL71: =AJ69-AL69 | AM71: Diferencia de Sistema y Aporte Cuota | AN71: =+AL70-AL71 | AO71: Diferencia de Costos Fundación y Equipos
AJ72: =AJ69/60 | AL72: =150000000 | AM72: Meta a cubrir 50%
D75: CANTIDAD | Q75: 0.3 | V75: 0.5 | W75: 0.2
B76: Forma pago | C76: Nivel | D76: Item | E76: Cantidad | F76: Cantidad | H76: 46023 | I76: 46054 | J76: 46082 | K76: 46113 | L76: 46143 | M76: 46174 | N76: 46204 | O76: 46235 | P76: 46266 | Q76: 46296 | R76: 46327 | S76: 46357 | T76: 2026 | V76: 46388 | W76: 46419 | X76: 46447 | Y76: 46478 | Z76: 46508 | AA76: 46539 | AB76: 46569 | AC76: 46600 | AD76: 46631 | AE76: 46661 | AF76: 46692 | AG76: 46722 | AH76: 2026
C77: 1 | D77: Compras activables ZIMPERTEC | E77: =+E5 | H77: =+'Flujo Neto'!H76 | I77: =+'Flujo Neto'!I76 | J77: =+'Flujo Neto'!J76 | K77: =+'Flujo Neto'!K76 | L77: =+'Flujo Neto'!L76 | M77: =+'Flujo Neto'!M76 | N77: =+'Flujo Neto'!N76 | O77: =+'Flujo Neto'!O76 | ... T77: =+'Flujo Neto'!T76 | V77: =+'Flujo Neto'!V76 | W77: =+'Flujo Neto'!W76 | X77: =+'Flujo Neto'!X76 | Y77: =+'Flujo Neto'!Y76 | Z77: =+'Flujo Neto'!Z76 | AA77: =+'Flujo Neto'!AA76 | AB77: =+'Flujo Neto'!AB76 | AC77: =+'Flujo Neto'!AC76 | ... AH77: =+'Flujo Neto'!AH76
B78: Factura | C78: 1.1 | D78: Sistemas AC | E78: =+E6 | F78: =+Supuestos!H9 | H78: =+'Flujo Neto'!H77 | I78: =+'Flujo Neto'!I77 | J78: =+'Flujo Neto'!J77 | K78: =+'Flujo Neto'!K77 | L78: =+'Flujo Neto'!L77 | M78: =+'Flujo Neto'!M77 | N78: =+'Flujo Neto'!N77 | O78: =+'Flujo Neto'!O77 | ... T78: =+'Flujo Neto'!T77 | V78: =+'Flujo Neto'!V77 | W78: =+'Flujo Neto'!W77 | X78: =+'Flujo Neto'!X77 | Y78: =+'Flujo Neto'!Y77 | Z78: =+'Flujo Neto'!Z77 | AA78: =+'Flujo Neto'!AA77 | AB78: =+'Flujo Neto'!AB77 | AC78: =+'Flujo Neto'!AC77 | ... AH78: =+'Flujo Neto'!AH77
B79: Factura | C79: 1.2 | D79: Paneles | E79: =+E7 | F79: =+Supuestos!H10 | H79: =+'Flujo Neto'!H78 | I79: =+'Flujo Neto'!I78 | J79: =+'Flujo Neto'!J78 | K79: =+'Flujo Neto'!K78 | L79: =+'Flujo Neto'!L78 | M79: =+'Flujo Neto'!M78 | N79: =+'Flujo Neto'!N78 | O79: =+'Flujo Neto'!O78 | ... T79: =+'Flujo Neto'!T78 | V79: =+'Flujo Neto'!V78 | W79: =+'Flujo Neto'!W78 | X79: =+'Flujo Neto'!X78 | Y79: =+'Flujo Neto'!Y78 | Z79: =+'Flujo Neto'!Z78 | AA79: =+'Flujo Neto'!AA78 | AB79: =+'Flujo Neto'!AB78 | AC79: =+'Flujo Neto'!AC78 | ... AH79: =+'Flujo Neto'!AH78
B80: Factura | C80: 1.3 | D80: Lamparas | E80: =+E8 | F80: =+Supuestos!H11 | H80: =+'Flujo Neto'!H79 | I80: =+'Flujo Neto'!I79 | J80: =+'Flujo Neto'!J79 | K80: =+'Flujo Neto'!K79 | L80: =+'Flujo Neto'!L79 | M80: =+'Flujo Neto'!M79 | N80: =+'Flujo Neto'!N79 | O80: =+'Flujo Neto'!O79 | ... T80: =+'Flujo Neto'!T79 | V80: =+'Flujo Neto'!V79 | W80: =+'Flujo Neto'!W79 | X80: =+'Flujo Neto'!X79 | Y80: =+'Flujo Neto'!Y79 | Z80: =+'Flujo Neto'!Z79 | AA80: =+'Flujo Neto'!AA79 | AB80: =+'Flujo Neto'!AB79 | AC80: =+'Flujo Neto'!AC79 | ... AH80: =+'Flujo Neto'!AH79
B81: Factura | C81: 1.4 | D81: Hardware Monitoreo | E81: =+E9 | F81: =+Supuestos!H12 | H81: =+'Flujo Neto'!H80 | I81: =+'Flujo Neto'!I80 | J81: =+'Flujo Neto'!J80 | K81: =+'Flujo Neto'!K80 | L81: =+'Flujo Neto'!L80 | M81: =+'Flujo Neto'!M80 | N81: =+'Flujo Neto'!N80 | O81: =+'Flujo Neto'!O80 | ... T81: =+'Flujo Neto'!T80 | V81: =+'Flujo Neto'!V80 | W81: =+'Flujo Neto'!W80 | X81: =+'Flujo Neto'!X80 | Y81: =+'Flujo Neto'!Y80 | Z81: =+'Flujo Neto'!Z80 | AA81: =+'Flujo Neto'!AA80 | AB81: =+'Flujo Neto'!AB80 | AC81: =+'Flujo Neto'!AC80 | ... AH81: =+'Flujo Neto'!AH80
B82: Factura | C82: 1.5 | D82: Software Monitoreo | E82: =+E10 | F82: =+Supuestos!H13 | H82: =+'Flujo Neto'!H81 | I82: =+'Flujo Neto'!I81 | J82: =+'Flujo Neto'!J81 | K82: =+'Flujo Neto'!K81 | L82: =+'Flujo Neto'!L81 | M82: =+'Flujo Neto'!M81 | N82: =+'Flujo Neto'!N81 | O82: =+'Flujo Neto'!O81 | ... T82: =+'Flujo Neto'!T81 | V82: =+'Flujo Neto'!V81 | W82: =+'Flujo Neto'!W81 | X82: =+'Flujo Neto'!X81 | Y82: =+'Flujo Neto'!Y81 | Z82: =+'Flujo Neto'!Z81 | AA82: =+'Flujo Neto'!AA81 | AB82: =+'Flujo Neto'!AB81 | AC82: =+'Flujo Neto'!AC81 | ... AH82: =+'Flujo Neto'!AH81
B83: Factura | C83: 1.6 | D83: Repuestos | E83: =+E11 | F83: =+Supuestos!H14 | H83: =+'Flujo Neto'!H82 | I83: =+'Flujo Neto'!I82 | J83: =+'Flujo Neto'!J82 | K83: =+'Flujo Neto'!K82 | L83: =+'Flujo Neto'!L82 | M83: =+'Flujo Neto'!M82 | N83: =+'Flujo Neto'!N82 | O83: =+'Flujo Neto'!O82 | ... T83: =+'Flujo Neto'!T82 | V83: =+'Flujo Neto'!V82 | W83: =+'Flujo Neto'!W82 | X83: =+'Flujo Neto'!X82 | Y83: =+'Flujo Neto'!Y82 | Z83: =+'Flujo Neto'!Z82 | AA83: =+'Flujo Neto'!AA82 | AB83: =+'Flujo Neto'!AB82 | AC83: =+'Flujo Neto'!AC82 | ... AH83: =+'Flujo Neto'!AH82
B84: Factura | C84: 1.7 | D84: Flete | E84: =+E12 | F84: =+Supuestos!H15 | H84: =+'Flujo Neto'!H83 | I84: =+'Flujo Neto'!I83 | J84: =+'Flujo Neto'!J83 | K84: =+'Flujo Neto'!K83 | L84: =+'Flujo Neto'!L83 | M84: =+'Flujo Neto'!M83 | N84: =+'Flujo Neto'!N83 | O84: =+'Flujo Neto'!O83 | ... T84: =+'Flujo Neto'!T83 | V84: =+'Flujo Neto'!V83 | W84: =+'Flujo Neto'!W83 | X84: =+'Flujo Neto'!X83 | Y84: =+'Flujo Neto'!Y83 | Z84: =+'Flujo Neto'!Z83 | AA84: =+'Flujo Neto'!AA83 | AB84: =+'Flujo Neto'!AB83 | AC84: =+'Flujo Neto'!AC83 | ... AH84: =+'Flujo Neto'!AH83
B85: Factura | C85: 7.2 | D85: Transporte DESCONSOLIDADO | E85: =+E13 | H85: =+'Flujo Neto'!H84 | I85: =+'Flujo Neto'!I84 | J85: =+'Flujo Neto'!J84 | K85: =+'Flujo Neto'!K84 | L85: =+'Flujo Neto'!L84 | M85: =+'Flujo Neto'!M84 | N85: =+'Flujo Neto'!N84 | O85: =+'Flujo Neto'!O84 | ... T85: =+'Flujo Neto'!T84 | V85: =+'Flujo Neto'!V84 | W85: =+'Flujo Neto'!W84 | X85: =+'Flujo Neto'!X84 | Y85: =+'Flujo Neto'!Y84 | Z85: =+'Flujo Neto'!Z84 | AA85: =+'Flujo Neto'!AA84 | AB85: =+'Flujo Neto'!AB84 | AC85: =+'Flujo Neto'!AC84 | ... AH85: =+'Flujo Neto'!AH84
B86: Factura | C86: 7.5 | D86: Grúa en Origen | E86: =+E14 | H86: =+'Flujo Neto'!H85 | I86: =+'Flujo Neto'!I85 | J86: =+'Flujo Neto'!J85 | K86: =+'Flujo Neto'!K85 | L86: =+'Flujo Neto'!L85 | M86: =+'Flujo Neto'!M85 | N86: =+'Flujo Neto'!N85 | O86: =+'Flujo Neto'!O85 | ... T86: =+'Flujo Neto'!T85 | V86: =+'Flujo Neto'!V85 | W86: =+'Flujo Neto'!W85 | X86: =+'Flujo Neto'!X85 | Y86: =+'Flujo Neto'!Y85 | Z86: =+'Flujo Neto'!Z85 | AA86: =+'Flujo Neto'!AA85 | AB86: =+'Flujo Neto'!AB85 | AC86: =+'Flujo Neto'!AC85 | ... AH86: =+'Flujo Neto'!AH85
B87: Factura | C87: 7.6 | D87: Grúa en Punto Destino (6 Horas) | E87: =+E15 | H87: =+'Flujo Neto'!H86 | I87: =+'Flujo Neto'!I86 | J87: =+'Flujo Neto'!J86 | K87: =+'Flujo Neto'!K86 | L87: =+'Flujo Neto'!L86 | M87: =+'Flujo Neto'!M86 | N87: =+'Flujo Neto'!N86 | O87: =+'Flujo Neto'!O86 | ... T87: =+'Flujo Neto'!T86 | V87: =+'Flujo Neto'!V86 | W87: =+'Flujo Neto'!W86 | X87: =+'Flujo Neto'!X86 | Y87: =+'Flujo Neto'!Y86 | Z87: =+'Flujo Neto'!Z86 | AA87: =+'Flujo Neto'!AA86 | AB87: =+'Flujo Neto'!AB86 | AC87: =+'Flujo Neto'!AC86 | ... AH87: =+'Flujo Neto'!AH86
C88: 2 | D88: Insumos Instalación | E88: =+E16 | H88: =+'Flujo Neto'!H87 | I88: =+'Flujo Neto'!I87 | J88: =+'Flujo Neto'!J87 | K88: =+'Flujo Neto'!K87 | L88: =+'Flujo Neto'!L87 | M88: =+'Flujo Neto'!M87 | N88: =+'Flujo Neto'!N87 | O88: =+'Flujo Neto'!O87 | ... T88: =+'Flujo Neto'!T87 | V88: =+'Flujo Neto'!V87 | W88: =+'Flujo Neto'!W87 | X88: =+'Flujo Neto'!X87 | Y88: =+'Flujo Neto'!Y87 | Z88: =+'Flujo Neto'!Z87 | AA88: =+'Flujo Neto'!AA87 | AB88: =+'Flujo Neto'!AB87 | AC88: =+'Flujo Neto'!AC87 | ... AH88: =+'Flujo Neto'!AH87
B89: Factura | C89: 2.1 | D89: Estructura | E89: =+E17 | F89: =+Supuestos!H20 | H89: =+'Flujo Neto'!H88 | I89: =+'Flujo Neto'!I88 | J89: =+'Flujo Neto'!J88 | K89: =+'Flujo Neto'!K88 | L89: =+'Flujo Neto'!L88 | M89: =+'Flujo Neto'!M88 | N89: =+'Flujo Neto'!N88 | O89: =+'Flujo Neto'!O88 | ... T89: =+'Flujo Neto'!T88 | V89: =+'Flujo Neto'!V88 | W89: =+'Flujo Neto'!W88 | X89: =+'Flujo Neto'!X88 | Y89: =+'Flujo Neto'!Y88 | Z89: =+'Flujo Neto'!Z88 | AA89: =+'Flujo Neto'!AA88 | AB89: =+'Flujo Neto'!AB88 | AC89: =+'Flujo Neto'!AC88 | ... AH89: =+'Flujo Neto'!AH88
B90: Factura o Boleta | C90: 2.2 | D90: Materiales instalación | E90: =+E18 | F90: =+Supuestos!H21 | H90: =+'Flujo Neto'!H89 | I90: =+'Flujo Neto'!I89 | J90: =+'Flujo Neto'!J89 | K90: =+'Flujo Neto'!K89 | L90: =+'Flujo Neto'!L89 | M90: =+'Flujo Neto'!M89 | N90: =+'Flujo Neto'!N89 | O90: =+'Flujo Neto'!O89 | ... T90: =+'Flujo Neto'!T89 | V90: =+'Flujo Neto'!V89 | W90: =+'Flujo Neto'!W89 | X90: =+'Flujo Neto'!X89 | Y90: =+'Flujo Neto'!Y89 | Z90: =+'Flujo Neto'!Z89 | AA90: =+'Flujo Neto'!AA89 | AB90: =+'Flujo Neto'!AB89 | AC90: =+'Flujo Neto'!AC89 | ... AH90: =+'Flujo Neto'!AH89
B91: Factura o Boleta | C91: 2.3 | D91: Herramientas | E91: =+E19 | F91: =+Supuestos!H22 | H91: =+'Flujo Neto'!H90 | I91: =+'Flujo Neto'!I90 | J91: =+'Flujo Neto'!J90 | K91: =+'Flujo Neto'!K90 | L91: =+'Flujo Neto'!L90 | M91: =+'Flujo Neto'!M90 | N91: =+'Flujo Neto'!N90 | O91: =+'Flujo Neto'!O90 | ... T91: =+'Flujo Neto'!T90 | V91: =+'Flujo Neto'!V90 | W91: =+'Flujo Neto'!W90 | X91: =+'Flujo Neto'!X90 | Y91: =+'Flujo Neto'!Y90 | Z91: =+'Flujo Neto'!Z90 | AA91: =+'Flujo Neto'!AA90 | AB91: =+'Flujo Neto'!AB90 | AC91: =+'Flujo Neto'!AC90 | ... AH91: =+'Flujo Neto'!AH90
C92: 3. | D92: Personal y Servicios | E92: =+E20 | H92: =+'Flujo Neto'!H91 | I92: =+'Flujo Neto'!I91 | J92: =+'Flujo Neto'!J91 | K92: =+'Flujo Neto'!K91 | L92: =+'Flujo Neto'!L91 | M92: =+'Flujo Neto'!M91 | N92: =+'Flujo Neto'!N91 | O92: =+'Flujo Neto'!O91 | ... T92: =+'Flujo Neto'!T91 | V92: =+'Flujo Neto'!V91 | W92: =+'Flujo Neto'!W91 | X92: =+'Flujo Neto'!X91 | Y92: =+'Flujo Neto'!Y91 | Z92: =+'Flujo Neto'!Z91 | AA92: =+'Flujo Neto'!AA91 | AB92: =+'Flujo Neto'!AB91 | AC92: =+'Flujo Neto'!AC91 | ... AH92: =+'Flujo Neto'!AH91
B93: Costo Empresa | C93: 3.1 | D93: Planilla Actual | E93: =+E21 | H93: =+'Flujo Neto'!H92 | I93: =+'Flujo Neto'!I92 | J93: =+'Flujo Neto'!J92 | K93: =+'Flujo Neto'!K92 | L93: =+'Flujo Neto'!L92 | M93: =+'Flujo Neto'!M92 | N93: =+'Flujo Neto'!N92 | O93: =+'Flujo Neto'!O92 | ... T93: =+'Flujo Neto'!T92 | V93: =+'Flujo Neto'!V92 | X93: =+'Flujo Neto'!X92 | Y93: =+'Flujo Neto'!Y92 | Z93: =+'Flujo Neto'!Z92 | AA93: =+'Flujo Neto'!AA92 | AB93: =+'Flujo Neto'!AB92 | AC93: =+'Flujo Neto'!AC92 | AD93: =+'Flujo Neto'!AD92 | AE93: =+'Flujo Neto'!AE92 | ... AH93: =+'Flujo Neto'!AH92
B94: Costo Empresa | C94: 3.2 | D94: Descarga estructura | E94: =+E22 | H94: =+'Flujo Neto'!H93 | I94: =+'Flujo Neto'!I93 | J94: =+'Flujo Neto'!J93 | K94: =+'Flujo Neto'!K93 | L94: =+'Flujo Neto'!L93 | M94: =+'Flujo Neto'!M93 | N94: =+'Flujo Neto'!N93 | O94: =+'Flujo Neto'!O93 | ... T94: =+'Flujo Neto'!T93 | V94: =+'Flujo Neto'!V93 | X94: =+'Flujo Neto'!X93 | Y94: =+'Flujo Neto'!Y93 | Z94: =+'Flujo Neto'!Z93 | AA94: =+'Flujo Neto'!AA93 | AB94: =+'Flujo Neto'!AB93 | AC94: =+'Flujo Neto'!AC93 | AD94: =+'Flujo Neto'!AD93 | AE94: =+'Flujo Neto'!AE93 | ... AH94: =+'Flujo Neto'!AH93
C95: 4. | D95: Servicios Profesionales | E95: =+E23 | H95: =+'Flujo Neto'!H94 | I95: =+'Flujo Neto'!I94 | J95: =+'Flujo Neto'!J94 | K95: =+'Flujo Neto'!K94 | L95: =+'Flujo Neto'!L94 | M95: =+'Flujo Neto'!M94 | N95: =+'Flujo Neto'!N94 | O95: =+'Flujo Neto'!O94 | ... T95: =+'Flujo Neto'!T94 | V95: =+'Flujo Neto'!V94 | W95: =+'Flujo Neto'!W94 | X95: =+'Flujo Neto'!X94 | Y95: =+'Flujo Neto'!Y94 | Z95: =+'Flujo Neto'!Z94 | AA95: =+'Flujo Neto'!AA94 | AB95: =+'Flujo Neto'!AB94 | AC95: =+'Flujo Neto'!AC94 | ... AH95: =+'Flujo Neto'!AH94
B96: Boleta Honorarios | C96: 4.1 | D96: Encargado de Logistica y Bodega | E96: =+E24 | H96: =+'Flujo Neto'!H95 | I96: =+'Flujo Neto'!I95 | J96: =+'Flujo Neto'!J95 | K96: =+'Flujo Neto'!K95 | L96: =+'Flujo Neto'!L95 | M96: =+'Flujo Neto'!M95 | N96: =+'Flujo Neto'!N95 | O96: =+'Flujo Neto'!O95 | ... T96: =+'Flujo Neto'!T95 | V96: =+'Flujo Neto'!V95 | X96: =+'Flujo Neto'!X95 | Y96: =+'Flujo Neto'!Y95 | Z96: =+'Flujo Neto'!Z95 | AA96: =+'Flujo Neto'!AA95 | AB96: =+'Flujo Neto'!AB95 | AC96: =+'Flujo Neto'!AC95 | AD96: =+'Flujo Neto'!AD95 | AE96: =+'Flujo Neto'!AE95 | ... AH96: =+'Flujo Neto'!AH95
B97: Boleta Honorarios | C97: 4.2 | D97: Técnico pago por instalación - Plan A | E97: =+E25 | H97: =+'Flujo Neto'!H96 | I97: =+'Flujo Neto'!I96 | J97: =+'Flujo Neto'!J96 | K97: =+'Flujo Neto'!K96 | L97: =+'Flujo Neto'!L96 | M97: =+'Flujo Neto'!M96 | N97: =+'Flujo Neto'!N96 | O97: =+'Flujo Neto'!O96 | ... T97: =+'Flujo Neto'!T96 | V97: =+'Flujo Neto'!V96 | W97: =+'Flujo Neto'!W96 | X97: =+'Flujo Neto'!X96 | Y97: =+'Flujo Neto'!Y96 | Z97: =+'Flujo Neto'!Z96 | AA97: =+'Flujo Neto'!AA96 | AB97: =+'Flujo Neto'!AB96 | AC97: =+'Flujo Neto'!AC96 | ... AH97: =+'Flujo Neto'!AH96
B98: Boleta Honorarios | C98: 4.3 | D98: Técnico contrato mensual - Plan B | E98: =+E26 | H98: =+'Flujo Neto'!H97 | I98: =+'Flujo Neto'!I97 | J98: =+'Flujo Neto'!J97 | K98: =+'Flujo Neto'!K97 | L98: =+'Flujo Neto'!L97 | M98: =+'Flujo Neto'!M97 | N98: =+'Flujo Neto'!N97 | O98: =+'Flujo Neto'!O97 | P98: =+'Flujo Neto'!P97 | Q98: 2 | R98: =+'Flujo Neto'!R97 | S98: =+'Flujo Neto'!S97 | T98: =+'Flujo Neto'!T97 | V98: =+'Flujo Neto'!V97 | W98: =+'Flujo Neto'!W97 | X98: =+'Flujo Neto'!X97 | Y98: =+'Flujo Neto'!Y97 | Z98: =+'Flujo Neto'!Z97 | AA98: =+'Flujo Neto'!AA97 | AB98: =+'Flujo Neto'!AB97 | AC98: =+'Flujo Neto'!AC97 | ... AH98: =+'Flujo Neto'!AH97
B99: Boleta Honorarios | C99: 4.4 | D99: Ayudante contrato mensual - Plan B | E99: =+E27 | H99: =+'Flujo Neto'!H98 | I99: =+'Flujo Neto'!I98 | J99: =+'Flujo Neto'!J98 | K99: =+'Flujo Neto'!K98 | L99: =+'Flujo Neto'!L98 | M99: =+'Flujo Neto'!M98 | N99: =+'Flujo Neto'!N98 | O99: =+'Flujo Neto'!O98 | P99: =+'Flujo Neto'!P98 | Q99: 2 | R99: =+'Flujo Neto'!R98 | S99: =+'Flujo Neto'!S98 | T99: =+'Flujo Neto'!T98 | V99: =+'Flujo Neto'!V98 | W99: =+'Flujo Neto'!W98 | X99: =+'Flujo Neto'!X98 | Y99: =+'Flujo Neto'!Y98 | Z99: =+'Flujo Neto'!Z98 | AA99: =+'Flujo Neto'!AA98 | AB99: =+'Flujo Neto'!AB98 | AC99: =+'Flujo Neto'!AC98 | ... AH99: =+'Flujo Neto'!AH98
B100: Boleta Honorarios | C100: 4.5 | D100: Personal apoyo Planos TE1 | E100: =+E28 | H100: =+'Flujo Neto'!H99 | I100: =+'Flujo Neto'!I99 | J100: =+'Flujo Neto'!J99 | K100: =+'Flujo Neto'!K99 | L100: =+'Flujo Neto'!L99 | M100: =+'Flujo Neto'!M99 | N100: =+'Flujo Neto'!N99 | O100: =+'Flujo Neto'!O99 | ... R100: =+'Flujo Neto'!R99 | S100: 30 | T100: =+'Flujo Neto'!T99 | V100: 30 | X100: =+'Flujo Neto'!X99 | Y100: =+'Flujo Neto'!Y99 | Z100: =+'Flujo Neto'!Z99 | AA100: =+'Flujo Neto'!AA99 | AB100: =+'Flujo Neto'!AB99 | AC100: =+'Flujo Neto'!AC99 | AD100: =+'Flujo Neto'!AD99 | AE100: =+'Flujo Neto'!AE99 | ... AH100: =+'Flujo Neto'!AH99
B101: Boleta Honorarios | C101: 4.6 | D101: Encargado territorial RRHH | E101: =+E29 | H101: =+'Flujo Neto'!H100 | I101: =+'Flujo Neto'!I100 | J101: =+'Flujo Neto'!J100 | K101: =+'Flujo Neto'!K100 | L101: =+'Flujo Neto'!L100 | M101: =+'Flujo Neto'!M100 | N101: =+'Flujo Neto'!N100 | O101: =+'Flujo Neto'!O100 | ... T101: =+'Flujo Neto'!T100 | V101: =+'Flujo Neto'!V100 | X101: =+'Flujo Neto'!X100 | Y101: =+'Flujo Neto'!Y100 | Z101: =+'Flujo Neto'!Z100 | AA101: =+'Flujo Neto'!AA100 | AB101: =+'Flujo Neto'!AB100 | AC101: =+'Flujo Neto'!AC100 | AD101: =+'Flujo Neto'!AD100 | AE101: =+'Flujo Neto'!AE100 | ... AH101: =+'Flujo Neto'!AH100
B102: Boleta Honorarios | C102: 4.7 | D102: Apoyo Financiero de proyecto | E102: =+E30 | H102: =+'Flujo Neto'!H101 | I102: =+'Flujo Neto'!I101 | J102: =+'Flujo Neto'!J101 | K102: =+'Flujo Neto'!K101 | L102: =+'Flujo Neto'!L101 | M102: =+'Flujo Neto'!M101 | N102: =+'Flujo Neto'!N101 | O102: =+'Flujo Neto'!O101 | ... T102: =+'Flujo Neto'!T101 | V102: =+'Flujo Neto'!V101 | X102: =+'Flujo Neto'!X101 | Y102: =+'Flujo Neto'!Y101 | Z102: =+'Flujo Neto'!Z101 | AA102: =+'Flujo Neto'!AA101 | AB102: =+'Flujo Neto'!AB101 | AC102: =+'Flujo Neto'!AC101 | AD102: =+'Flujo Neto'!AD101 | AE102: =+'Flujo Neto'!AE101 | ... AH102: =+'Flujo Neto'!AH101
B103: Boleta Honorarios | C103: 4.8 | E103: =+E31 | H103: =+'Flujo Neto'!H102 | I103: =+'Flujo Neto'!I102 | J103: =+'Flujo Neto'!J102 | K103: =+'Flujo Neto'!K102 | L103: =+'Flujo Neto'!L102 | M103: =+'Flujo Neto'!M102 | N103: =+'Flujo Neto'!N102 | O103: =+'Flujo Neto'!O102 | ... T103: =+'Flujo Neto'!T102 | V103: =+'Flujo Neto'!V102 | W103: =+'Flujo Neto'!W102 | X103: =+'Flujo Neto'!X102 | Y103: =+'Flujo Neto'!Y102 | Z103: =+'Flujo Neto'!Z102 | AA103: =+'Flujo Neto'!AA102 | AB103: =+'Flujo Neto'!AB102 | AC103: =+'Flujo Neto'!AC102 | ... AH103: =+'Flujo Neto'!AH102
B104: Boleta Honorarios | H104: =+'Flujo Neto'!H103 | I104: =+'Flujo Neto'!I103 | J104: =+'Flujo Neto'!J103 | K104: =+'Flujo Neto'!K103 | L104: =+'Flujo Neto'!L103 | M104: =+'Flujo Neto'!M103 | N104: =+'Flujo Neto'!N103 | O104: =+'Flujo Neto'!O103 | ... T104: =+'Flujo Neto'!T103 | V104: =+'Flujo Neto'!V103 | W104: =+'Flujo Neto'!W103 | X104: =+'Flujo Neto'!X103 | Y104: =+'Flujo Neto'!Y103 | Z104: =+'Flujo Neto'!Z103 | AA104: =+'Flujo Neto'!AA103 | AB104: =+'Flujo Neto'!AB103 | AC104: =+'Flujo Neto'!AC103 | ... AH104: =+'Flujo Neto'!AH103
...

Sheet Antecedentes Programa
A1: ANTECEDENTES Y CONTEXTO DEL PROGRAMA — LUZ EN CASA
A3: Antecedentes y Contexto del Programa
A4: Luz en Casa · GORE Coquimbo · Fundación acciona.org
A5: Fuente: Minuta de Proyecto + Minuta Técnica de Proyecto
B7: 1. Antecedentes y contextualización
B8: El programa Luz en Casa es una iniciativa de ACCIONA.org, la fundación corporativa de ACCIONA, orientada a llevar soluciones de electrificación con sistemas fotovoltaicos domiciliarios a hogares rurales y aislados de Chile que no cuentan con acceso estable a electricidad.
B10: El programa se implementa por primera vez en Chile en 2021, con un proyecto piloto en Caleta Maitencillo, en la Región de Coquimbo. Esta comunidad de pescadores carecía de electricidad o dependía de generadores costosos y de uso limitado. El piloto introdujo un modelo de provisión de servicio adaptado al contexto chileno, incorporando sistemas fotovoltaicos domiciliarios con operación en energía continua como alterna, capaces de alimentar electrodomésticos como refrigeradores.
B12: En 2019, aún existían cerca de 24.556 hogares sin acceso o con acceso parcial a electricidad en Chile, concentrados principalmente en regiones rurales como Coquimbo, donde se registraban cerca de 3.181 viviendas sin electrificación. Las familias dependían de velas, pilas y generadores fósiles, soluciones costosas y poco seguras. Este contexto justificó la implementación de Luz en Casa para proveer energía renovable asequible y permanente.
B14: Tras el piloto, el programa se extendió por toda la Región de Coquimbo, alcanzando comunidades costeras y precordilleranas como Los Vilos, Illapel, Canela, Combarbalá, Monte Patria, Punitaqui y Ovalle. Estas zonas incluyen principalmente familias dedicadas a la pesca, ganadería y agricultura, muy afectadas por el cambio climático.
B16: Entre 2021 y 2025, el programa benefició a más de 800 familias solo en Coquimbo, mejorando las condiciones de vida de más de 2.600 personas en 160 comunidades.
B18: En 2025, la iniciativa se amplió a la Región de Atacama, específicamente a las comunas de Caldera y Copiapó, donde se implementaron sistemas fotovoltaicos en 230 hogares aislados. Esta expansión responde a que aún existen aproximadamente 1.000 viviendas sin acceso a la red eléctrica en el país.
B20: El programa en Chile incorpora un modelo de gestión que garantiza:
B22: • | C22: Mantenimiento continuo de los equipos, asegurado mediante cuotas asequibles aportadas por los usuarios de forma mensual con destino solo a la operación del proyecto.
B24: • | C24: Un sistema de pago adaptado al territorio, utilizando las 30.000 sucursales de Caja Vecina de BancoEstado, facilitando el acceso de familias rurales a un método de pago cercano y simple.
B26: Este modelo asegura la sostenibilidad económica y técnica del programa a largo plazo, ya que con el pago de cuota se asegura un cambio de elementos a fin de su vida útil sin un costo extra para los usuarios.
B28: El acceso a electricidad estable ha promovido:
B30: • | C30: Mejora en salud, educación y conectividad digital de comunidades aisladas.
B32: • | C32: Desarrollo de actividades productivas, como conservación de alimentos, elaboración de productos y trabajo nocturno.
B34: • | C34: Reducción del uso de combustibles fósiles y, con ello, de la contaminación y los costos operativos familiares.
B36: • | C36: Generación de empleo local en técnicos eléctricos locales, a cargo de labores de mantenimiento y atención de usuarios.
B39: 2. Forma de trabajo
B40: El éxito del programa Luz en Casa en Chile se basa en una estructura operativa integral que combina coordinación institucional, trabajo comunitario, logística eficiente y un modelo de gestión orientado a la sostenibilidad.
B42: 2.1. Relacionamiento institucional y comunitario
B43: La primera etapa del programa consiste en establecer una red de coordinación con actores relevantes del territorio:
B45: 2.1.1. Instituciones públicas
B46: • | C46: Municipalidades: se coordinan acciones para diagnóstico territorial, acceso a información local y apoyo en la identificación de comunidades prioritarias.
B47: • | C47: Superintendencia de Electricidad y Combustibles (SEC): se asegura el cumplimiento de normativas y estándares técnicos.
B48: • | C48: Otros organismos sectoriales: Subsecretarías Regionales, Gobernaciones Regionales, INDAP y programas sociales de instituciones públicas.
B50: 2.1.2. Organizaciones sociales y comunitarias
B51: • | C51: Presidentes de comunidades y juntas de vecinos: actores clave en la convocatoria, registro y validación de beneficiarios.
B52: • | C52: Centros de Energía Fotovoltaica (CEF): estructuras comunitarias conformadas por Fundación acciona.org que apoyan el uso, supervisión y mantenimiento básico del sistema.
B53: • | C53: Actores productivos locales: asociaciones de pescadores, crianceros y agricultores que requieren energía para mejorar sus capacidades productivas.
B55: Esta fase permite asegurar legitimidad territorial, transparencia y participación de la comunidad en todo el proceso.
B57: 2.2. Trabajo comunitario
B58: El trabajo directo con las familias es esencial para asegurar un diseño adecuado y sostenible del proyecto. Incluye las siguientes actividades:
B60: • | C60: Reuniones con autoridades locales para presentar el programa, sus beneficios y requerimientos.
B61: • | C61: Identificación de comunidades y levantamiento documental: información preliminar de necesidades energéticas para proyectar trabajo de gabinete y recolección en terreno.
B62: • | C62: Sensibilización y jornadas informativas: se presenta el modelo de servicio, costos, equipos y compromisos mutuos, incluyendo alcances y limitaciones del equipo, registrando solo a quienes con esa información sigan interesados.
B63: • | C63: Registro de fichas de interés: las familias formalizan su intención de participar mediante documento físico que pasa a base de datos. Se revisa condición de vivienda y propiedad de terreno (requisito: residente permanente).
B64: • | C64: Encuestas socioeconómicas para priorizar hogares según vulnerabilidad, dispersión geográfica y/o urgencia energética.
B65: • | C65: Conformación de Centros Luz en Casa (CEF): red comunitaria encargada de apoyar la operación local del programa y fortalecer la apropiación comunitaria del sistema.
B67: 2.3. Suministro y logística
B68: La logística del programa combina procesos nacionales e internacionales, asegurando el suministro y buen estado de los equipos:
B70: • | C70: Compra de equipos en fábrica (Zimpertec GmbH & Co. KG, Alemania) bajo especificaciones técnicas internacionales. Tiempo de importación desde la compra: 4–5 meses.
B71: • | C71: Transporte marítimo hacia Chile, incluyendo gestión aduanera para internación: ~2 meses en proceso.
B72: • | C72: Recepción en bodega: inspección técnica y control de calidad de equipos a la llegada al país.
B73: • | C73: Contratación de personal local: contribuye al empleo comunitario y mejora la implementación en terreno.
B74: • | C74: Compra de insumos complementarios: soportes, cableado, porta soquetes, elementos de ferretería eléctrica.
B75: • | C75: Transporte de insumos entre regiones cuando no se cuente con proveedor local.
B76: • | C76: Preparación logística y contractiva: documentación de usuarios, contratos de servicio y carga de datos en sistema Proteo.
B77: • | C77: Asignación de cuadrillas de instalación según ruta y geografía.
B78: • | C78: Entrega e instalación de los sistemas fotovoltaicos, junto con capacitación básica a los usuarios.
B80: 3. Alcance técnico de los equipos suministrados
B81: Los sistemas solares domiciliarios utilizados en el proyecto Luz en Casa Chile provienen del proveedor Zimpertec GmbH & Co. KG, Alemania, fabricante especializado en soluciones solares autónomas y sistemas off-grid para electrificación rural.
B83: 3.1. Sistema Solar Domiciliario AC (SHS AC)
B84: Modelo completo: AC-LS-AC25.6V/50Ah/1.28kWh/220V/50Hz/0.9kW-HP/Termcon-a
B86: • | C86: Inversor AC: 900 W, salida nominal 220 V / 50 Hz.
B87: • | C87: Batería: Litio LFP 25.6 V / 50 Ah / 1.28 kWh, larga vida útil.
B88: • | C88: Controlador: PWM 40 A.
B89: • | C89: Salida DC: 24 V / 10 A.
B90: • | C90: Conexiones internas: AC OUT, LOAD1 OUT (DC), PANEL IN.
B91: • | C91: Gabinete: color gris, especificación especial para acciona.org.
B92: • | C92: Operación: optimizado para cargas AC básicas y picos por motores pequeños.
B94: 3.2. Panel solar fotovoltaico
B95: Modelo: SP-500-66M-S4-0.35
B97: • | C97: 500 Wp, tecnología monocristalina.
B98: • | C98: 66 celdas en serie.
B99: • | C99: Cableado S4 con terminal de 0.35 m.
B101: 3.3. Luminarias LED
B102: Modelo: SFL-12-24/05CW
B104: • | C104: 5 W.
B105: • | C105: 12/24 VDC (consumo reducido).
B106: • | C106: Cool White.
B107: • | C107: Certificaciones CE y ROHS.
B109: 4. Alcance de la instalación por vivienda
B110: Cada vivienda usuaria del programa Luz en Casa Chile recibe una instalación estandarizada, basada en el modelo AC del proveedor.
B112: 4.1. Puntos de alumbrado (DC)
B113: • | C113: 3 luminarias LED DC conectadas al sistema.
B114: • | C114: Tensión: 12/24 V DC.
B115: • | C115: Distribución interna mediante cableado premontado.
B116: • | C116: Máximo total permitido: 20 metros lineales de cableado interior por vivienda.
B118: (Este alcance está alineado al estándar de instalación de acciona.org para kit de sistemas y a la distribución típica de iluminación del SHS AC.)
B120: 4.2. Punto de energía alterna (AC)
B121: Cada vivienda recibe:
B122: • | C122: 1 toma de corriente AC, conectada al inversor integrado.
B123: • | C123: Salida: 220 V / 50 Hz.
B124: • | C124: Capacidad: cargas básicas de bajo consumo (TV pequeña, router, ventilador pequeño, laptop, etc.).
B125: • | C125: Los equipos quedan prohibidos para uso en congeladoras de gran tamaño, bombas de agua y cualquier otro elemento de alto consumo energético.
B127: Este punto permite el uso de electrodomésticos esenciales, ampliando significativamente el impacto energético respecto a soluciones de menor capacidad.
B129: 5. Proceso formal de instalación
B130: Las cuadrillas realizan el proceso bajo protocolo interno:
B132: 1. | C132: Recepción y revisión de equipos en bodega (conforme a la guía de trabajo de usuarios asignada).
B133: 2. | C133: Montaje del panel en cubierta con orientación adecuada, para buscar la máxima eficiencia.
B134: 3. | C134: Instalación del gabinete AC dentro de la vivienda, en zona segura y ventilada, validado con el propietario.
B135: 4. | C135: Instalación del circuito DC (3 luminarias, con un máximo de 20 metros lineales) y punto AC (1 enchufe a menos de 1 metro de equipo).
B136: 5. | C136: Trabajo de toma a tierra de cada equipo.
B137: 6. | C137: Pruebas de funcionamiento y verificación de tensiones.
B138: 7. | C138: Registro fotográfico y georreferenciación.
B139: 8. | C139: Firma de acta de recepción de instalaciones.
B141: 5.1. Declaración voluntaria TE-1
...

Sheet Flujo Neto
A1: FLUJO NETO (PRECIOS NETO SIN IVA) — LUZ EN CASA · GORE COQUIMBO
D4: PRECIOS NETO | P4: Voluntariado | Q4: Voluntariado | R4: Voluntariado
A5: Fuente: Minuta de Proyecto + Minuta Técnica de Proyecto | B5: Forma pago | C5: Nivel | D5: Item | E5: NETO | H5: 46023 | I5: 46054 | J5: 46082 | K5: 46113 | L5: 46143 | M5: 46174 | N5: 46204 | O5: 46235 | P5: 46266 | Q5: 46296 | R5: 46327 | S5: 46357 | T5: 2026 | V5: 46388 | W5: 46419 | X5: 46447 | Y5: 46478 | Z5: 46508 | AA5: 46539 | AB5: 46569 | AC5: 46600 | AD5: 46631 | AE5: 46661 | AF5: 46692 | AG5: 46722 | AH5: 2027 | AJ5: TOTAL
C6: 1 | D6: Compras activables ZIMPERTEC | E6: =+Supuestos!E8 | F6: =+F76 | H6: =+SUM(H6:H13) | I6: =+SUM(I6:I13) | J6: =+SUM(J6:J13) | K6: =+SUM(K6:K13) | L6: =+SUM(L6:L13) | M6: =+SUM(M6:M13) | N6: =+SUM(N6:N13) | O6: =+SUM(O6:O13) | ... S6: =+SUM(S6:S13) | T6: =SUM(H5:S5) | V6: =+SUM(V6:V13) | W6: =+SUM(W6:W13) | X6: =+SUM(X6:X13) | Y6: =+SUM(Y6:Y13) | Z6: =+SUM(Z6:Z13) | AA6: =+SUM(AA6:AA13) | AB6: =+SUM(AB6:AB13) | AC6: =+SUM(AC6:AC13) | ... AG6: =+SUM(AG6:AG13) | AH6: =SUM(V5:AG5) | AJ6: =+AH5+T5
B7: Factura | C7: 1.1 | D7: Sistemas AC | E7: =+Supuestos!E9 | F7: =+F77 | H7: =+$E6*H77 | I7: =+$E6*I77 | J7: =+$E6*J77 | K7: =+$E6*K77 | L7: =+$E6*L77 | M7: =+$E6*M77 | N7: =+$E6*N77 | O7: =+$E6*O77 | ... S7: =+$E6*S77 | V7: =+$E6*V77 | W7: =+$E6*W77 | X7: =+$E6*X77 | Y7: =+$E6*Y77 | Z7: =+$E6*Z77 | AA7: =+$E6*AA77 | AB7: =+$E6*AB77 | AC7: =+$E6*AC77 | ... AG7: =+$E6*AG77
B8: Factura | C8: 1.2 | D8: Paneles | E8: =+Supuestos!E10 | F8: =+F78 | H8: =+$E7*H78 | I8: =+$E7*I78 | J8: =+$E7*J78 | K8: =+$E7*K78 | L8: =+$E7*L78 | M8: =+$E7*M78 | N8: =+$E7*N78 | O8: =+$E7*O78 | ... S8: =+$E7*S78 | V8: =+$E7*V78 | W8: =+$E7*W78 | X8: =+$E7*X78 | Y8: =+$E7*Y78 | Z8: =+$E7*Z78 | AA8: =+$E7*AA78 | AB8: =+$E7*AB78 | AC8: =+$E7*AC78 | ... AG8: =+$E7*AG78
B9: Factura | C9: 1.3 | D9: Lamparas | E9: =+Supuestos!E11 | F9: =+F79 | H9: =+$E8*H79 | I9: =+$E8*I79 | J9: =+$E8*J79 | K9: =+$E8*K79 | L9: =+$E8*L79 | M9: =+$E8*M79 | N9: =+$E8*N79 | O9: =+$E8*O79 | ... S9: =+$E8*S79 | V9: =+$E8*V79 | W9: =+$E8*W79 | X9: =+$E8*X79 | Y9: =+$E8*Y79 | Z9: =+$E8*Z79 | AA9: =+$E8*AA79 | AB9: =+$E8*AB79 | AC9: =+$E8*AC79 | ... AG9: =+$E8*AG79
B10: El programa se implementa por primera vez en Chile en 2021, con un proyecto piloto en Caleta Maitencillo, en la Región de Coquimbo. Esta comunidad de pescadores carecía de electricidad o dependía de generadores costosos y de uso limitado. El piloto introdujo un modelo de provisión de servicio adaptado al contexto chileno, incorporando sistemas fotovoltaicos domiciliarios con operación en energía continua como alterna, capaces de alimentar electrodomésticos como refrigeradores. | C10: 1.4 | D10: Hardware Monitoreo | E10: =+Supuestos!E12 | F10: =+F80 | H10: =+$E9*H80 | I10: =+$E9*I80 | J10: =+$E9*J80 | K10: =+$E9*K80 | L10: =+$E9*L80 | M10: =+$E9*M80 | N10: =+$E9*N80 | O10: =+$E9*O80 | ... S10: =+$E9*S80 | V10: =+$E9*V80 | W10: =+$E9*W80 | X10: =+$E9*X80 | Y10: =+$E9*Y80 | Z10: =+$E9*Z80 | AA10: =+$E9*AA80 | AB10: =+$E9*AB80 | AC10: =+$E9*AC80 | ... AG10: =+$E9*AG80
B11: Factura | C11: 1.5 | D11: Software Monitoreo | E11: =+Supuestos!E13 | F11: =+F81 | H11: =+$E10*H81 | I11: =+$E10*I81 | J11: =+$E10*J81 | K11: =+$E10*K81 | L11: =+$E10*L81 | M11: =+$E10*M81 | N11: =+$E10*N81 | O11: =+$E10*O81 | ... S11: =+$E10*S81 | V11: =+$E10*V81 | W11: =+$E10*W81 | X11: =+$E10*X81 | Y11: =+$E10*Y81 | Z11: =+$E10*Z81 | AA11: =+$E10*AA81 | AB11: =+$E10*AB81 | AC11: =+$E10*AC81 | ... AG11: =+$E10*AG81
B12: Factura | C12: 1.6 | D12: Repuestos | E12: =+Supuestos!E14 | F12: =+F82 | H12: =+$E11*H82 | I12: =+$E11*I82 | J12: =+$E11*J82 | K12: =+$E11*K82 | L12: =+$E11*L82 | M12: =+$E11*M82 | N12: =+$E11*N82 | O12: =+$E11*O82 | ... S12: =+$E11*S82 | V12: =+$E11*V82 | W12: =+$E11*W82 | X12: =+$E11*X82 | Y12: =+$E11*Y82 | Z12: =+$E11*Z82 | AA12: =+$E11*AA82 | AB12: =+$E11*AB82 | AC12: =+$E11*AC82 | ... AG12: =+$E11*AG82
B13: Factura | C13: 1.7 | D13: Flete | E13: =+Supuestos!E15 | F13: =+F83 | H13: =+$E12*H83 | I13: =+$E12*I83 | J13: =+$E12*J83 | K13: =+$E12*K83 | L13: =+$E12*L83 | M13: =+$E12*M83 | N13: =+$E12*N83 | O13: =+$E12*O83 | ... S13: =+$E12*S83 | V13: =+$E12*V83 | W13: =+$E12*W83 | X13: =+$E12*X83 | Y13: =+$E12*Y83 | Z13: =+$E12*Z83 | AA13: =+$E12*AA83 | AB13: =+$E12*AB83 | AC13: =+$E12*AC83 | ... AG13: =+$E12*AG83
B14: Factura | C14: 7.2 | D14: Transporte DESCONSOLIDADO | E14: =+Supuestos!E16 | F14: =+F84 | H14: =+$E13*H84 | I14: =+$E13*I84 | J14: =+$E13*J84 | K14: =+$E13*K84 | L14: =+$E13*L84 | M14: =+$E13*M84 | N14: =+$E13*N84 | O14: =+$E13*O84 | ... S14: =+$E13*S84 | V14: =+$E13*V84 | W14: =+$E13*W84 | X14: =+$E13*X84 | Y14: =+$E13*Y84 | Z14: =+$E13*Z84 | AA14: =+$E13*AA84 | AB14: =+$E13*AB84 | AC14: =+$E13*AC84 | ... AG14: =+$E13*AG84
B15: Factura | C15: 7.5 | D15: Grúa en Origen | E15: =+Supuestos!E17 | F15: =+F85 | H15: =+$E14*H85 | I15: =+$E14*I85 | J15: =+$E14*J85 | K15: =+$E14*K85 | L15: =+$E14*L85 | M15: =+$E14*M85 | N15: =+$E14*N85 | O15: =+$E14*O85 | ... S15: =+$E14*S85 | V15: =+$E14*V85 | W15: =+$E14*W85 | X15: =+$E14*X85 | Y15: =+$E14*Y85 | Z15: =+$E14*Z85 | AA15: =+$E14*AA85 | AB15: =+$E14*AB85 | AC15: =+$E14*AC85 | ... AG15: =+$E14*AG85
B16: Factura | C16: 7.6 | D16: Grúa en Punto Destino (6 Horas) | E16: =+Supuestos!E18 | F16: =+F86 | H16: =+$E15*H86 | I16: =+$E15*I86 | J16: =+$E15*J86 | K16: =+$E15*K86 | L16: =+$E15*L86 | M16: =+$E15*M86 | N16: =+$E15*N86 | O16: =+$E15*O86 | ... S16: =+$E15*S86 | V16: =+$E15*V86 | W16: =+$E15*W86 | X16: =+$E15*X86 | Y16: =+$E15*Y86 | Z16: =+$E15*Z86 | AA16: =+$E15*AA86 | AB16: =+$E15*AB86 | AC16: =+$E15*AC86 | ... AG16: =+$E15*AG86
C17: 2 | D17: Insumos Instalación | E17: =+Supuestos!E19 | F17: =+F87 | H17: =+SUM(H17:H19) | I17: =+SUM(I17:I19) | J17: =+SUM(J17:J19) | K17: =+SUM(K17:K19) | L17: =+SUM(L17:L19) | M17: =+SUM(M17:M19) | N17: =+SUM(N17:N19) | O17: =+SUM(O17:O19) | ... S17: =+SUM(S17:S19) | T17: =SUM(H16:S16) | V17: =+SUM(V17:V19) | W17: =+SUM(W17:W19) | X17: =+SUM(X17:X19) | Y17: =+SUM(Y17:Y19) | Z17: =+SUM(Z17:Z19) | AA17: =+SUM(AA17:AA19) | AB17: =+SUM(AB17:AB19) | AC17: =+SUM(AC17:AC19) | ... AG17: =+SUM(AG17:AG19) | AH17: =SUM(V16:AG16) | AJ17: =+AH16+T16
B18: Factura | C18: 2.1 | D18: Estructura | E18: =+Supuestos!E20 | F18: =+F88 | H18: =+$E17*H88 | I18: =+$E17*I88 | J18: =+$E17*J88 | K18: =+$E17*K88 | L18: =+$E17*L88 | M18: =+$E17*M88 | N18: =+$E17*N88 | O18: =+$E17*O88 | ... S18: =+$E17*S88 | V18: =+$E17*V88 | W18: =+$E17*W88 | X18: =+$E17*X88 | Y18: =+$E17*Y88 | Z18: =+$E17*Z88 | AA18: =+$E17*AA88 | AB18: =+$E17*AB88 | AC18: =+$E17*AC88 | ... AG18: =+$E17*AG88
B19: Factura o Boleta | C19: 2.2 | D19: Materiales instalación | E19: =+Supuestos!E21 | F19: =+F89 | H19: =+$E18*H89 | I19: =+$E18*I89 | J19: =+$E18*J89 | K19: =+$E18*K89 | L19: =+$E18*L89 | M19: =+$E18*M89 | N19: =+$E18*N89 | O19: =+$E18*O89 | ... S19: =+$E18*S89 | V19: =+$E18*V89 | W19: =+$E18*W89 | X19: =+$E18*X89 | Y19: =+$E18*Y89 | Z19: =+$E18*Z89 | AA19: =+$E18*AA89 | AB19: =+$E18*AB89 | AC19: =+$E18*AC89 | ... AG19: =+$E18*AG89
B20: Factura o Boleta | C20: 2.3 | D20: Herramientas | E20: =+Supuestos!E22 | F20: =+F90 | H20: =+$E19*H90 | I20: =+$E19*I90 | J20: =+$E19*J90 | K20: =+$E19*K90 | L20: =+$E19*L90 | M20: =+$E19*M90 | N20: =+$E19*N90 | O20: =+$E19*O90 | ... S20: =+$E19*S90 | V20: =+$E19*V90 | W20: =+$E19*W90 | X20: =+$E19*X90 | Y20: =+$E19*Y90 | Z20: =+$E19*Z90 | AA20: =+$E19*AA90 | AB20: =+$E19*AB90 | AC20: =+$E19*AC90 | ... AG20: =+$E19*AG90
C21: 3. | D21: Personal y Servicios | E21: =+Supuestos!E23 | F21: =+F91 | H21: =H21+H22 | I21: =I21+I22 | J21: =J21+J22 | K21: =K21+K22 | L21: =L21+L22 | M21: =M21+M22 | N21: =N21+N22 | O21: =O21+O22 | ... S21: =S21+S22 | T21: =SUM(H20:S20) | V21: =V21+V22 | W21: =W21+W22 | X21: =X21+X22 | Y21: =Y21+Y22 | Z21: =Z21+Z22 | AA21: =AA21+AA22 | AB21: =AB21+AB22 | AC21: =AC21+AC22 | ... AG21: =AG21+AG22 | AH21: =SUM(V20:AG20) | AJ21: =+AH20+T20
B22: Costo Empresa | C22: 3.1 | D22: Planilla Actual | E22: =+Supuestos!E24 | F22: =+F92 | H22: =+$E21*H92 | I22: =+$E21*I92 | J22: =+$E21*J92 | K22: =+$E21*K92 | L22: =+$E21*L92 | M22: =+$E21*M92 | N22: =+$E21*N92 | O22: =+$E21*O92 | ... S22: =+$E21*S92 | V22: =+$E21*V92 | W22: =+$E21*W92 | X22: =+$E21*X92 | Y22: =+$E21*Y92 | Z22: =+$E21*Z92 | AA22: =+$E21*AA92 | AB22: =+$E21*AB92 | AC22: =+$E21*AC92 | ... AG22: =+$E21*AG92
C23: 3.2 | D23: Descarga Estructura | E23: =+Supuestos!E25 | H23: =+$E22*H93 | I23: =+$E22*I93 | J23: =+$E22*J93 | K23: =+$E22*K93 | L23: =+$E22*L93 | M23: =+$E22*M93 | N23: =+$E22*N93 | O23: =+$E22*O93 | ... S23: =+$E22*S93 | V23: =+$E22*V93 | W23: =+$E22*W93 | X23: =+$E22*X93 | Y23: =+$E22*Y93 | Z23: =+$E22*Z93 | AA23: =+$E22*AA93 | AB23: =+$E22*AB93 | AC23: =+$E22*AC93 | ... AG23: =+$E22*AG93
C24: 4. | D24: Servicios Profesionales | E24: =+Supuestos!E26 | F24: =+F94 | H24: =+SUM(H24:H31) | I24: =+SUM(I24:I31) | J24: =+SUM(J24:J31) | K24: =+SUM(K24:K31) | L24: =+SUM(L24:L31) | M24: =+SUM(M24:M31) | N24: =+SUM(N24:N31) | O24: =+SUM(O24:O31) | ... S24: =+SUM(S24:S31) | T24: =SUM(H23:S23) | V24: =+SUM(V24:V31) | W24: =+SUM(W24:W31) | X24: =+SUM(X24:X31) | Y24: =+SUM(Y24:Y31) | Z24: =+SUM(Z24:Z31) | AA24: =+SUM(AA24:AA31) | AB24: =+SUM(AB24:AB31) | AC24: =+SUM(AC24:AC31) | ... AG24: =+SUM(AG24:AG31) | AH24: =SUM(V23:AG23) | AJ24: =+AH23+T23
B25: Boleta Honorarios | C25: 4.1 | D25: Encargado de Logistica y Bodega | E25: =+Supuestos!E27 | F25: =+F95 | H25: =+$E24*H95 | I25: =+$E24*I95 | J25: =+$E24*J95 | K25: =+$E24*K95 | L25: =+$E24*L95 | M25: =+$E24*M95 | N25: =+$E24*N95 | O25: =+$E24*O95 | ... S25: =+$E24*S95 | V25: =+$E24*V95 | W25: =+$E24*W95 | X25: =+$E24*X95 | Y25: =+$E24*Y95 | Z25: =+$E24*Z95 | AA25: =+$E24*AA95 | AB25: =+$E24*AB95 | AC25: =+$E24*AC95 | ... AG25: =+$E24*AG95
B26: Boleta Honorarios | C26: 4.2 | D26: Técnico pago por instalación - Plan A | E26: =+Supuestos!E28 | F26: =+F96 | H26: =+$E25*H96 | I26: =+$E25*I96 | J26: =+$E25*J96 | K26: =+$E25*K96 | L26: =+$E25*L96 | M26: =+$E25*M96 | N26: =+$E25*N96 | O26: =+$E25*O96 | ... S26: =+$E25*S96 | V26: =+$E25*V96 | W26: =+$E25*W96 | X26: =+$E25*X96 | Y26: =+$E25*Y96 | Z26: =+$E25*Z96 | AA26: =+$E25*AA96 | AB26: =+$E25*AB96 | AC26: =+$E25*AC96 | ... AG26: =+$E25*AG96
B27: Boleta Honorarios | C27: 4.3 | D27: Técnico contrato mensual - Plan B | E27: =+Supuestos!E29 | F27: =+F97 | H27: =+$E26*H97 | I27: =+$E26*I97 | J27: =+$E26*J97 | K27: =+$E26*K97 | L27: =+$E26*L97 | M27: =+$E26*M97 | N27: =+$E26*N97 | O27: =+$E26*O97 | ... S27: =+$E26*S97 | V27: =+$E26*V97 | W27: =+$E26*W97 | X27: =+$E26*X97 | Y27: =+$E26*Y97 | Z27: =+$E26*Z97 | AA27: =+$E26*AA97 | AB27: =+$E26*AB97 | AC27: =+$E26*AC97 | ... AG27: =+$E26*AG97
B28: Boleta Honorarios | C28: 4.4 | D28: Ayudante contrato mensual - Plan B | E28: =+Supuestos!E30 | F28: =+F98 | H28: =+$E27*H98 | I28: =+$E27*I98 | J28: =+$E27*J98 | K28: =+$E27*K98 | L28: =+$E27*L98 | M28: =+$E27*M98 | N28: =+$E27*N98 | O28: =+$E27*O98 | ... S28: =+$E27*S98 | V28: =+$E27*V98 | W28: =+$E27*W98 | X28: =+$E27*X98 | Y28: =+$E27*Y98 | Z28: =+$E27*Z98 | AA28: =+$E27*AA98 | AB28: =+$E27*AB98 | AC28: =+$E27*AC98 | ... AG28: =+$E27*AG98
B29: Boleta Honorarios | C29: 4.5 | D29: Personal apoyo Planos TE1 | E29: =+Supuestos!E31 | F29: =+F99 | H29: =+$E28*H99 | I29: =+$E28*I99 | J29: =+$E28*J99 | K29: =+$E28*K99 | L29: =+$E28*L99 | M29: =+$E28*M99 | N29: =+$E28*N99 | O29: =+$E28*O99 | ... S29: =+$E28*S99 | V29: =+$E28*V99 | W29: =+$E28*W99 | X29: =+$E28*X99 | Y29: =+$E28*Y99 | Z29: =+$E28*Z99 | AA29: =+$E28*AA99 | AB29: =+$E28*AB99 | AC29: =+$E28*AC99 | ... AG29: =+$E28*AG99
B30: Boleta Honorarios | C30: 4.6 | D30: Encargado territorial RRHH | E30: =Supuestos!E32 | H30: =+$E29*H100 | I30: =+$E29*I100 | J30: =+$E29*J100 | K30: =+$E29*K100 | L30: =+$E29*L100 | M30: =+$E29*M100 | N30: =+$E29*N100 | O30: =+$E29*O100 | ... S30: =+$E29*S100 | V30: =+$E29*V100 | W30: =+$E29*W100 | X30: =+$E29*X100 | Y30: =+$E29*Y100 | Z30: =+$E29*Z100 | AA30: =+$E29*AA100 | AB30: =+$E29*AB100 | AC30: =+$E29*AC100 | ... AG30: =+$E29*AG100
B31: Boleta Honorarios | C31: 4.7 | D31: Apoyo Financiero de proyecto | E31: =Supuestos!E33 | H31: =+$E30*H101 | I31: =+$E30*I101 | J31: =+$E30*J101 | K31: =+$E30*K101 | L31: =+$E30*L101 | M31: =+$E30*M101 | N31: =+$E30*N101 | O31: =+$E30*O101 | ... S31: =+$E30*S101 | V31: =+$E30*V101 | W31: =+$E30*W101 | X31: =+$E30*X101 | Y31: =+$E30*Y101 | Z31: =+$E30*Z101 | AA31: =+$E30*AA101 | AB31: =+$E30*AB101 | AC31: =+$E30*AC101 | ... AG31: =+$E30*AG101
B32: Boleta Honorarios | C32: 4.8 | E32: =Supuestos!E34 | H32: =+$E31*H102 | I32: =+$E31*I102 | J32: =+$E31*J102 | K32: =+$E31*K102 | L32: =+$E31*L102 | M32: =+$E31*M102 | N32: =+$E31*N102 | O32: =+$E31*O102 | ... S32: =+$E31*S102 | V32: =+$E31*V102 | W32: =+$E31*W102 | X32: =+$E31*X102 | Y32: =+$E31*Y102 | Z32: =+$E31*Z102 | AA32: =+$E31*AA102 | AB32: =+$E31*AB102 | AC32: =+$E31*AC102 | ... AG32: =+$E31*AG102
C34: 5. | D34: Alquileres RRCC | E34: =+Supuestos!E36 | F34: =+F104 | H34: =+SUM(H34:H35) | I34: =+SUM(I34:I35) | J34: =+SUM(J34:J35) | K34: =+SUM(K34:K35) | L34: =+SUM(L34:L35) | M34: =+SUM(M34:M35) | N34: =+SUM(N34:N35) | O34: =+SUM(O34:O35) | ... S34: =+SUM(S34:S35) | T34: =SUM(H33:S33) | V34: =+SUM(V34:V35) | W34: =+SUM(W34:W35) | X34: =+SUM(X34:X35) | Y34: =+SUM(Y34:Y35) | Z34: =+SUM(Z34:Z35) | AA34: =+SUM(AA34:AA35) | AB34: =+SUM(AB34:AB35) | AC34: =+SUM(AC34:AC35) | ... AG34: =+SUM(AG34:AG35) | AH34: =SUM(V33:AG33) | AJ34: =+AH33+T33
B35: Factura | C35: 5.1 | D35: Arriendo vehículo diario - RRCC | E35: =+Supuestos!E37 | F35: =+F105 | H35: =+$E34*H105 | I35: =+$E34*I105 | J35: =+$E34*J105 | K35: =+$E34*K105 | L35: =+$E34*L105 | M35: =+$E34*M105 | N35: =+$E34*N105 | O35: =+$E34*O105 | ... S35: =+$E34*S105 | V35: =+$E34*V105 | W35: =+$E34*W105 | X35: =+$E34*X105 | Y35: =+$E34*Y105 | Z35: =+$E34*Z105 | AA35: =+$E34*AA105 | AB35: =+$E34*AB105 | AC35: =+$E34*AC105 | ... AG35: =+$E34*AG105
B36: Factura | C36: 5.2 | D36: Vehiculo RRCC | E36: =+Supuestos!E38 | F36: =+F106 | H36: =+$E35*H106 | I36: =+$E35*I106 | J36: =+$E35*J106 | K36: =+$E35*K106 | L36: =+$E35*L106 | M36: =+$E35*M106 | N36: =+$E35*N106 | O36: =+$E35*O106 | ... S36: =+$E35*S106 | V36: =+$E35*V106 | W36: =+$E35*W106 | X36: =+$E35*X106 | Y36: =+$E35*Y106 | Z36: =+$E35*Z106 | AA36: =+$E35*AA106 | AB36: =+$E35*AB106 | AC36: =+$E35*AC106 | ... AG36: =+$E35*AG106
C37: 6. | D37: Alquileres Gestión Técnica | E37: =+Supuestos!E39 | F37: =+F107 | H37: =+SUM(H37:H40) | I37: =+SUM(I37:I40) | J37: =+SUM(J37:J40) | K37: =+SUM(K37:K40) | L37: =+SUM(L37:L40) | M37: =+SUM(M37:M40) | N37: =+SUM(N37:N40) | O37: =+SUM(O37:O40) | ... S37: =+SUM(S37:S40) | T37: =SUM(H36:S36) | V37: =+SUM(V37:V40) | W37: =+SUM(W37:W40) | X37: =+SUM(X37:X40) | Y37: =+SUM(Y37:Y40) | Z37: =+SUM(Z37:Z40) | AA37: =+SUM(AA37:AA40) | AB37: =+SUM(AB37:AB40) | AC37: =+SUM(AC37:AC40) | ... AG37: =+SUM(AG37:AG40) | AH37: =SUM(V36:AG36) | AJ37: =+AH36+T36
B38: Factura | C38: 6.1 | D38: Bodega Terreno | E38: =+Supuestos!E40 | F38: =+F108 | H38: =+$E37*H108 | I38: =+$E37*I108 | J38: =+$E37*J108 | K38: =+$E37*K108 | L38: =+$E37*L108 | M38: =+$E37*M108 | N38: =+$E37*N108 | O38: =+$E37*O108 | ... S38: =+$E37*S108 | V38: =+$E37*V108 | W38: =+$E37*W108 | X38: =+$E37*X108 | Y38: =+$E37*Y108 | Z38: =+$E37*Z108 | AA38: =+$E37*AA108 | AB38: =+$E37*AB108 | AC38: =+$E37*AC108 | ... AG38: =+$E37*AG108
B39: Factura | C39: 6.2 | D39: Arriendo vehículo diario - Área Técnica | E39: =+Supuestos!E41 | F39: =+F109 | H39: =+$E38*H109 | I39: =+$E38*I109 | J39: =+$E38*J109 | K39: =+$E38*K109 | L39: =+$E38*L109 | M39: =+$E38*M109 | N39: =+$E38*N109 | O39: =+$E38*O109 | ... S39: =+$E38*S109 | V39: =+$E38*V109 | W39: =+$E38*W109 | X39: =+$E38*X109 | Y39: =+$E38*Y109 | Z39: =+$E38*Z109 | AA39: =+$E38*AA109 | AB39: =+$E38*AB109 | AC39: =+$E38*AC109 | ... AG39: =+$E38*AG109
B40: Factura | C40: 6.3 | D40: Vehiculo Instaladores | E40: =+Supuestos!E42 | F40: =+F110 | H40: =+$E39*H110 | I40: =+$E39*I110 | J40: =+$E39*J110 | K40: =+$E39*K110 | L40: =+$E39*L110 | M40: =+$E39*M110 | N40: =+$E39*N110 | O40: =+$E39*O110 | ... S40: =+$E39*S110 | V40: =+$E39*V110 | W40: =+$E39*W110 | X40: =+$E39*X110 | Y40: =+$E39*Y110 | Z40: =+$E39*Z110 | AA40: =+$E39*AA110 | AB40: =+$E39*AB110 | AC40: =+$E39*AC110 | ... AG40: =+$E39*AG110
B41: Factura | C41: 6.4 | D41: Vehiculo Transporte (Maxus Deliver 9) | E41: =+Supuestos!E43 | F41: =+F111 | H41: =+$E40*H111 | I41: =+$E40*I111 | J41: =+$E40*J111 | K41: =+$E40*K111 | L41: =+$E40*L111 | M41: =+$E40*M111 | N41: =+$E40*N111 | O41: =+$E40*O111 | ... S41: =+$E40*S111 | V41: =+$E40*V111 | W41: =+$E40*W111 | X41: =+$E40*X111 | Y41: =+$E40*Y111 | Z41: =+$E40*Z111 | AA41: =+$E40*AA111 | AB41: =+$E40*AB111 | AC41: =+$E40*AC111 | ... AG41: =+$E40*AG111
C42: 7. | D42: Transporte | E42: =+Supuestos!E44 | F42: =+F112 | H42: =+SUM(H42:H48) | I42: =+SUM(I42:I48) | J42: =+SUM(J42:J48) | K42: =+SUM(K42:K48) | L42: =+SUM(L42:L48) | M42: =+SUM(M42:M48) | N42: =+SUM(N42:N48) | O42: =+SUM(O42:O48) | ... S42: =+SUM(S42:S48) | T42: =SUM(H41:S41) | V42: =+SUM(V42:V48) | W42: =+SUM(W42:W48) | X42: =+SUM(X42:X48) | Y42: =+SUM(Y42:Y48) | Z42: =+SUM(Z42:Z48) | AA42: =+SUM(AA42:AA48) | AB42: =+SUM(AB42:AB48) | AC42: =+SUM(AC42:AC48) | ... AG42: =+SUM(AG42:AG48) | AH42: =SUM(V41:AG41) | AJ42: =+AH41+T41
B43: Factura | C43: 7.1 | D43: Transporte ZIMPERTEC | E43: =+Supuestos!E45 | F43: =+F113 | H43: =+$E42*H113 | I43: =+$E42*I113 | J43: =+$E42*J113 | K43: =+$E42*K113 | L43: =+$E42*L113 | M43: =+$E42*M113 | N43: =+$E42*N113 | O43: =+$E42*O113 | ... S43: =+$E42*S113 | V43: =+$E42*V113 | W43: =+$E42*W113 | X43: =+$E42*X113 | Y43: =+$E42*Y113 | Z43: =+$E42*Z113 | AA43: =+$E42*AA113 | AB43: =+$E42*AB113 | AC43: =+$E42*AC113 | ... AG43: =+$E42*AG113
B45: Factura | C45: 7.3 | D45: Traslado Contenedor (ida y vuelta) | E45: =+Supuestos!E47 | F45: =+F115 | H45: =+$E44*H115 | I45: =+$E44*I115 | J45: =+$E44*J115 | K45: =+$E44*K115 | L45: =+$E44*L115 | M45: =+$E44*M115 | N45: =+$E44*N115 | O45: =+$E44*O115 | ... S45: =+$E44*S115 | V45: =+$E44*V115 | W45: =+$E44*W115 | X45: =+$E44*X115 | Y45: =+$E44*Y115 | Z45: =+$E44*Z115 | AA45: =+$E44*AA115 | AB45: =+$E44*AB115 | AC45: =+$E44*AC115 | ... AG45: =+$E44*AG115
B46: Factura | C46: 7.4 | D46: Camión Transporte Origen - Punto Destino (RAMPLA ABIERTA) | E46: =+Supuestos!E48 | F46: =+F116 | H46: =+$E45*H116 | I46: =+$E45*I116 | J46: =+$E45*J116 | K46: =+$E45*K116 | L46: =+$E45*L116 | M46: =+$E45*M116 | N46: =+$E45*N116 | O46: =+$E45*O116 | ... S46: =+$E45*S116 | V46: =+$E45*V116 | W46: =+$E45*W116 | X46: =+$E45*X116 | Y46: =+$E45*Y116 | Z46: =+$E45*Z116 | AA46: =+$E45*AA116 | AB46: =+$E45*AB116 | AC46: =+$E45*AC116 | ... AG46: =+$E45*AG116
B49: Factura | C49: 7.7 | D49: Camión Transporte Origen - Punto Destino (Camión cerrado) | E49: =+Supuestos!E51 | F49: =+F119 | H49: =+$E48*H119 | I49: =+$E48*I119 | J49: =+$E48*J119 | K49: =+$E48*K119 | L49: =+$E48*L119 | M49: =+$E48*M119 | N49: =+$E48*N119 | O49: =+$E48*O119 | ... S49: =+$E48*S119 | V49: =+$E48*V119 | W49: =+$E48*W119 | X49: =+$E48*X119 | Y49: =+$E48*Y119 | Z49: =+$E48*Z119 | AA49: =+$E48*AA119 | AB49: =+$E48*AB119 | AC49: =+$E48*AC119 | ... AG49: =+$E48*AG119
C50: 8. | D50: Viajes RRCC | E50: =+Supuestos!E52 | F50: =+F120 | H50: =+SUM(H50:H55) | I50: =+SUM(I50:I55) | J50: =+SUM(J50:J55) | K50: =+SUM(K50:K55) | L50: =+SUM(L50:L55) | M50: =+SUM(M50:M55) | N50: =+SUM(N50:N55) | O50: =+SUM(O50:O55) | ... S50: =+SUM(S50:S55) | T50: =SUM(H49:S49) | V50: =+SUM(V50:V55) | W50: =+SUM(W50:W55) | X50: =+SUM(X50:X55) | Y50: =+SUM(Y50:Y55) | Z50: =+SUM(Z50:Z55) | AA50: =+SUM(AA50:AA55) | AB50: =+SUM(AB50:AB55) | AC50: =+SUM(AC50:AC55) | ... AG50: =+SUM(AG50:AG55) | AH50: =SUM(V49:AG49) | AJ50: =+AH49+T49
B51: Factura | C51: 8.1 | D51: Traslados de personal | E51: =+Supuestos!E53 | F51: =+F121 | H51: =+$E50*H121 | I51: =+$E50*I121 | J51: =+$E50*J121 | K51: =+$E50*K121 | L51: =+$E50*L121 | M51: =+$E50*M121 | N51: =+$E50*N121 | O51: =+$E50*O121 | ... S51: =+$E50*S121 | V51: =+$E50*V121 | W51: =+$E50*W121 | X51: =+$E50*X121 | Y51: =+$E50*Y121 | Z51: =+$E50*Z121 | AA51: =+$E50*AA121 | AB51: =+$E50*AB121 | AC51: =+$E50*AC121 | ... AG51: =+$E50*AG121
B52: Factura o Boleta | C52: 8.2 | D52: Alojamiento | E52: =+Supuestos!E54 | F52: =+F122 | H52: =+$E51*H122 | I52: =+$E51*I122 | J52: =+$E51*J122 | K52: =+$E51*K122 | L52: =+$E51*L122 | M52: =+$E51*M122 | N52: =+$E51*N122 | O52: =+$E51*O122 | ... S52: =+$E51*S122 | V52: =+$E51*V122 | W52: =+$E51*W122 | X52: =+$E51*X122 | Y52: =+$E51*Y122 | Z52: =+$E51*Z122 | AA52: =+$E51*AA122 | AB52: =+$E51*AB122 | AC52: =+$E51*AC122 | ... AG52: =+$E51*AG122
B53: Boleta | C53: 8.3 | D53: Alimentación | E53: =+Supuestos!G55 | F53: =+F123 | H53: =+$E52*H123 | I53: =+$E52*I123 | J53: =+$E52*J123 | K53: =+$E52*K123 | L53: =+$E52*L123 | M53: =+$E52*M123 | N53: =+$E52*N123 | O53: =+$E52*O123 | ... S53: =+$E52*S123 | V53: =+$E52*V123 | W53: =+$E52*W123 | X53: =+$E52*X123 | Y53: =+$E52*Y123 | Z53: =+$E52*Z123 | AA53: =+$E52*AA123 | AB53: =+$E52*AB123 | AC53: =+$E52*AC123 | ... AG53: =+$E52*AG123
B54: Factura o Boleta | C54: 8.4 | D54: Combustible arriendo diario | E54: =+Supuestos!G56 | F54: =+F124 | H54: =+$E53*H124 | I54: =+$E53*I124 | J54: =+$E53*J124 | K54: =+$E53*K124 | L54: =+$E53*L124 | M54: =+$E53*M124 | N54: =+$E53*N124 | O54: =+$E53*O124 | ... S54: =+$E53*S124 | V54: =+$E53*V124 | W54: =+$E53*W124 | X54: =+$E53*X124 | Y54: =+$E53*Y124 | Z54: =+$E53*Z124 | AA54: =+$E53*AA124 | AB54: =+$E53*AB124 | AC54: =+$E53*AC124 | ... AG54: =+$E53*AG124
B55: Factura o Boleta | C55: 8.5 | D55: Combustible arriendo mensual | E55: =+Supuestos!E57 | F55: =+F125 | H55: =+$E54*H125 | I55: =+$E54*I125 | J55: =+$E54*J125 | K55: =+$E54*K125 | L55: =+$E54*L125 | M55: =+$E54*M125 | N55: =+$E54*N125 | O55: =+$E54*O125 | ... S55: =+$E54*S125 | V55: =+$E54*V125 | W55: =+$E54*W125 | X55: =+$E54*X125 | Y55: =+$E54*Y125 | Z55: =+$E54*Z125 | AA55: =+$E54*AA125 | AB55: =+$E54*AB125 | AC55: =+$E54*AC125 | ... AG55: =+$E54*AG125
B56: Boleta | C56: 8.6 | D56: Peajes | E56: =+Supuestos!G58 | F56: =+F126 | H56: =+$E55*H126 | I56: =+$E55*I126 | J56: =+$E55*J126 | K56: =+$E55*K126 | L56: =+$E55*L126 | M56: =+$E55*M126 | N56: =+$E55*N126 | O56: =+$E55*O126 | ... S56: =+$E55*S126 | V56: =+$E55*V126 | W56: =+$E55*W126 | X56: =+$E55*X126 | Y56: =+$E55*Y126 | Z56: =+$E55*Z126 | AA56: =+$E55*AA126 | AB56: =+$E55*AB126 | AC56: =+$E55*AC126 | ... AG56: =+$E55*AG126
C57: 9. | D57: Viajes Gestión Técnica | E57: =+Supuestos!E59 | F57: =+F127 | H57: =+SUM(H57:H62) | I57: =+SUM(I57:I62) | J57: =+SUM(J57:J62) | K57: =+SUM(K57:K62) | L57: =+SUM(L57:L62) | M57: =+SUM(M57:M62) | N57: =+SUM(N57:N62) | O57: =+SUM(O57:O62) | ... S57: =+SUM(S57:S62) | T57: =SUM(H56:S56) | V57: =+SUM(V57:V62) | W57: =+SUM(W57:W62) | X57: =+SUM(X57:X62) | Y57: =+SUM(Y57:Y62) | Z57: =+SUM(Z57:Z62) | AA57: =+SUM(AA57:AA62) | AB57: =+SUM(AB57:AB62) | AC57: =+SUM(AC57:AC62) | ... AG57: =+SUM(AG57:AG62) | AH57: =SUM(V56:AG56) | AJ57: =+AH56+T56
B58: Factura | C58: 9.1 | D58: Traslados de personal | E58: =+Supuestos!E60 | F58: =+F128 | H58: =+$E57*H128 | I58: =+$E57*I128 | J58: =+$E57*J128 | K58: =+$E57*K128 | L58: =+$E57*L128 | M58: =+$E57*M128 | N58: =+$E57*N128 | O58: =+$E57*O128 | ... S58: =+$E57*S128 | V58: =+$E57*V128 | W58: =+$E57*W128 | X58: =+$E57*X128 | Y58: =+$E57*Y128 | Z58: =+$E57*Z128 | AA58: =+$E57*AA128 | AB58: =+$E57*AB128 | AC58: =+$E57*AC128 | ... AG58: =+$E57*AG128
B59: Factura o Boleta | C59: 9.2 | D59: Alojamiento | E59: =+Supuestos!E61 | F59: =+F129 | H59: =+$E58*H129 | I59: =+$E58*I129 | J59: =+$E58*J129 | K59: =+$E58*K129 | L59: =+$E58*L129 | M59: =+$E58*M129 | N59: =+$E58*N129 | O59: =+$E58*O129 | ... S59: =+$E58*S129 | V59: =+$E58*V129 | W59: =+$E58*W129 | X59: =+$E58*X129 | Y59: =+$E58*Y129 | Z59: =+$E58*Z129 | AA59: =+$E58*AA129 | AB59: =+$E58*AB129 | AC59: =+$E58*AC129 | ... AG59: =+$E58*AG129
B60: Boleta | C60: 9.3 | D60: Alimentación | E60: =+Supuestos!G55 | F60: =+F130 | H60: =+$E59*H130 | I60: =+$E59*I130 | J60: =+$E59*J130 | K60: =+$E59*K130 | L60: =+$E59*L130 | M60: =+$E59*M130 | N60: =+$E59*N130 | O60: =+$E59*O130 | ... S60: =+$E59*S130 | V60: =+$E59*V130 | W60: =+$E59*W130 | X60: =+$E59*X130 | Y60: =+$E59*Y130 | Z60: =+$E59*Z130 | AA60: =+$E59*AA130 | AB60: =+$E59*AB130 | AC60: =+$E59*AC130 | ... AG60: =+$E59*AG130
B61: Factura o Boleta | C61: 9.4 | D61: Combustible arriendo diario | E61: =+Supuestos!G63 | F61: =+F131 | H61: =+$E60*H131 | I61: =+$E60*I131 | J61: =+$E60*J131 | K61: =+$E60*K131 | L61: =+$E60*L131 | M61: =+$E60*M131 | N61: =+$E60*N131 | O61: =+$E60*O131 | ... S61: =+$E60*S131 | V61: =+$E60*V131 | W61: =+$E60*W131 | X61: =+$E60*X131 | Y61: =+$E60*Y131 | Z61: =+$E60*Z131 | AA61: =+$E60*AA131 | AB61: =+$E60*AB131 | AC61: =+$E60*AC131 | ... AG61: =+$E60*AG131
B62: Factura o Boleta | C62: 9.5 | D62: Combustible arriendo mensual | E62: =+Supuestos!E64 | F62: =+F132 | H62: =+$E61*H132 | I62: =+$E61*I132 | J62: =+$E61*J132 | K62: =+$E61*K132 | L62: =+$E61*L132 | M62: =+$E61*M132 | N62: =+$E61*N132 | O62: =+$E61*O132 | ... S62: =+$E61*S132 | V62: =+$E61*V132 | W62: =+$E61*W132 | X62: =+$E61*X132 | Y62: =+$E61*Y132 | Z62: =+$E61*Z132 | AA62: =+$E61*AA132 | AB62: =+$E61*AB132 | AC62: =+$E61*AC132 | ... AG62: =+$E61*AG132
B63: Boleta | C63: 9.6 | D63: Peajes | E63: =+Supuestos!G65 | F63: =+F133 | H63: =+$E62*H133 | I63: =+$E62*I133 | J63: =+$E62*J133 | K63: =+$E62*K133 | L63: =+$E62*L133 | M63: =+$E62*M133 | N63: =+$E62*N133 | O63: =+$E62*O133 | ... S63: =+$E62*S133 | V63: =+$E62*V133 | W63: =+$E62*W133 | X63: =+$E62*X133 | Y63: =+$E62*Y133 | Z63: =+$E62*Z133 | AA63: =+$E62*AA133 | AB63: =+$E62*AB133 | AC63: =+$E62*AC133 | ... AG63: =+$E62*AG133
C64: 10. | D64: Gastos Varios | E64: =+Supuestos!E66 | F64: =+F134 | H64: =+SUM(H64:H68) | I64: =+SUM(I64:I68) | J64: =+SUM(J64:J68) | K64: =+SUM(K64:K68) | L64: =+SUM(L64:L68) | M64: =+SUM(M64:M68) | N64: =+SUM(N64:N68) | O64: =+SUM(O64:O68) | ... S64: =+SUM(S64:S68) | T64: =SUM(H63:S63) | V64: =+SUM(V64:V68) | W64: =+SUM(W64:W68) | X64: =+SUM(X64:X68) | Y64: =+SUM(Y64:Y68) | Z64: =+SUM(Z64:Z68) | AA64: =+SUM(AA64:AA68) | AB64: =+SUM(AB64:AB68) | AC64: =+SUM(AC64:AC68) | ... AG64: =+SUM(AG64:AG68) | AH64: =SUM(V63:AG63) | AJ64: =+AH63+T63
B65: Boleta | C65: 10.1 | D65: Compras de Equipos, EEPP, Otros | E65: =+Supuestos!E67 | F65: =+F135 | H65: =+$E64*H135 | I65: =+$E64*I135 | J65: =+$E64*J135 | K65: =+$E64*K135 | L65: =+$E64*L135 | M65: =+$E64*M135 | N65: =+$E64*N135 | O65: =+$E64*O135 | ... S65: =+$E64*S135 | V65: =+$E64*V135 | W65: =+$E64*W135 | X65: =+$E64*X135 | Y65: =+$E64*Y135 | Z65: =+$E64*Z135 | AA65: =+$E64*AA135 | AB65: =+$E64*AB135 | AC65: =+$E64*AC135 | ... AG65: =+$E64*AG135
B66: Boleta | C66: 10.2 | D66: Mensajerias (Correo de Chile) | E66: =+Supuestos!E68 | F66: =+F136 | H66: =+$E65*H136 | I66: =+$E65*I136 | J66: =+$E65*J136 | K66: =+$E65*K136 | L66: =+$E65*L136 | M66: =+$E65*M136 | N66: =+$E65*N136 | O66: =+$E65*O136 | ... S66: =+$E65*S136 | V66: =+$E65*V136 | W66: =+$E65*W136 | X66: =+$E65*X136 | Y66: =+$E65*Y136 | Z66: =+$E65*Z136 | AA66: =+$E65*AA136 | AB66: =+$E65*AB136 | AC66: =+$E65*AC136 | ... AG66: =+$E65*AG136
B67: Factura + Boleta | C67: 10.3 | D67: Impresión de manuales | E67: =+Supuestos!E69 | F67: =+F137 | H67: =+$E66*H137 | I67: =+$E66*I137 | J67: =+$E66*J137 | K67: =+$E66*K137 | L67: =+$E66*L137 | M67: =+$E66*M137 | N67: =+$E66*N137 | O67: =+$E66*O137 | ... S67: =+$E66*S137 | V67: =+$E66*V137 | W67: =+$E66*W137 | X67: =+$E66*X137 | Y67: =+$E66*Y137 | Z67: =+$E66*Z137 | AA67: =+$E66*AA137 | AB67: =+$E66*AB137 | AC67: =+$E66*AC137 | ... AG67: =+$E66*AG137
B68: Factura + Boleta | C68: 10.4 | D68: Mantención y reparación de Vehículos | E68: 0 | F68: =+F138 | H68: =+$E67*H138 | I68: =+$E67*I138 | J68: =+$E67*J138 | K68: =+$E67*K138 | L68: =+$E67*L138 | M68: =+$E67*M138 | N68: =+$E67*N138 | O68: =+$E67*O138 | ... S68: =+$E67*S138 | V68: =+$E67*V138 | W68: =+$E67*W138 | X68: =+$E67*X138 | Y68: =+$E67*Y138 | Z68: =+$E67*Z138 | AA68: =+$E67*AA138 | AB68: =+$E67*AB138 | AC68: =+$E67*AC138 | ... AG68: =+$E67*AG138
B69: Boleta | C69: 10.5 | D69: Otros varios | E69: =+Supuestos!E71 | F69: =+F139 | H69: =+$E68*H139 | I69: =+$E68*I139 | J69: =+$E68*J139 | K69: =+$E68*K139 | L69: =+$E68*L139 | M69: =+$E68*M139 | N69: =+$E68*N139 | O69: =+$E68*O139 | ... S69: =+$E68*S139 | V69: =+$E68*V139 | W69: =+$E68*W139 | X69: =+$E68*X139 | Y69: =+$E68*Y139 | Z69: =+$E68*Z139 | AA69: =+$E68*AA139 | AB69: =+$E68*AB139 | AC69: =+$E68*AC139 | ... AG69: =+$E68*AG139
AJ70: =SUM(AJ5:AJ68) | AK70: TOTAL
AJ71: =AJ69/60
D75: CANTIDAD | O75: 0.3 | R75: 0.5 | S75: 0.2
B76: Forma pago | C76: Nivel | D76: Item | E76: Cantidad | F76: Cantidad | H76: 46023 | I76: 46054 | J76: 46082 | K76: 46113 | L76: 46143 | M76: 46174 | N76: 46204 | O76: 46235 | P76: 46266 | Q76: 46296 | R76: 46327 | S76: 46357 | T76: 2026 | V76: 46388 | W76: 46419 | X76: 46447 | Y76: 46478 | Z76: 46508 | AA76: 46539 | AB76: 46569 | AC76: 46600 | AD76: 46631 | AE76: 46661 | AF76: 46692 | AG76: 46722 | AH76: 2027
C77: 1 | D77: Compras activables ZIMPERTEC | E77: =+E5 | H77: 0 | I77: 0 | J77: 0 | K77: 0 | L77: 0 | M77: 0 | N77: 0 | O77: 0 | P77: 0 | Q77: 0 | R77: 0 | S77: 0 | V77: 0 | W77: 0 | X77: 0 | Y77: 0 | Z77: 0 | AA77: 0 | AB77: 0 | AC77: 0 | AD77: 0 | AE77: 0 | AF77: 0 | AG77: 0
B78: Factura | C78: 1.1 | D78: Sistemas AC | E78: =+E6 | F78: =+Supuestos!H9 | H78: =+$F77*H$74 | I78: =+$F77*I$74 | J78: =+$F77*J$74 | K78: =+$F77*K$74 | L78: =+$F77*L$74 | M78: =+$F77*M$74 | N78: =+$F77*N$74 | O78: =+$F77*O$74 | ... S78: =+$F77*S$74 | V78: =+$F77*V$74 | W78: =+$F77*W$74 | X78: =+$F77*X$74 | Y78: =+$F77*Y$74 | Z78: =+$F77*Z$74 | AA78: =+$F77*AA$74 | AB78: =+$F77*AB$74 | AC78: =+$F77*AC$74 | ... AG78: =+$F77*AG$74
B79: Factura | C79: 1.2 | D79: Paneles | E79: =+E7 | F79: =+Supuestos!H10 | H79: =+$F78*H$74 | I79: =+$F78*I$74 | J79: =+$F78*J$74 | K79: =+$F78*K$74 | L79: =+$F78*L$74 | M79: =+$F78*M$74 | N79: =+$F78*N$74 | O79: =+$F78*O$74 | ... S79: =+$F78*S$74 | V79: =+$F78*V$74 | W79: =+$F78*W$74 | X79: =+$F78*X$74 | Y79: =+$F78*Y$74 | Z79: =+$F78*Z$74 | AA79: =+$F78*AA$74 | AB79: =+$F78*AB$74 | AC79: =+$F78*AC$74 | ... AG79: =+$F78*AG$74
B80: Factura | C80: 1.3 | D80: Lamparas | E80: =+E8 | F80: =+Supuestos!H11 | H80: =+$F79*H$74 | I80: =+$F79*I$74 | J80: =+$F79*J$74 | K80: =+$F79*K$74 | L80: =+$F79*L$74 | M80: =+$F79*M$74 | N80: =+$F79*N$74 | O80: =+$F79*O$74 | ... S80: =+$F79*S$74 | V80: =+$F79*V$74 | W80: =+$F79*W$74 | X80: =+$F79*X$74 | Y80: =+$F79*Y$74 | Z80: =+$F79*Z$74 | AA80: =+$F79*AA$74 | AB80: =+$F79*AB$74 | AC80: =+$F79*AC$74 | ... AG80: =+$F79*AG$74
B81: Factura | C81: 1.4 | D81: Hardware Monitoreo | E81: =+E9 | F81: =+Supuestos!H12 | H81: =+$F80*H$74 | I81: =+$F80*I$74 | J81: =+$F80*J$74 | K81: =+$F80*K$74 | L81: =+$F80*L$74 | M81: =+$F80*M$74 | N81: =+$F80*N$74 | O81: =+$F80*O$74 | ... S81: =+$F80*S$74 | V81: =+$F80*V$74 | W81: =+$F80*W$74 | X81: =+$F80*X$74 | Y81: =+$F80*Y$74 | Z81: =+$F80*Z$74 | AA81: =+$F80*AA$74 | AB81: =+$F80*AB$74 | AC81: =+$F80*AC$74 | ... AG81: =+$F80*AG$74
B82: Factura | C82: 1.5 | D82: Software Monitoreo | E82: =+E10 | F82: =+Supuestos!H13 | H82: =+$F81*H$74 | I82: =+$F81*I$74 | J82: =+$F81*J$74 | K82: =+$F81*K$74 | L82: =+$F81*L$74 | M82: =+$F81*M$74 | N82: =+$F81*N$74 | O82: =+$F81*O$74 | ... S82: =+$F81*S$74 | V82: =+$F81*V$74 | W82: =+$F81*W$74 | X82: =+$F81*X$74 | Y82: =+$F81*Y$74 | Z82: =+$F81*Z$74 | AA82: =+$F81*AA$74 | AB82: =+$F81*AB$74 | AC82: =+$F81*AC$74 | ... AG82: =+$F81*AG$74
B83: Factura | C83: 1.6 | D83: Repuestos | E83: =+E11 | F83: 1 | H83: =+$F82*H$74 | I83: =+$F82*I$74 | J83: =+$F82*J$74 | K83: =+$F82*K$74 | L83: =+$F82*L$74 | M83: =+$F82*M$74 | N83: =+$F82*N$74 | O83: =+$F82*O$74 | ... S83: =+$F82*S$74 | V83: =+$F82*V$74 | W83: =+$F82*W$74 | X83: =+$F82*X$74 | Y83: =+$F82*Y$74 | Z83: =+$F82*Z$74 | AA83: =+$F82*AA$74 | AB83: =+$F82*AB$74 | AC83: =+$F82*AC$74 | ... AG83: =+$F82*AG$74
B84: Factura | C84: 1.7 | D84: Flete | E84: =+E12 | F84: =+Supuestos!H15 | H84: =+$F83*H$74 | I84: =+$F83*I$74 | J84: =+$F83*J$74 | K84: =+$F83*K$74 | L84: =+$F83*L$74 | M84: =+$F83*M$74 | N84: =+$F83*N$74 | O84: =+$F83*O$74 | ... S84: =+$F83*S$74 | V84: =+$F83*V$74 | W84: =+$F83*W$74 | X84: =+$F83*X$74 | Y84: =+$F83*Y$74 | Z84: =+$F83*Z$74 | AA84: =+$F83*AA$74 | AB84: =+$F83*AB$74 | AC84: =+$F83*AC$74 | ... AG84: =+$F83*AG$74
B85: Factura | C85: 7.2 | D85: Transporte DESCONSOLIDADO | E85: =+E13 | H85: 0 | I85: 0 | J85: 0 | K85: 0 | L85: 0 | M85: 0 | N85: 0 | O85: 0 | P85: 0 | R85: 1 | S85: 0 | V85: 0 | W85: 0 | X85: 0 | Y85: 0 | Z85: 0 | AA85: 0 | AB85: 0 | AC85: 0 | AD85: 0 | AE85: 0 | AF85: 0 | AG85: 0
B86: Factura | C86: 7.5 | D86: Grúa en Origen | E86: =+E14 | H86: 0 | I86: 0 | J86: 0 | K86: 0 | L86: 0 | M86: 0 | N86: 0 | O86: 0 | P86: 0 | R86: 1 | S86: 0 | V86: 0 | W86: 0 | X86: 0 | Y86: 0 | Z86: 0 | AA86: 0 | AB86: 0 | AC86: 0 | AD86: 0 | AE86: 0 | AF86: 0 | AG86: 0
B87: Factura | C87: 7.6 | D87: Grúa en Punto Destino (6 Horas) | E87: =+E15 | H87: 0 | I87: 0 | J87: 0 | K87: 0 | L87: 0 | M87: 0 | N87: 0 | O87: 0 | P87: 0 | R87: 1 | S87: 0 | V87: 0 | W87: 0 | X87: 0 | Y87: 0 | Z87: 0 | AA87: 0 | AB87: 0 | AC87: 0 | AD87: 0 | AE87: 0 | AF87: 0 | AG87: 0
C88: 2 | D88: Insumos Instalación | E88: =+E16 | H88: 0 | I88: 0 | J88: 0 | K88: 0 | L88: 0 | M88: 0 | N88: 0 | O88: 0 | P88: 0 | Q88: 0 | R88: 0 | S88: 0 | V88: 0 | W88: 0 | X88: 0 | Y88: 0 | Z88: 0 | AA88: 0 | AB88: 0 | AC88: 0 | AD88: 0 | AE88: 0 | AF88: 0 | AG88: 0
B89: Factura | C89: 2.1 | D89: Estructura | E89: =+E17 | F89: =+Supuestos!H20 | H89: 0 | I89: 0 | J89: 0 | K89: 0 | L89: 0 | M89: 0 | N89: 0 | O89: 0 | P89: 0 | Q89: 0 | R89: =F88 | S89: 0 | V89: 0 | W89: 0 | X89: 0 | Y89: 0 | Z89: 0 | AA89: 0 | AB89: 0 | AC89: 0 | AD89: 0 | AE89: 0 | AF89: 0 | AG89: 0
B90: Factura o Boleta | C90: 2.2 | D90: Materiales instalación | E90: =+E18 | F90: =+Supuestos!H21 | H90: 0 | I90: 0 | J90: 0 | K90: 0 | L90: 0 | M90: 0 | N90: 0 | O90: 0 | P90: 0 | Q90: 0 | R90: =F89 | S90: 0 | V90: 0 | W90: 0 | X90: 0 | Y90: 0 | Z90: 0 | AA90: 0 | AB90: 0 | AC90: 0 | AD90: 0 | AE90: 0 | AF90: 0 | AG90: 0
B91: Factura o Boleta | C91: 2.3 | D91: Herramientas | E91: =+E19 | F91: =+Supuestos!H22 | H91: 0 | I91: 0 | J91: 0 | K91: 0 | L91: 0 | M91: 0 | N91: 0 | O91: 0 | P91: 0 | Q91: 0 | R91: =F90 | S91: 0 | V91: 0 | W91: 0 | X91: 0 | Y91: 0 | Z91: 0 | AA91: 0 | AB91: 0 | AC91: 0 | AD91: 0 | AE91: 0 | AF91: 0 | AG91: 0
C92: 3. | D92: Personal y Servicios | E92: =+E20 | H92: 0 | I92: 0 | J92: 0 | K92: 0 | L92: 0 | M92: 0 | N92: 0 | O92: 0 | P92: 0 | Q92: 0 | R92: 0 | S92: 0 | V92: 0 | W92: 0 | X92: 0 | Y92: 0 | Z92: 0 | AA92: 0 | AB92: 0 | AC92: 0 | AD92: 0 | AE92: 0 | AF92: 0 | AG92: 0
B93: Costo Empresa | C93: 3.1 | D93: Planilla Actual | E93: =+E21 | H93: 0 | I93: 0 | J93: 0 | K93: 0 | L93: 0 | M93: 0 | N93: 0 | O93: 1 | P93: 1 | Q93: 1 | R93: 1 | S93: 1 | V93: 1 | AA93: 0 | AB93: 0 | AC93: 0 | AD93: 0 | AE93: 0 | AF93: 0 | AG93: 0
B94: Costo Empresa | C94: 3.2 | D94: Descarga Estructura | E94: =Supuestos!E25 | H94: 0 | I94: 0 | J94: 0 | K94: 0 | L94: 0 | M94: 0 | N94: 0 | O94: 1 | P94: 1 | Q94: 1 | R94: 1 | S94: 1 | V94: 1 | AA94: 0 | AB94: 0 | AC94: 0 | AD94: 0 | AE94: 0 | AF94: 0 | AG94: 0
C95: 4. | D95: Servicios Profesionales | E95: =+E23 | H95: 0 | I95: 0 | J95: 0 | K95: 0 | L95: 0 | M95: 0 | N95: 0 | O95: 0 | P95: 0 | Q95: 0 | R95: 0 | S95: 0 | V95: 0 | X95: 0 | Y95: 0 | Z95: 0 | AA95: 0 | AB95: 0 | AC95: 0 | AD95: 0 | AE95: 0 | AF95: 0 | AG95: 0
B96: Boleta Honorarios | C96: 4.1 | D96: Encargado de Logistica y Bodega | E96: =+E24 | H96: 0 | I96: 0 | J96: 0 | K96: 0 | L96: 0 | M96: 0 | N96: 0 | O96: 0 | P96: 0 | Q96: 1 | R96: 1 | S96: 1 | AA96: 0 | AB96: 0 | AC96: 0 | AD96: 0 | AE96: 0 | AF96: 0 | AG96: 0
B97: Boleta Honorarios | C97: 4.2 | D97: Técnico pago por instalación - Plan A | E97: =+E25 | H97: 0 | I97: 0 | J97: 0 | K97: 0 | L97: 0 | M97: 0 | N97: 0 | O97: 0 | P97: 0 | Q97: 0 | R97: 0 | S97: 0 | V97: 0 | W97: 0 | Z97: 0 | AA97: 0 | AB97: 0 | AC97: 0 | AD97: 0 | AE97: 0 | AF97: 0 | AG97: 0
B98: Boleta Honorarios | C98: 4.3 | D98: Técnico contrato mensual - Plan B | E98: =+E26 | H98: 0 | I98: 0 | J98: 0 | K98: 0 | L98: 0 | M98: 0 | N98: 0 | O98: 0 | P98: 0 | Q98: 1 | R98: 2 | S98: 2 | X98: 0 | Y98: 0 | Z98: 0 | AA98: 0 | AB98: 0 | AC98: 0 | AD98: 0 | AE98: 0 | AF98: 0 | AG98: 0
B99: Boleta Honorarios | C99: 4.4 | D99: Ayudante contrato mensual - Plan B | E99: =+E27 | H99: 0 | I99: 0 | J99: 0 | K99: 0 | L99: 0 | M99: 0 | N99: 0 | O99: 0 | P99: 0 | Q99: 1 | R99: 2 | S99: 2 | X99: 0 | Y99: 0 | Z99: 0 | AA99: 0 | AB99: 0 | AC99: 0 | AD99: 0 | AE99: 0 | AF99: 0 | AG99: 0
B100: Boleta Honorarios | C100: 4.5 | D100: Personal apoyo Planos TE1 | E100: =+E28 | H100: 0 | I100: 0 | J100: 0 | K100: 0 | L100: 0 | M100: 0 | N100: 0 | O100: 0 | P100: 0 | S100: =+F77 | X100: 0 | Y100: 0 | Z100: 0 | AA100: 0 | AB100: 0 | AC100: 0 | AD100: 0 | AE100: 0 | AF100: 0 | AG100: 0
B101: Boleta Honorarios | C101: 4.6 | D101: Encargado territorial RRHH | E101: =Supuestos!E32 | H101: 0 | I101: 0 | J101: 0 | K101: 0 | L101: 0 | M101: 0 | N101: 0 | O101: 1 | P101: 1 | Q101: 1 | R101: 1 | S101: 1 | V101: 1 | X101: 0 | Y101: 0 | Z101: 0 | AA101: 0 | AB101: 0 | AC101: 0 | AD101: 0 | AE101: 0 | AF101: 0 | AG101: 0
B102: Boleta Honorarios | C102: 4.7 | D102: Apoyo Financiero de proyecto | E102: =Supuestos!E33 | H102: 0 | I102: 0 | J102: 0 | K102: 0 | L102: 0 | M102: 0 | N102: 0 | O102: 0 | P102: 1 | Q102: 1 | R102: 1 | S102: 1 | V102: 1 | X102: 0 | Y102: 0 | Z102: 0 | AA102: 0 | AB102: 0 | AC102: 0 | AD102: 0 | AE102: 0 | AF102: 0 | AG102: 0
B103: Boleta Honorarios | C103: 4.8 | E103: =Supuestos!E34 | H103: 0 | I103: 0 | J103: 0 | K103: 0 | L103: 0 | M103: 0 | N103: 0 | O103: 0 | P103: 0 | Q103: 0 | R103: 0 | S103: 0 | V103: 0 | X103: 0 | Y103: 0 | Z103: 0 | AA103: 0 | AB103: 0 | AC103: 0 | AD103: 0 | AE103: 0 | AF103: 0 | AG103: 0
C105: 5. | D105: Alquileres RRCC | E105: =+E33 | H105: 0 | I105: 0 | J105: 0 | K105: 0 | L105: 0 | M105: 0 | N105: 0 | O105: 0 | P105: 0 | Q105: 0 | R105: 0 | S105: 0 | V105: 0 | W105: 0 | X105: 0 | Y105: 0 | Z105: 0 | AA105: 0 | AB105: 0 | AC105: 0 | AD105: 0 | AE105: 0 | AF105: 0 | AG105: 0
B106: Factura | C106: 5.1 | D106: Arriendo vehículo diario - RRCC | E106: =+E34 | H106: 0 | I106: 0 | J106: 0 | K106: 0 | L106: 0 | M106: 0 | N106: 0 | O106: 0 | P106: 0 | Q106: 8 | R106: 8 | S106: 8 | X106: 0 | Y106: 0 | Z106: 0 | AA106: 0 | AB106: 0 | AC106: 0 | AD106: 0 | AE106: 0 | AF106: 0 | AG106: 0
B107: Factura | C107: 5.2 | D107: Vehiculo RRCC | E107: =+E35 | H107: 0 | I107: 0 | J107: 0 | K107: 0 | L107: 0 | M107: 0 | N107: 0 | O107: 0 | P107: 1 | Q107: 1 | R107: 1 | S107: 1 | V107: 0 | W107: 0 | X107: 0 | Y107: 0 | Z107: 0 | AA107: 0 | AB107: 0 | AC107: 0 | AD107: 0 | AE107: 0 | AF107: 0 | AG107: 0
C108: 6. | D108: Alquileres Gestión Técnica | E108: =+E36 | H108: 0 | I108: 0 | J108: 0 | K108: 0 | L108: 0 | M108: 0 | N108: 0 | O108: 0 | P108: 0 | Q108: 0 | R108: 0 | S108: 0 | V108: 0 | W108: 0 | X108: 0 | Y108: 0 | Z108: 0 | AA108: 0 | AB108: 0 | AC108: 0 | AD108: 0 | AE108: 0 | AF108: 0 | AG108: 0
B109: Factura | C109: 6.1 | D109: Bodega Terreno | E109: =+E37 | H109: 0 | I109: 0 | J109: 0 | K109: 0 | L109: 0 | M109: 0 | N109: 0 | O109: 0 | P109: 1 | Q109: 1 | R109: 1 | S109: 1 | V109: 1 | X109: 0 | Y109: 0 | Z109: 0 | AA109: 0 | AB109: 0 | AC109: 0 | AD109: 0 | AE109: 0 | AF109: 0 | AG109: 0
B110: Factura | C110: 6.2 | D110: Arriendo vehículo diario - Área Técnica | E110: =+E38 | H110: 0 | I110: 0 | J110: 0 | K110: 0 | L110: 0 | M110: 0 | N110: 0 | O110: 0 | P110: 0 | Q110: 8 | R110: 8 | S110: 8 | V110: 8 | X110: 0 | Y110: 0 | Z110: 0 | AA110: 0 | AB110: 0 | AC110: 0 | AD110: 0 | AE110: 0 | AF110: 0 | AG110: 0
...

Sheet Guía Maestra
A1: GUÍA MAESTRA — Luz en Casa GORE | Modelo Financiero de Simulación
A2: Documento único de referencia: totales de control + arquitectura del modelo + reglas de edición
A4: 1. TOTALES DE CONTROL
B5: Concepto | C5: Valor Total CLP | D5: Valor Unitario | E5: Referencia | F5: Notas
B6: Analítica (NETO) | C6: =+Analitica!AG36 | D6: =+C6/$C$9 | E6: D1) Resultado Proyectos Bruto → hoja Analítica | F6: Suma de Flujo Neto por código corporativo
B7: Cashflow (BRUTO) | C7: =+Cashflow!AE19 | D7: =+C7/$C$9 | E7: Cashflow LOC → hoja Cashflow | F7: Suma de Flujo Bruto con IVA incluido
B8: Ratio Bruto/Neto | C8: ≈ 1.144× | D8: — | E8: — | F8: ~14.4% diferencia = IVA 19% sobre ítems afectos
B9: Instalaciones | C9: 60 | D9: — | E9: Supuestos!E2 | F9: Afecta cantidades: ítems 1.1-1.3, 2.1-2.2, 10.3
B10: Cuadrillas | C10: 3 | D10: — | E10: Supuestos!E4 | F10: Afecta cantidad de Herramientas (ítem 2.3)
B11: TC USD/CLP | C11: 950 | D11: — | E11: Supuestos!E3 | F11: Afecta conversión equipos importados (ítem 1.x)
A13: 2. MAPA DE PESTAÑAS
B14: Pestaña | C14: Rol | D14: Tipo | E14: ¿Editable? | F14: Depende de | G14: Alimenta a | H14: Descripción
B15: Supuestos | C15: Fuente única de datos | D15: INPUT | E15: ✅ SÍ | F15: — | G15: Flujo Neto Flujo Bruto | H15: Precios unitarios, cantidades, TC, cuadrillas, y ahora cols R/S con código analítico y CF.
B16: Flujo Neto | C16: Motor cálculo neto | D16: CÁLCULO | E16: ⛔ NO | F16: Supuestos | G16: Analítica | H16: Valor unitario NETO × factor mensual. Tabla inferior: factores de distribución por mes.
B17: Flujo Bruto | C17: Motor cálculo bruto | D17: CÁLCULO | E17: ⛔ NO | F17: Supuestos | G17: Cashflow | H17: Valor unitario BRUTO × factor mensual. Factores vinculados a Flujo Neto (por diseño).
B18: Analítica | C18: Reporte corporativo NETO | D18: CORPORATIVO | E18: ⛔ NO | F18: Flujo Neto | G18: — | H18: Formato ACCIONA inamovible. SUM() de rangos de Flujo Neto agrupados por código 20-27.
B19: Cashflow | C19: Reporte corporativo BRUTO | D19: CORPORATIVO | E19: ⛔ NO | F19: Flujo Bruto | G19: — | H19: Formato ACCIONA inamovible. SUM() de rangos de Flujo Bruto por código Cashflow.
B20: Analisis Tecnicos | C20: Referencia técnica | D20: REFERENCIA | E20: ✅ SÍ | F20: — | G20: Supuestos (ref.) | H20: Costos técnicos por instalación (Técnico A, Ayudante, Combustible). Insumo para validar precios.
B21: Guía Maestra | C21: Documentación central | D21: DOC | E21: ✅ SÍ | F21: — | G21: — | H21: Este documento. Reemplaza a NOTAS y a la Guía de Vínculos.
A23: 3. CADENA DE CÁLCULO
A24: NETO: Supuestos → Flujo Neto → Analítica
B25: PASO 1 | C25: Precio unitario | D25: Supuestos col E → Flujo Neto col E | E25: =#NAME? | F25: Cada ítem de Flujo Neto toma su precio NETO directamente de Supuestos col E. Cambiar en Supuestos propaga automáticamente.
B26: PASO 2 | C26: Factor mensual | D26: Tabla inferior Flujo Neto (filas 68+) | E26: Fila 69 = 0 / 0.3 / 0.5 / 0.2... | F26: Define en qué mes ocurre cada gasto. Si cambia el cronograma, se editan estos factores. Suma de factores = cantidad total del ítem.
B27: PASO 3 | C27: Cálculo mensual | D27: Flujo Neto tabla superior | E27: H6 = =$E6*H69 | F27: Precio unitario × factor del mes correspondiente. Las filas de grupo suman sus sub-ítems con SUM().
B28: PASO 4 | C28: Agrupación en Analítica | D28: Flujo Neto → Analítica | E28: Analítica G12 = SUM('Flujo Neto'!H6:H10) | F28: Analítica suma rangos de Flujo Neto por código corporativo (21, 22, 23, 24, 25.x). También hay referencias directas para ítems únicos.
A30: BRUTO: Supuestos → Flujo Bruto → Cashflow
B31: PASO 1 | C31: Precio unitario BRUTO | D31: Supuestos col G → Flujo Bruto col E | E31: =#NAME? | F31: Flujo Bruto toma el precio con IVA de col G de Supuestos. El IVA está embebido en el precio unitario bruto.
B32: PASO 2 | C32: Factores mensuales vinculados | D32: Tabla inferior Flujo Bruto ↔ Flujo Neto | E32: Por diseño: misma distribución | F32: Los factores de Flujo Bruto son los mismos que Flujo Neto (misma distribución temporal). Están duplicados por diseño, no por error — ambas hojas deben tener la misma tabla para funcionar de forma autónoma.
B33: PASO 3 | C33: Agrupación en Cashflow | D33: Flujo Bruto → Cashflow | E33: SUM por código Cashflow corporativo | F33: Cashflow suma rangos de Flujo Bruto por código b.x (b.1 Compras activables, b.3 Alquileres, b.4 Personal, etc.).
A35: 4. CORRESPONDENCIA ÍTEM → CÓDIGO ANALÍTICA / CASHFLOW (1 a 1)
B36: Nivel | C36: Item | D36: Código Analítica | E36: Descripción Analítica | F36: Código Cashflow | G36: Descripción Cashflow
B37: 1 | C37: Compras activables ZIMPERTEC | D37: 21 | E37: Inversión de proyectos | F37: b.1 | G37: Compras activables
B38: 1.1 | C38: Sistemas AC | D38: 21.1 | E38: Compras activables equipos energía | F38: b.1 | G38: Compras activables
B39: 1.2 | C39: Paneles | D39: 21.1 | E39: Compras activables equipos energía | F39: b.1 | G39: Compras activables
B40: 1.3 | C40: Lamparas | D40: 21.1 | E40: Compras activables equipos energía | F40: b.1 | G40: Compras activables
B41: 1.4 | C41: Hardware Monitoreo | D41: 21.1 | E41: Compras activables equipos energía | F41: b.1 | G41: Compras activables
B42: 1.5 | C42: Software Monitoreo | D42: 21.1 | E42: Compras activables equipos energía | F42: b.1 | G42: Compras activables
B43: 1.6 | C43: Repuestos | D43: 22.2 | E43: Compra de repuestos a inventario | F43: b.2 | G43: Compras inventariables
B44: 1.7 | C44: Flete | D44: 25.7 | E44: Correo, mensajería, transporte equipos | F44: b.7 | G44: Transporte equipos
B45: 2 | C45: Insumos Instalación | D45: 23 | E45: Compras no activables ni inventariables | F45: b.2 | G45: No activables
B46: 2.1 | C46: Estructura | D46: 23 | E46: Compras no activables ni inventariables | F46: b.2 | G46: No activables
B47: 2.2 | C47: Materiales instalación | D47: 23 | E47: Compras no activables ni inventariables | F47: b.2 | G47: No activables
... B92: 10.5 | C92: Otros varios | D92: 25.14 | E92: Otros servicios (resto) | F92: b.6 | G92: Otros gastos
A94: 5. REGLAS DE EDICIÓN Y MEJORAS PENDIENTES
B95: 🟢 REGLA 1 | C95: Solo se edita en Supuestos | D95: Todos los precios unitarios, tasas de cambio y cantidades se modifican únicamente en Supuestos. Las columnas R y S (Código Analítica / Cashflow) también están ahí para referencia directa.
B96: 🟢 REGLA 2 | C96: Factores de distribución mensual | D96: Si cambia el cronograma de instalaciones, se actualizan los factores en la tabla inferior de Flujo Neto Y en la tabla equivalente de Flujo Bruto. La suma de factores por ítem debe igualar la cantidad total.
B97: 🟢 REGLA 3 | C97: Analítica y Cashflow son inamovibles | D97: Formato corporativo ACCIONA. No agregar ni eliminar filas ni columnas. Si hay un ítem nuevo sin código asignado, coordinar con el equipo financiero antes de incorporarlo.
B98: 🔴 RESTRICCIÓN | C98: No agregar filas en Flujo Neto/Bruto sin actualizar Analítica | D98: Si se agrega un ítem nuevo, los rangos SUM() en Analítica (ej. H6:H10) pueden quedar incompletos. Verificar que el rango incluye la fila nueva antes de guardar.
B99: 🟡 MEJORA A | C99: Validación automática en Guía Maestra | D99: Agregar fórmulas en Sección 1 que lean directamente el total de Analítica y Cashflow para verificar que coinciden con los valores de control. Ej: =Analitica!AF_total con condicional de color.
B100: 🟡 MEJORA B | C100: Protección de hojas | D100: Proteger con contraseña Flujo Neto, Flujo Bruto, Analítica y Cashflow (Revisar → Proteger hoja). Dejar solo Supuestos y Analisis Tecnicos editables, evitando modificaciones accidentales.
A102: ACTUALIZACIÓN Rev.1 — 2025-05-13
A103: Nueva pestaña agregada: | B103: Rendición GORE | C103: Pestaña pública de rendición en lenguaje FNDR/GORE Coquimbo | D103: Vinculada a Supuestos (K3 para monto equip+traslados GORE)
A104: Lógica GORE: | B104: El GORE financia 100% equipos + traslados asociados = $2.001.190 (Supuestos K3)

Sheet Supuestos
A1: SUPUESTOS FINANCIEROS — LUZ EN CASA · GORE COQUIMBO
D3: Cantidad Equipos a comprar | E3: 75
D4: Tasa de cambio USD/CLP | E4: 1000
D5: Cantidad Cuadrillas | E5: 1
E7: NETO | G7: BRUTO | I7: NETO | K7: BRUTO | N7: NETO | Q7: NETO | S7: BRUTO
B8: Forma pago | C8: Nivel | D8: Item | E8: Valor unitario CLP NETO | F8: IVA | G8: Valor unitario CLP BRUTO | H8: Cantidad | I8: Valor total CLP NETO | J8: IVA | K8: Valor total CLP BRUTO | L8: Código Analítica | M8: Código Cashflow | N8: Valor unitario USD NETO | O8: IVA | P8: Cantidad | Q8: Valor total USD NETO | R8: IVA | S8: Valor total USD BRUTO
C9: 1 | D9: Compras activables ZIMPERTEC | E9: =+SUM(E9:E16) | F9: =+SUM(F9:F16) | G9: =+SUM(G9:G16) | I9: =+SUM(I9:I16) | J9: =+SUM(J9:J16) | K9: =+SUM(K9:K16) | L9: 21 | M9: b.1 Compras activables | N9: =+SUM(N9:N16) | O9: =+SUM(O9:O16) | Q9: =+SUM(Q9:Q16) | R9: =+SUM(R9:R16) | S9: =+SUM(S9:S16)
B10: Factura | C10: 1.1 | D10: Sistemas AC | E10: =+N9*$E$3 | F10: =+E9*19% | G10: =+E9+F9 | H10: =+$E$2 | I10: =+E9*H9 | J10: =+I9*19% | K10: =+SUM(I9:J9) | L10: 21.1 | M10: b.1 Compras activables | N10: 1300.63 | O10: =+N9*19% | P10: =+$E$2 | Q10: =+P9*N9 | R10: =+Q9*19% | S10: =+Q9+R9
B11: Factura | C11: 1.2 | D11: Paneles | E11: =+N10*$E$3 | F11: =+E10*19% | G11: =+E10+F10 | H11: =+H9*2 | I11: =+E10*H10 | J11: =+I10*19% | K11: =+SUM(I10:J10) | L11: 21.1 | M11: b.1 Compras activables | N11: 75 | O11: =+N10*19% | P11: =+P9*2 | Q11: =+P10*N10 | R11: =+Q10*19% | S11: =+Q10+R10
B12: Factura | C12: 1.3 | D12: Lamparas | E12: =+N11*$E$3 | F12: =+E11*19% | G12: =+E11+F11 | H12: =+H9*3 | I12: =+E11*H11 | J12: =+I11*19% | K12: =+SUM(I11:J11) | L12: 21.1 | M12: b.1 Compras activables | N12: 7.82 | O12: =+N11*19% | P12: =+P9*3 | Q12: =+P11*N11 | R12: =+Q11*19% | S12: =+Q11+R11
B13: Factura | C13: 1.4 | D13: Hardware Monitoreo | E13: =+N12*$E$3 | F13: =+E12*19% | G13: =+E12+F12 | H13: 0 | I13: =+E12*H12 | J13: =+I12*19% | K13: =+SUM(I12:J12) | L13: 21.1 | M13: b.1 Compras activables | N13: 39.51 | O13: =+N12*19% | P13: 0 | Q13: =+P12*N12 | R13: =+Q12*19% | S13: =+Q12+R12
B14: Factura | C14: 1.5 | D14: Software Monitoreo | E14: =+N13*$E$3 | F14: =+E13*19% | G14: =+E13+F13 | H14: 0 | I14: =+E13*H13 | J14: =+I13*19% | K14: =+SUM(I13:J13) | L14: 21.1 | M14: b.1 Compras activables | N14: 60.01 | O14: =+N13*19% | P14: 0 | Q14: =+P13*N13 | R14: =+Q13*19% | S14: =+Q13+R13
B15: Factura | C15: 1.6 | D15: Repuestos | E15: =+N14*$E$3 | F15: =+E14*19% | G15: =+E14+F14 | H15: 0 | I15: =+E14*H14 | J15: =+I14*19% | K15: =+SUM(I14:J14) | L15: 22.2 | M15: b.2 Compras inventariables | N15: 6209 | O15: =+N14*19% | P15: 1 | Q15: =+P14*N14 | R15: =+Q14*19% | S15: =+Q14+R14
B16: Factura | C16: 1.7 | D16: Flete | E16: =+N15*$E$3 | F16: =+E15*19% | G16: =+E15+F15 | H16: 1 | I16: =+E15*H15 | K16: =+SUM(I15:J15) | L16: 25.7 | M16: b.7 Transporte equipos | N16: =8800*1.25 | O16: =+N15*19% | P16: 1 | Q16: =+P15*N15 | R16: =+Q15*19% | S16: =+Q15+R15
B17: Factura | C17: 7.2 | D17: Transporte DESCONSOLIDADO | E17: 3565000 | F17: =+E16*19% | G17: =+E16+F16 | H17: 1 | I17: =+E16*H16 | J17: =+I16*19% | K17: =+SUM(I16:J16) | L17: 25.7 | M17: b.7 Transporte
B18: Factura | C18: 7.5 | D18: Grúa en Origen | E18: 747500 | F18: =+E17*19% | G18: =+E17+F17 | H18: 1 | I18: =+E17*H17 | J18: =+I17*19% | K18: =+SUM(I17:J17) | L18: 25.7 | M18: b.7 Transporte
B19: Factura | C19: 7.6 | D19: Grúa en Punto Destino (6 Horas) | E19: 747500 | F19: =+E18*19% | G19: =+E18+F18 | H19: 1 | I19: =+E18*H18 | J19: =+I18*19% | K19: =+SUM(I18:J18) | L19: 25.7 | M19: b.7 Transporte
C20: 2 | D20: Insumos Instalación | E20: =+SUM(E20:E22) | F20: =+SUM(F20:F22) | G20: =+SUM(G20:G22) | I20: =+SUM(I20:I22) | J20: =+SUM(J20:J22) | K20: =+SUM(K20:K22) | L20: 23 | M20: b.2 No activables
B21: Factura | C21: 2.1 | D21: Estructura | E21: 40700 | F21: =+E20*19% | G21: =+E20+F20 | H21: =+$E$2 | I21: =+E20*H20 | J21: =+I20*19% | K21: =+SUM(I20:J20) | L21: 23 | M21: b.2 No activables
B22: Factura o Boleta | C22: 2.2 | D22: Materiales instalación | E22: 85800 | F22: =+E21*19% | G22: =+E21+F21 | H22: =+$E$2 | I22: =+E21*H21 | J22: =+I21*19% | K22: =+SUM(I21:J21) | L22: 23 | M22: b.2 No activables
B23: Factura o Boleta | C23: 2.3 | D23: Herramientas | E23: 1430000 | F23: =+E22*19% | G23: =+E22+F22 | H23: =+E4 | I23: =+E22*H22 | J23: =+I22*19% | K23: =+SUM(I22:J22) | L23: 23 | M23: b.2 No activables
C24: 3. | D24: Personal y Servicios | G24: =+E23+F23 | L24: 24 | M24: b.4 Personal
B25: Costo Empresa | C25: 3.1 | D25: Planilla Actual | E25: 6195000 | G25: =+E24+F24 | H25: 1 | I25: =+E24*H24 | K25: =+SUM(I24:J24) | L25: 24 | M25: b.4 Personal
B26: Costo Empresa | C26: 3.2 | D26: Descarga estructura | G26: =+E25+F25
C27: 4. | D27: Servicios Profesionales | E27: =+SUM(E27:E34) | F27: =+SUM(F27:F34) | G27: =+SUM(G27:G34) | I27: =+SUM(I27:I34) | J27: =+SUM(J27:J34) | K27: =+SUM(K27:K34) | L27: 25.6 | M27: b.4 Serv. profesionales
B28: Boleta Honorarios | C28: 4.1 | D28: Encargado de Logistica y Bodega | E28: 1000000 | G28: =+E27+F27 | H28: 1 | I28: =+E27*H27 | J28: =+I27*19% | K28: =+SUM(I27:J27) | L28: 25.6 | M28: b.4 Serv. profesionales
B29: Boleta Honorarios | C29: 4.2 | D29: Técnico pago por instalación - Plan A | E29: 125000 | G29: =+E28+F28 | H29: 1 | I29: =+E28*H28 | J29: =+I28*19% | K29: =+SUM(I28:J28) | L29: 25.6 | M29: b.4 Serv. profesionales
B30: Boleta Honorarios | C30: 4.3 | D30: Técnico contrato mensual - Plan B | E30: 1365000 | G30: =+E29+F29 | H30: 1 | I30: =+E29*H29 | J30: =+I29*19% | K30: =+SUM(I29:J29) | L30: 25.6 | M30: b.4 Serv. profesionales
B31: Boleta Honorarios | C31: 4.4 | D31: Ayudante contrato mensual - Plan B | E31: 750000 | G31: =+E30+F30 | H31: 1 | I31: =+E30*H30 | J31: =+I30*19% | K31: =+SUM(I30:J30) | L31: 25.6 | M31: b.4 Serv. profesionales
B32: Boleta Honorarios | C32: 4.5 | D32: Personal apoyo Planos TE1 | E32: 10000 | G32: =+E31+F31 | H32: 1 | I32: =+E31*H31 | J32: =+I31*19% | K32: =+SUM(I31:J31) | L32: 25.6 | M32: b.4 Serv. profesionales
B33: Boleta Honorarios | C33: 4.6 | D33: Encargado territorial RRCC | E33: 900000 | G33: =+E32+F32
B34: Boleta Honorarios | C34: 4.7 | D34: Apoyo Financiero de proyecto | E34: 800000 | G34: =+E33+F33
B35: Boleta Honorarios | C35: 4.8
C37: 5. | D37: Alquileres RRCC | E37: =+SUM(E37:E38) | F37: =+SUM(F37:F38) | G37: =+SUM(G37:G38) | I37: =+SUM(I37:I38) | J37: =+SUM(J37:J38) | K37: =+SUM(K37:K38) | L37: 25.1 | M37: b.3 Alquileres
B38: Factura | C38: 5.1 | D38: Arriendo vehículo diario - RRCC | E38: 90000 | F38: =+E37*19% | G38: =+E37+F37 | H38: 1 | I38: =+E37*H37 | J38: =+I37*19% | K38: =+SUM(I37:J37) | L38: 25.1 | M38: b.3 Alquileres
B39: Factura | C39: 5.2 | D39: Vehiculo RRCC | E39: 1400000 | F39: =+E38*19% | G39: =+E38+F38 | H39: 1 | I39: =+E38*H38 | J39: =+I38*19% | K39: =+SUM(I38:J38) | L39: 25.1 | M39: b.3 Alquileres
C40: 6. | D40: Alquileres Gestión Técnica | E40: =+SUM(E40:E43) | F40: =+SUM(F40:F43) | G40: =+SUM(G40:G43) | I40: =+SUM(I40:I43) | J40: =+SUM(J40:J43) | K40: =+SUM(K40:K43) | L40: 25.1/25.3 | M40: b.3 Alquileres
B41: Factura | C41: 6.1 | D41: Bodega Terreno | E41: 1100000 | F41: =+E40*19% | G41: =+E40+F40 | H41: 1 | I41: =+E40*H40 | J41: =+I40*19% | K41: =+SUM(I40:J40) | L41: 25.3 | M41: b.3 Alquileres
B42: Factura | C42: 6.2 | D42: Arriendo vehículo diario - Área Técnica | E42: 90000 | F42: =+E41*19% | G42: =+E41+F41 | H42: 1 | I42: =+E41*H41 | J42: =+I41*19% | K42: =+SUM(I41:J41) | L42: 25.1 | M42: b.3 Alquileres
B43: Factura | C43: 6.3 | D43: Vehiculo Instaladores | E43: 1400000 | F43: =+E42*19% | G43: =+E42+F42 | H43: 1 | I43: =+E42*H42 | J43: =+I42*19% | K43: =+SUM(I42:J42) | L43: 25.1 | M43: b.3 Alquileres
B44: Factura | C44: 6.4 | D44: Vehiculo Transporte (Maxus Deliver 9) | E44: 1600000 | F44: =+E43*19% | G44: =+E43+F43 | H44: 1 | I44: =+E43*H43 | J44: =+I43*19% | K44: =+SUM(I43:J43) | L44: 25.1 | M44: b.3 Alquileres
C45: 7. | D45: Transporte | E45: =+SUM(E45:E51) | F45: =+SUM(F45:F51) | G45: =+SUM(G45:G51) | I45: =+SUM(I45:I51) | J45: =+SUM(J45:J51) | K45: =+SUM(K45:K51) | L45: 25.7 | M45: b.7 Transporte
B46: Factura | C46: 7.1 | D46: Transporte ZIMPERTEC | E46: 5016000 | F46: =+E45*19% | G46: =+E45+F45 | H46: 0 | I46: =+E45*H45 | J46: =+I45*19% | K46: =+SUM(I45:J45) | L46: 25.7 | M46: b.7 Transporte
B48: Factura | C48: 7.3 | D48: Traslado Contenedor (ida y vuelta) | E48: 920000 | F48: =+E47*19% | G48: =+E47+F47 | H48: 1 | I48: =+E47*H47 | J48: =+I47*19% | K48: =+SUM(I47:J47) | L48: 25.7 | M48: b.7 Transporte
B49: Factura | C49: 7.4 | D49: Camión Transporte Origen - Punto Destino (RAMPLA ABIERTA) | E49: 1725000 | F49: =+E48*19% | G49: =+E48+F48 | H49: 1 | I49: =+E48*H48 | J49: =+I48*19% | K49: =+SUM(I48:J48) | L49: 25.7 | M49: b.7 Transporte
B52: Factura | C52: 7.7 | D52: Camión Transporte Origen - Punto Destino (Camión cerrado) | E52: 1725000 | F52: =+E51*19% | G52: =+E51+F51 | H52: 1 | I52: =+E51*H51 | J52: =+I51*19% | K52: =+SUM(I51:J51) | L52: 25.7 | M52: b.7 Transporte
C53: 8. | D53: Viajes RRCC | E53: =+SUM(E53:E58) | F53: =+SUM(F53:F58) | G53: =+SUM(G53:G58) | I53: =+SUM(I53:I58) | J53: =+SUM(J53:J58) | K53: =+SUM(K53:K58) | L53: 25.11/25.13 | M53: b.5 Viajes
B54: Factura | C54: 8.1 | D54: Traslados de personal | E54: 180000 | F54: =+E53*19% | G54: =+E53+F53 | H54: 1 | I54: =+E53*H53 | J54: =+I53*19% | K54: =+SUM(I53:J53) | L54: 25.13 | M54: b.5 Viajes
B55: Factura o Boleta | C55: 8.2 | D55: Alojamiento | E55: 60000 | F55: =+E54*19% | G55: =+E54+F54 | H55: 1 | I55: =+E54*H54 | J55: =+I54*19% | K55: =+SUM(I54:J54) | L55: 25.13 | M55: b.5 Viajes
B56: Boleta | C56: 8.3 | D56: Alimentación | E56: 15000 | F56: =+E55*19% | G56: =+E55+F55 | H56: 1 | I56: =+E55*H55 | J56: =+I55*19% | K56: =+SUM(I55:J55) | L56: 25.13 | M56: b.5 Viajes
B57: Factura o Boleta | C57: 8.4 | D57: Combustible arriendo diario | E57: 70000 | F57: =+E56*19% | G57: =+E56+F56 | H57: 1 | I57: =+E56*H56 | J57: =+I56*19% | K57: =+SUM(I56:J56) | L57: 25.11 | M57: b.5 Viajes
B58: Factura o Boleta | C58: 8.5 | D58: Combustible arriendo mensual | E58: 700000 | F58: =+E57*19% | G58: =+E57+F57 | H58: 1 | I58: =+E57*H57 | J58: =+I57*19% | K58: =+SUM(I57:J57) | L58: 25.11 | M58: b.5 Viajes
B59: Boleta | C59: 8.6 | D59: Peajes | E59: 20000 | F59: =+E58*19% | G59: =+E58+F58 | H59: 1 | I59: =+E58*H58 | J59: =+I58*19% | K59: =+SUM(I58:J58) | L59: 25.13 | M59: b.5 Viajes
C60: 9. | D60: Viajes Gestión Técnica | E60: =+SUM(E60:E65) | F60: =+SUM(F60:F65) | G60: =+SUM(G60:G65) | I60: =+SUM(I60:I65) | J60: =+SUM(J60:J65) | K60: =+SUM(K60:K65) | L60: 25.11/25.13 | M60: b.5 Viajes
B61: Factura | C61: 9.1 | D61: Traslados de personal | E61: 180000 | F61: =+E60*19% | G61: =+E60+F60 | H61: 1 | I61: =+E60*H60 | J61: =+I60*19% | K61: =+SUM(I60:J60) | L61: 25.13 | M61: b.5 Viajes
B62: Factura o Boleta | C62: 9.2 | D62: Alojamiento | E62: 60000 | F62: =+E61*19% | G62: =+E61+F61 | H62: 1 | I62: =+E61*H61 | J62: =+I61*19% | K62: =+SUM(I61:J61) | L62: 25.13 | M62: b.5 Viajes
B63: Boleta | C63: 9.3 | D63: Alimentación | E63: 15000 | F63: =+E62*19% | G63: =+E62+F62 | H63: 1 | I63: =+E62*H62 | J63: =+I62*19% | K63: =+SUM(I62:J62) | L63: 25.13 | M63: b.5 Viajes
B64: Factura o Boleta | C64: 9.4 | D64: Combustible arriendo diario | E64: 70000 | F64: =+E63*19% | G64: =+E63+F63 | H64: 1 | I64: =+E63*H63 | J64: =+I63*19% | K64: =+SUM(I63:J63) | L64: 25.11 | M64: b.5 Viajes
B65: Factura o Boleta | C65: 9.5 | D65: Combustible arriendo mensual | E65: 600000 | F65: =+E64*19% | G65: =+E64+F64 | H65: 1 | I65: =+E64*H64 | J65: =+I64*19% | K65: =+SUM(I64:J64) | L65: 25.11 | M65: b.5 Viajes
B66: Boleta | C66: 9.6 | D66: Peajes | E66: 20000 | F66: =+E65*19% | G66: =+E65+F65 | H66: 1 | I66: =+E65*H65 | J66: =+I65*19% | K66: =+SUM(I65:J65) | L66: 25.13 | M66: b.5 Viajes
C67: 10. | D67: Gastos Varios | E67: =+SUM(E67:E71) | F67: =+SUM(F67:F71) | G67: =+SUM(G67:G71) | I67: =+SUM(I67:I71) | J67: =+SUM(J67:J71) | K67: =+SUM(K67:K71) | L67: 25.14 | M67: b.6 Otros gastos
B68: Boleta | C68: 10.1 | D68: Compras de Equipos, EEPP, Otros | E68: 1800000 | F68: =+E67*19% | G68: =+E67+F67 | H68: 1 | I68: =+E67*H67 | J68: =+I67*19% | K68: =+SUM(I67:J67) | L68: 25.9 | M68: b.6 Otros gastos
B69: Boleta | C69: 10.2 | D69: Mensajerias (Correo de Chile) | E69: 10500 | F69: =+E68*19% | G69: =+E68+F68 | H69: 1 | I69: =+E68*H68 | J69: =+I68*19% | K69: =+SUM(I68:J68) | L69: 25.7 | M69: b.6 Otros gastos
B70: Factura o Boleta | C70: 10.3 | D70: Impresión de manuales | E70: 15750 | F70: =+E69*19% | G70: =+E69+F69 | H70: 1 | I70: =+E69*H69 | J70: =+I69*19% | K70: =+SUM(I69:J69) | L70: 25.14 | M70: b.6 Otros gastos
B71: Factura o Boleta | C71: 10.4 | D71: Mantención y reparación de Vehículos | E71: 0 | F71: =+E70*19% | G71: =+E70+F70 | H71: 1 | I71: =+E70*H70 | J71: =+I70*19% | K71: =+SUM(I70:J70) | L71: 25.14 | M71: b.6 Otros gastos
B72: Factura o Boleta | C72: 10.5 | D72: Otros varios | E72: 14250 | G72: =+E71+F71 | H72: 1 | I72: =+E71*H71 | J72: =+I71*19% | K72: =+SUM(I71:J71) | L72: 25.14 | M72: b.6 Otros gastos
E74: NETO | F74: BRUTO
D75: Calculo de precio unitario Sistemas AC + Paneles + Lámparas + Flete + ( Transp.descons. + Grúas)/N° Equipo a Instalar | E75: =+SUM(I9:I16)/E2+(SUM(I16,I17,I18)/E2) | F75: =F75+((K16+K17+K18)/E2)
D76: Calculo de precio unitario Sistemas AC + Paneles + Lámparas + Flete | E76: =+I8/E2 | F76: =+K8/E2
D78: Factura
D79: Boleta
D80: B. Honorarios
D81: Factura o Boleta
D82: Costo Empresa

Sheet Diagnóstico Vínculos
A1: DIAGNÓSTICO DE VÍNCULOS — Filas de Flujo Neto/Bruto NO capturadas por Analítica/Cashflow
A2: Estas son las filas que existen en Flujo Neto/Flujo Bruto pero que Analítica y/o Cashflow NO están sumando. Debes agregar manualmente las fórmulas indicadas en las columnas H e I.
A3: N° | B3: Flujo Neto Fila | C3: Flujo Bruto Fila | D3: Ítem / Descripción | E3: Código Analítica | F3: Código Cashflow | G3: Estado coverage | H3: Fórmula a agregar en ANALÍTICA (columna G en adelante, patrón por mes) | I3: Fórmula a agregar en CASHFLOW (columna C en adelante, patrón por mes)
A4: 1 | B4: 14 | C4: 14 | D4: 2.1 — Estructura | E4: 23 | F4: b.2 | G4: ⚠ FALTA | H4: Anal.G18: +'Flujo Neto'!H13+SUM('Flujo Neto'!H14:H16) [replicar cols H..AE] | I4: Cashflow!C18 → +'Flujo Bruto'!H13+SUM('Flujo Bruto'!H14:H16)
A5: 2 | B5: 15 | C5: 15 | D5: 2.2 — Materiales instalación | E5: 23 | F5: b.2 | G5: ⚠ FALTA | H5: Ver nota 2.1 — misma fórmula de grupo | I5: Ver nota 2.1
A6: 3 | B6: 16 | C6: 16 | D6: 2.3 — Herramientas | E6: 23 | F6: b.2 | G6: ⚠ FALTA | H6: Ver nota 2.1 | I6: Ver nota 2.1
A7: 4 | B7: 18 | C7: 18 | D7: 3.1 — Planilla Actual | E7: 24 | F7: b.4 | G7: ⚠ FALTA | H7: Si requieres detalle: Anal.G19 → +'Flujo Neto'!H17+'Flujo Neto'!H18 | I7: Si requieres detalle: Cash.C10 → +'Flujo Bruto'!H17+'Flujo Bruto'!H18
A8: 5 | B8: 19 | C8: 19 | D8: 3.2 — Descarga Estructura | E8: 24 | F8: b.4 | G8: ✓ OK subtotal | H8: Sin acción requerida mientras valor=0 | I8: Sin acción requerida mientras valor=0
A9: 6 | B9: 21 | C9: 21 | D9: 4.1 — Encargado Logística | E9: 25.6 | F9: b.4 | G9: ⚠ FALTA | H9: Anal.G26 → ampliar: +'Flujo Neto'!H20+SUM('Flujo Neto'!H21:H27) — o dejar en subtotal fila 20 | I9: Cash.C13 → +'Flujo Bruto'!H20+SUM('Flujo Bruto'!H21:H27)
A10: 7 | B10: 22 | C10: 22 | D10: 4.2 — Técnico instalación (Plan A) | E10: 25.6 | F10: b.4 | G10: ⚠ FALTA | H10: Ver nota 4.1 | I10: Ver nota 4.1
A11: 8 | B11: 23 | C11: 23 | D11: 4.3 — Técnico mensual (Plan B) | E11: 25.6 | F11: b.4 | G11: ⚠ FALTA | H11: Ver nota 4.1 | I11: Ver nota 4.1
A12: 9 | B12: 24 | C12: 24 | D12: 4.4 — Ayudante mensual (Plan B) | E12: 25.6 | F12: b.4 | G12: ⚠ FALTA | H12: Ver nota 4.1 | I12: Ver nota 4.1
A13: 10 | B13: 25 | C13: 25 | D13: 4.5 — Apoyo Planos TE-1 | E13: 25.6 | F13: b.4 | G13: ⚠ FALTA | H13: Ver nota 4.1 | I13: Ver nota 4.1
A14: 11 | B14: 26 | C14: 26 | D14: 4.6 — Encargado territorial | E14: 25.6 | F14: b.4 | G14: ✓ OK subtotal | H14: Sin acción requerida mientras valor=0 | I14: Sin acción requerida
A15: 12 | B15: 27 | C15: 27 | D15: 4.7 — Apoyo Financiero | E15: 25.6 | F15: b.4 | G15: ✓ OK subtotal | H15: Sin acción requerida | I15: Sin acción requerida
... A22: 19 | B22: 60 | C22: 60 | D22: 10. — Subtotal Gastos Varios | E22: 25.14 | F22: b.6 | G22: ✓ OK subtotal | H22: Sin acción — sub-ítems cubiertos | I22: Sin acción
A24: LEYENDA — ⚠ FALTA: el ítem tiene valores monetarios que NO están siendo capturados por Analítica/Cashflow. Debes ampliar la fórmula manualmente. ✓ OK subtotal: el ítem es un subtotal de grupo; los sub-ítems individuales sí están cubiertos, o bien la fila está vacía (valor=0).
A26: RESUMEN: 3 acciones críticas a realizar manualmente en Analítica
A27: ACCIÓN 1 — Grupo 2 (Insumos instalación) | D27: Analítica!G18: cambiar ='Flujo Neto'!H13 → ='Flujo Neto'!H13+SUM('Flujo Neto'!H14:H16) Cashflow!C18: cambiar ='Flujo Bruto'!H13 → ='Flujo Bruto'!H13+SUM('Flujo Bruto'!H14:H16) Replicar para columnas H..AE (Analítica) / D..AA (Cashflow) cambiando solo la letra de columna.
A28: ACCIÓN 2 — Grupo 3+4 (Personal + Servicios Prof.) | D28: Analítica!G19: cambiar ='Flujo Neto'!H17 → ='Flujo Neto'!H17+SUM('Flujo Neto'!H18:H27) Analítica!G26: cambiar ='Flujo Neto'!H20 → ='Flujo Neto'!H20+SUM('Flujo Neto'!H21:H27) Cashflow!C10: cambiar ='Flujo Bruto'!H17 → ='Flujo Bruto'!H17+SUM('Flujo Bruto'!H18:H19) Cashflow!C13: cambiar ='Flujo Bruto'!H20 → ='Flujo Bruto'!H20+SUM('Flujo Bruto'!H21:H27) Replicar para todas las columnas de meses.
A29: ACCIÓN 3 — Ítem 5.2 (Vehículo RRCC) — SOLO Analítica | D29: Analítica!G21: agregar +'Flujo Neto'!H32 al final de la fórmula existente. La fórmula actual es: ='Flujo Neto'!H31+'Flujo Neto'!H35+'Flujo Neto'!H36+'Flujo Neto'!H37 Debe quedar: ='Flujo Neto'!H31+'Flujo Neto'!H32+'Flujo Neto'!H35+'Flujo Neto'!H36+'Flujo Neto'!H37 Replicar para todas las columnas de meses. (Cashflow ya incluye fila 32.)

Sheet Carta Gantt
A1: CARTA GANTT — PROYECTO LUZ EN CASA · GORE COQUIMBO
A2: Fundación acciona.org · Financiamiento FNDR · 75 sistemas FV domiciliarios · Período de ejecución: julio 2026 – febrero 2027 (instalaciones) · cierre junio 2027
E3: 2026 | K3: 2027
A4: Fase | B4: Actividad / Hito | C4: Dur. | D4: Responsable | E4: Jul 2026 | F4: Ago 2026 | G4: Sep 2026 | H4: Oct 2026 | I4: Nov 2026 | J4: Dic 2026 | K4: Ene 2027 | L4: Feb 2027 | M4: Mar 2027 | N4: Abr 2027 | O4: May 2027 | P4: Jun 2027
A6: GESTIÓN | B6: FASE 1 — GESTIÓN Y SUSCRIPCIÓN DE CONVENIO
A7: Gestión | B7: Elaboración y revisión Resolución Exenta de aprobación GORE | C7: 3s | D7: Agustín D. / GORE
A8: Gestión | B8: Suscripción convenio de transferencia GORE · habilitación SISREC · FEA | C8: 3s | D8: Agustín D. / GORE
A9: Gestión | B9: Designación de roles rendición (SISREC) · apertura cuenta bancaria proyecto | C9: 3s | D9: Agustín D. / GORE
A10: Gestión | B10: Coordinación con DIPIR (GORE) · calendario de cuotas FNDR | C10: 1m | D10: Agustín D. / GORE
A11: Gestión | B11: ◆ Convenio firmado · primera cuota recibida | C11: ⬥ | D11: — | F11: ◆
A13: Compra Equipos | B13: FASE 2 — COMPRA DE EQUIPOS ZIMPERTEC
A14: Compra | B14: Cotización definitiva y aprobación interna Zimpertec GmbH · 75 kits SHS AC | C14: 2s | D14: Log. / Finanzas
A15: Compra | B15: Orden de compra a proveedor · factura proforma y pago anticipado | C15: 2s | D15: Log. / Finanzas
A16: Compra | B16: Publicación en Mercado Público (si aplica por GORE) · documentación OC | C16: 2s | D16: Log. / Finanzas
A17: Compra | B17: Confirmación de pedido · inicio de fabricación en fábrica Alemania | C17: 2s | D17: Logística
A18: Compra | B18: ◆ Equipos ordenados y pagados · fabricación iniciada | C18: ⬥ | D18: — | F18: ◆
A20: Importa- ción | B20: FASE 3 — IMPORTACIÓN Y GESTIÓN ADUANERA
A21: Importación | B21: Fabricación equipos en fábrica Zimpertec, Alemania (lead time ~3-4 meses) | C21: 4m | D21: Zimpertec / Log.
A22: Importación | B22: Coordinación logística de transporte marítimo (agente de carga, naviera) | C22: 1m | D22: Logística
A23: Importación | B23: Embarque y tránsito marítimo hacia puerto Chile (~4-6 semanas) | C23: 6s | D23: Agente carga
A24: Importación | B24: Gestión aduanera: DUS, liquidación arancelaria, liberación carga | C24: 2s | D24: Agente aduana
A25: Importación | B25: Transporte terrestre desde puerto → bodega proyecto Coquimbo (desconsolidado) | C25: 1s | D25: Logística
A26: Importación | B26: ◆ Equipos en bodega Chile · recepción + control de calidad | C26: ⬥ | D26: — | H26: ◆
A28: Contra- tación | B28: FASE 4 — CONTRATACIONES DE PERSONAL
A29: Contratación | B29: Reclutamiento y selección Encargado de Logística y Bodega | C29: 3s | D29: RRHH / Agustín D.
A30: Contratación | B30: Contratación técnicos instaladores (Plan B: contrato mensual) — cuadrillas | C30: 3s | D30: RRHH / Agustín D.
A31: Contratación | B31: Contratación Encargado Territorial / RRCC | C31: 3s | D31: RRHH / Agustín D.
A32: Contratación | B32: Contratación Apoyo Financiero de proyecto | C32: 2s | D32: RRHH / Agustín D.
A33: Contratación | B33: Contratación personal Apoyo Planos TE-1 (inicio en instalaciones) | C33: 1s | D33: RRHH
A35: Mate- riales | B35: FASE 5 — MATERIALES E INSUMOS DE INSTALACIÓN
A36: Materiales | B36: Cotización y compra herramientas para cuadrillas (3 sets completos) | C36: 2s | D36: Enc. Bodega
A37: Materiales | B37: Compra estructuras metálicas soporte panel (75 unidades) | C37: 3s | D37: Enc. Bodega
A38: Materiales | B38: Compra materiales instalación: cableado DC/AC, porta soquetes, ferretería eléctrica | C38: 3s | D38: Enc. Bodega
A39: Materiales | B39: Compra insumos complementarios: impresión manuales usuarios (75 sets) | C39: 1s | D39: Enc. Bodega
A40: Materiales | B40: Recepción y stock en bodega · inventario de insumos | C40: 1s | D40: Enc. Bodega
A42: Logís- tica | B42: FASE 6 — LOGÍSTICA NACIONAL Y PREPARACIÓN TERRENO
A43: Logística | B43: Habilitación bodega terreno (arriendo, acondicionamiento, seguridad) | C43: 2s | D43: Enc. Bodega
A44: Logística | B44: Recepción equipos en bodega · inventario por kit y número de serie | C44: 1s | D44: Enc. Bodega
A45: Logística | B45: Carga usuarios en sistema Proteo · contratos de servicio | C45: 2s | D45: RRCC / Apoyo Fin.
A46: Logística | B46: Asignación rutas cuadrillas por comunidad · calendarización visitas | C46: 1s | D46: Enc. Bodega / RRCC
A47: Logística | B47: Coordinación municipios y organizaciones comunitarias · jornadas informativas | C47: 2s | D47: RRCC
A49: Instala- ción | B49: FASE 7 — INSTALACIÓN EN TERRENO (75 viviendas)
A50: Instalación | B50: Encuestas socioeconómicas finales · fichas de interés · priorización beneficiarios | C50: 4s | D50: RRCC / Cuadrillas
A51: Instalación | B51: Conformación Centros Luz en Casa (CEF) por comunidad | C51: 2s | D51: RRCC
A52: Instalación | B52: Instalación Lote 1 | C52: 1m | D52: Cuadrillas / ITO
A53: Instalación | B53: Instalación Lote 2 | C53: 2m | D53: Cuadrillas / ITO
A54: Instalación | B54: Instalación Lote 3 | C54: 1m | D54: Cuadrillas / ITO
A55: Instalación | B55: Registro fotográfico + georreferenciación + acta recepción conforme (todas) | C55: 5m | D55: Cuadrillas / ITO
A56: Instalación | B56: Declaraciones TE-1 SEC voluntarias por instalación (trámite simultáneo) | C56: 4m | D56: Ap. Planos TE1
A57: Instalación | B57: Capacitación usuarios: uso, cuidado y reporte de fallas del sistema | C57: 4m | D57: RRCC / Cuadrillas
A58: Instalación | B58: ◆ 75/75 instalaciones completas · acta recepción total firmada | C58: ⬥ | D58: — | L58: ◆
A60: Rendi- ción | B60: FASE 8 — RENDICIÓN SISREC Y SEGUIMIENTO FINANCIERO
A61: Rendición | B61: Rendición mensual SISREC (plazo: 15 días hábiles tras cierre de mes) | C61: 11m | D61: Apoyo Financiero
A62: Rendición | B62: Conciliación bancaria mensual · carta conductora DIPIR · GORE Coquimbo | C62: 11m | D62: Apoyo Financiero
A63: Rendición | B63: Gestión observaciones GORE · corrección documentos y reenvío | C63: 11m | D63: Apoyo Financiero
A65: Cierre | B65: FASE 9 — CIERRE TÉCNICO Y ADMINISTRATIVO
A66: Cierre | B66: Elaboración Informe Final Técnico-Financiero (GORE + acciona.org) | C66: 2m | D66: Agustín D. / GORE
A67: Cierre | B67: Acta de Administración y Resguardo definitiva · inventario de activos (75 equipos) | C67: 2m | D67: Agustín D.
A68: Cierre | B68: Rendición final acumulada · cuadre total de gastos GORE vs FNDR | C68: 1m | D68: Apoyo Financiero
A69: Cierre | B69: Solicitud de cierre formal proyecto en SISREC (Subt. 33) | C69: 1m | D69: Apoyo Financiero
A70: Cierre | B70: Tramitación liberación garantía / boleta de fiel cumplimiento (si aplica) | C70: 1m | D70: Agustín D. / GORE
A71: Cierre | B71: ◆ Proyecto cerrado y aprobado por GORE · rendición 100% aprobada | C71: ⬥ | D71: — | P71: ◆
A73: LEYENDA DE COLORES POR FASE
F74: Gestión / Convenio | H74: Compra de equipos | J74: Importación / Aduana | L74: Contratación personal | N74: Materiales e insumos
F75: Logística nacional | H75: Instalación terreno | J75: Rendición SISREC | L75: Cierre | N75: ◆ Hito clave
A76: ⚠ CARTA GANTT REFERENCIAL — Plazos estimados conforme a Minuta de Proyecto Rev.1 (17/02/2026) y distribución de gastos del Flujo Neto/Bruto v1.4. Inicio del proyecto: julio 2026 (suscripción convenio GORE). Término instalaciones: febrero 2027. Cierre administrativo: junio 2027. La distribución de lotes sigue los factores de Supuestos: Lote 1=30% (nov-2026) · Lote 2=50% (dic-2026+ene-2027) · Lote 3=20% (feb-2027). Lead time importación Zimpertec: 4-5 meses fabricación + ~6 semanas transporte marítimo (dato Minuta Técnica Rev.1.0). Plazos reales sujetos a fecha de firma del convenio y disponibilidad de cuadrillas.

Sheet Analitica
A1: ANALÍTICA MENSUAL LOC CONSOLIDADA — LUZ EN CASA · GORE COQUIMBO
G2: PAÍS: | H2: =#NAME?
G3: DATO: | H3: =#NAME?
G4: CTRO COSTE | H4: APR Propio | AH4: =#NAME?
AG5: =#NAME?
A6: AUXILIAR | E6: ANALÍTICA MENSUAL LOC CONSOLIDADA | F6: EJECUTADO | G6: SIMULACIÓN | S6: BUDGET | T6: SIMULACIÓN | AF6: BUDGET | AG6: TOTAL | AH6: =#NAME? | AI6: =#NAME? | AJ6: =#NAME?
A7: CTRO. COSTE | B7: NIVEL 1 | C7: NIVEL 2 | D7: P&G | F7: ANTERIOR | G7: 46023 | H7: 46054 | I7: 46082 | J7: 46113 | K7: 46143 | L7: 46174 | M7: 46204 | N7: 46235 | O7: 46266 | P7: 46296 | Q7: 46327 | R7: 46357 | S7: 2026 | T7: 46388 | U7: 46419 | V7: 46447 | W7: 46478 | X7: 46508 | Y7: 46539 | Z7: 46569 | AA7: 46600 | AB7: 46631 | AC7: 46661 | AD7: 46692 | AE7: 46722 | AF7: 2027 | AG7: =#NAME? | AH7: =#NAME? | AI7: =#NAME? | AJ7: =#NAME?
A8: PROYECTOS | B8: =+E7 | C8: =+E7 | E8: PROYECTOS
A9: =+A7 | B9: =+E8 | C9: =+E8 | E9: 20. Ingresos de proyectos | G9: =SUM(G9:G10) | H9: =SUM(H9:H10) | I9: =SUM(I9:I10) | J9: =SUM(J9:J10) | K9: =SUM(K9:K10) | L9: =SUM(L9:L10) | M9: =SUM(M9:M10) | N9: =SUM(N9:N10) | ... R9: =SUM(R9:R10) | S9: =SUM(G8:R8) | T9: =SUM(T9:T10) | U9: =SUM(U9:U10) | V9: =SUM(V9:V10) | W9: =SUM(W9:W10) | X9: =SUM(X9:X10) | Y9: =SUM(Y9:Y10) | Z9: =SUM(Z9:Z10) | AA9: =SUM(AA9:AA10) | ... AE9: =SUM(AE9:AE10) | AF9: =SUM(T8:AE8) | AG9: =SUM(AG9:AG10) | AI9: =SUM(AI9:AI10) | AJ9: =IF(AI8<>0,AI8/AH8,0)
A10: =+A8 | B10: =+B8 | C10: =+E9 | E10: 20.1. Subvenciones y ayudas AECID | S10: =SUM(G9:R9) | AF10: =SUM(T9:AE9) | AG10: =+SUM(S9,F9,AF9) | AI10: =+AG9-AH9 | AJ10: =IF(AI9<>0,AI9/AH9,0)
A11: =+A9 | B11: =+B9 | C11: =+E10 | E11: 20.2. Otras subvenciones y ayudas | S11: =SUM(G10:R10) | AF11: =SUM(T10:AE10) | AG11: =+SUM(S10,F10,AF10) | AI11: =+AG10-AH10 | AJ11: =IF(AI10<>0,AI10/AH10,0)
A12: =+A10 | B12: =+E11 | C12: =+E11 | E12: 21. Inversión de proyectos | G12: =SUM(G12:G14) | H12: =SUM(H12:H14) | I12: =SUM(I12:I14) | J12: =SUM(J12:J14) | K12: =SUM(K12:K14) | L12: =SUM(L12:L14) | M12: =SUM(M12:M14) | N12: =SUM(N12:N14) | ... R12: =SUM(R12:R14) | S12: =SUM(G11:R11) | T12: =SUM(T12:T14) | U12: =SUM(U12:U14) | V12: =SUM(V12:V14) | W12: =SUM(W12:W14) | X12: =SUM(X12:X14) | Y12: =SUM(Y12:Y14) | Z12: =SUM(Z12:Z14) | AA12: =SUM(AA12:AA14) | ... AE12: =SUM(AE12:AE14) | AF12: =SUM(T11:AE11) | AG12: =SUM(AG12:AG14) | AI12: =SUM(AI12:AI14) | AJ12: =IF(AI11<>0,AI11/AH11,0)
A13: =+A11 | B13: =+B11 | C13: =+E12 | E13: 21.1. Compras activables equipos energía | G13: =+SUM('Flujo Neto'!H6:H10) | H13: =+SUM('Flujo Neto'!I6:I10) | I13: =+SUM('Flujo Neto'!J6:J10) | J13: =+SUM('Flujo Neto'!K6:K10) | K13: =+SUM('Flujo Neto'!L6:L10) | L13: =+SUM('Flujo Neto'!M6:M10) | M13: =+SUM('Flujo Neto'!N6:N10) | N13: =+SUM('Flujo Neto'!O6:O10) | ... R13: =+SUM('Flujo Neto'!S6:S10) | S13: =SUM(G12:R12) | T13: =+SUM('Flujo Neto'!V6:V10) | U13: =+SUM('Flujo Neto'!W6:W10) | V13: =+SUM('Flujo Neto'!X6:X10) | W13: =+SUM('Flujo Neto'!Y6:Y10) | X13: =+SUM('Flujo Neto'!Z6:Z10) | Y13: =+SUM('Flujo Neto'!AA6:AA10) | Z13: =+SUM('Flujo Neto'!AB6:AB10) | AA13: =+SUM('Flujo Neto'!AC6:AC10) | ... AE13: =+SUM('Flujo Neto'!AG6:AG10) | AF13: =SUM(T12:AE12) | AG13: =+SUM(S12,F12,AF12) | AI13: =+AG12-AH12 | AJ13: =IF(AI12<>0,AI12/AH12,0)
A14: =+A12 | B14: =+B12 | C14: =+E13 | E14: 21.2. Compras activables equipos agua | S14: =SUM(G13:R13) | AF14: =SUM(T13:AE13) | AG14: =+SUM(S13,F13,AF13) | AI14: =+AG13-AH13 | AJ14: =IF(AI13<>0,AI13/AH13,0)
A15: =+A13 | B15: =+B13 | C15: =+E14 | E15: 21.3. Trabajos realizados por otras empresas y activables como inversión | S15: =SUM(G14:R14) | AF15: =SUM(T14:AE14) | AG15: =+SUM(S14,F14,AF14) | AI15: =+AG14-AH14 | AJ15: =IF(AI14<>0,AI14/AH14,0)
A16: =+A14 | B16: =+E15 | C16: =+E15 | E16: 22. Compras inventariables de proyectos | G16: =SUM(G16:G17) | H16: =SUM(H16:H17) | I16: =SUM(I16:I17) | J16: =SUM(J16:J17) | K16: =SUM(K16:K17) | L16: =SUM(L16:L17) | M16: =SUM(M16:M17) | N16: =SUM(N16:N17) | ... R16: =SUM(R16:R17) | S16: =SUM(G15:R15) | T16: =SUM(T16:T17) | U16: =SUM(U16:U17) | V16: =SUM(V16:V17) | W16: =SUM(W16:W17) | X16: =SUM(X16:X17) | Y16: =SUM(Y16:Y17) | Z16: =SUM(Z16:Z17) | AA16: =SUM(AA16:AA17) | ... AE16: =SUM(AE16:AE17) | AF16: =SUM(T15:AE15) | AG16: =SUM(AG16:AG17) | AI16: =SUM(AI16:AI17) | AJ16: =IF(AI15<>0,AI15/AH15,0) | AK16: =AG15/$AG$36 | AL16: =AI15*1.19 | AN16: 22. Compras inventariables de proyectos
A17: =+A15 | B17: =+B15 | C17: =+E16 | E17: 22.1. Compra de artefactos a inventario (electrodómesticos) | S17: =SUM(G16:R16) | AF17: =SUM(T16:AE16) | AG17: =+SUM(S16,F16,AF16) | AI17: =+AG16-AH16 | AJ17: =IF(AI16<>0,AI16/AH16,0) | AN17: 22.1. Compra de artefactos a inventario (electrodómesticos)
A18: =+A16 | B18: =+B16 | C18: =+E17 | E18: 22.2. Compra de repuestos a inventario (panel, batería, PCBA, lámpara) | G18: =+'Flujo Neto'!H11 | H18: =+'Flujo Neto'!I11 | I18: =+'Flujo Neto'!J11 | J18: =+'Flujo Neto'!K11 | K18: =+'Flujo Neto'!L11 | L18: =+'Flujo Neto'!M11 | M18: =+'Flujo Neto'!N11 | N18: =+'Flujo Neto'!O11 | ... R18: =+'Flujo Neto'!S11 | S18: =SUM(G17:R17) | T18: =+'Flujo Neto'!V11 | U18: =+'Flujo Neto'!W11 | V18: =+'Flujo Neto'!X11 | W18: =+'Flujo Neto'!Y11 | X18: =+'Flujo Neto'!Z11 | Y18: =+'Flujo Neto'!AA11 | Z18: =+'Flujo Neto'!AB11 | AA18: =+'Flujo Neto'!AC11 | ... AE18: =+'Flujo Neto'!AG11 | AF18: =SUM(T17:AE17) | AG18: =+SUM(S17,F17,AF17) | AI18: =+AG17-AH17 | AJ18: =IF(AI17<>0,AI17/AH17,0) | AL18: =AI17*1.19 | AN18: 22.2. Compra de repuestos a inventario (panel, batería, PCBA, lámpara)
A19: =+A17 | B19: =+E18 | C19: =+E18 | E19: 23. Compras no activables ni inventariables de proyectos | G19: =+'Flujo Neto'!H16 | H19: =+'Flujo Neto'!I16 | I19: =+'Flujo Neto'!J16 | J19: =+'Flujo Neto'!K16 | K19: =+'Flujo Neto'!L16 | L19: =+'Flujo Neto'!M16 | M19: =+'Flujo Neto'!N16 | N19: =+'Flujo Neto'!O16 | ... R19: =+'Flujo Neto'!S16 | S19: =SUM(G18:R18) | T19: =+'Flujo Neto'!V16 | U19: =+'Flujo Neto'!W16 | V19: =+'Flujo Neto'!X16 | W19: =+'Flujo Neto'!Y16 | X19: =+'Flujo Neto'!Z16 | Y19: =+'Flujo Neto'!AA16 | Z19: =+'Flujo Neto'!AB16 | AA19: =+'Flujo Neto'!AC16 | ... AE19: =+'Flujo Neto'!AG16 | AF19: =SUM(T18:AE18) | AG19: =+SUM(S18,F18,AF18) | AI19: =+AG18-AH18 | AJ19: =IF(AI18<>0,AI18/AH18,0) | AK19: =AG18/$AG$36 | AL19: =AI18*1.19 | AN19: 23. Compras no activables ni inventariables de proyectos
A20: =+A18 | B20: =+E19 | C20: =+E19 | E20: 24. Gastos de personal de proyectos | G20: =+'Flujo Neto'!H20 | H20: =+'Flujo Neto'!I20 | I20: =+'Flujo Neto'!J20 | J20: =+'Flujo Neto'!K20 | K20: =+'Flujo Neto'!L20 | L20: =+'Flujo Neto'!M20 | M20: =+'Flujo Neto'!N20 | N20: =+'Flujo Neto'!O20 | ... R20: =+'Flujo Neto'!S20 | S20: =SUM(G19:R19) | T20: =+'Flujo Neto'!V20 | U20: =+'Flujo Neto'!W20 | V20: =+'Flujo Neto'!X20 | W20: =+'Flujo Neto'!Y20 | X20: =+'Flujo Neto'!Z20 | Y20: =+'Flujo Neto'!AA20 | Z20: =+'Flujo Neto'!AB20 | AA20: =+'Flujo Neto'!AC20 | ... AE20: =+'Flujo Neto'!AG20 | AF20: =SUM(T19:AE19) | AG20: =+SUM(S19,F19,AF19) | AI20: =+AG19-AH19 | AJ20: =IF(AI19<>0,AI19/AH19,0) | AK20: =AG19/$AG$36 | AL20: =AI19 | AN20: 24. Gastos de personal de proyectos
A21: =+A19 | B21: =+E20 | C21: =+E20 | E21: 25. Gastos de proyectos | G21: =SUM(G21:G35) | H21: =SUM(H21:H35) | I21: =SUM(I21:I35) | J21: =SUM(J21:J35) | K21: =SUM(K21:K35) | L21: =SUM(L21:L35) | M21: =SUM(M21:M35) | N21: =SUM(N21:N35) | ... R21: =SUM(R21:R35) | S21: =SUM(G20:R20) | T21: =SUM(T21:T35) | U21: =SUM(U21:U35) | V21: =SUM(V21:V35) | W21: =SUM(W21:W35) | X21: =SUM(X21:X35) | Y21: =SUM(Y21:Y35) | Z21: =SUM(Z21:Z35) | AA21: =SUM(AA21:AA35) | ... AE21: =SUM(AE21:AE35) | AF21: =SUM(T20:AE20) | AG21: =SUM(AG21:AG35) | AI21: =SUM(AI21:AI35) | AJ21: =IF(AI20<>0,AI20/AH20,0) | AK21: =AG20/$AG$36 | AL21: =AI20*1.19 | AN21: 25. Gastos de proyectos
A22: =+A20 | B22: =+B20 | C22: =+E21 | E22: 25.1. Alquiler de vehículos | G22: =+'Flujo Neto'!H34+'Flujo Neto'!H38+'Flujo Neto'!H39+'Flujo Neto'!H40 | H22: =+'Flujo Neto'!I34+'Flujo Neto'!I38+'Flujo Neto'!I39+'Flujo Neto'!I40 | I22: =+'Flujo Neto'!J34+'Flujo Neto'!J38+'Flujo Neto'!J39+'Flujo Neto'!J40 | J22: =+'Flujo Neto'!K34+'Flujo Neto'!K38+'Flujo Neto'!K39+'Flujo Neto'!K40 | K22: =+'Flujo Neto'!L34+'Flujo Neto'!L38+'Flujo Neto'!L39+'Flujo Neto'!L40 | L22: =+'Flujo Neto'!M34+'Flujo Neto'!M38+'Flujo Neto'!M39+'Flujo Neto'!M40 | M22: =+'Flujo Neto'!N34+'Flujo Neto'!N38+'Flujo Neto'!N39+'Flujo Neto'!N40 | N22: =+'Flujo Neto'!O34+'Flujo Neto'!O38+'Flujo Neto'!O39+'Flujo Neto'!O40 | ... R22: =+'Flujo Neto'!S34+'Flujo Neto'!S38+'Flujo Neto'!S39+'Flujo Neto'!S40 | S22: =SUM(G21:R21) | T22: =+'Flujo Neto'!V34+'Flujo Neto'!V38+'Flujo Neto'!V39+'Flujo Neto'!V40 | U22: =+'Flujo Neto'!W34+'Flujo Neto'!W38+'Flujo Neto'!W39+'Flujo Neto'!W40 | V22: =+'Flujo Neto'!X34+'Flujo Neto'!X38+'Flujo Neto'!X39+'Flujo Neto'!X40 | W22: =+'Flujo Neto'!Y34+'Flujo Neto'!Y38+'Flujo Neto'!Y39+'Flujo Neto'!Y40 | X22: =+'Flujo Neto'!Z34+'Flujo Neto'!Z38+'Flujo Neto'!Z39+'Flujo Neto'!Z40 | Y22: =+'Flujo Neto'!AA34+'Flujo Neto'!AA38+'Flujo Neto'!AA39+'Flujo Neto'!AA40 | Z22: =+'Flujo Neto'!AB34+'Flujo Neto'!AB38+'Flujo Neto'!AB39+'Flujo Neto'!AB40 | AA22: =+'Flujo Neto'!AC34+'Flujo Neto'!AC38+'Flujo Neto'!AC39+'Flujo Neto'!AC40 | ... AE22: =+'Flujo Neto'!AG34+'Flujo Neto'!AG38+'Flujo Neto'!AG39+'Flujo Neto'!AG40 | AF22: =SUM(T21:AE21) | AG22: =+SUM(S21,F21,AF21) | AI22: =+AG21-AH21 | AJ22: =IF(AI21<>0,AI21/AH21,0) | AK22: =AG21/$AG$36 | AN22: 25.1. Alquiler de vehículos
A23: =+A21 | B23: =+B21 | C23: =+E22 | E23: 25.2. Alquiler de oficinas | S23: =SUM(G22:R22) | AF23: =SUM(T22:AE22) | AG23: =+SUM(S22,F22,AF22) | AI23: =+AG22-AH22 | AJ23: =IF(AI22<>0,AI22/AH22,0) | AK23: =AG22/$AG$36 | AN23: 25.2. Alquiler de oficinas
A24: =+A22 | B24: =+B22 | C24: =+E23 | E24: 25.3. Alquiler otros | G24: =+'Flujo Neto'!H37 | H24: =+'Flujo Neto'!I37 | I24: =+'Flujo Neto'!J37 | J24: =+'Flujo Neto'!K37 | K24: =+'Flujo Neto'!L37 | L24: =+'Flujo Neto'!M37 | M24: =+'Flujo Neto'!N37 | N24: =+'Flujo Neto'!O37 | ... R24: =+'Flujo Neto'!S37 | S24: =SUM(G23:R23) | T24: =+'Flujo Neto'!V37 | U24: =+'Flujo Neto'!W37 | V24: =+'Flujo Neto'!X37 | W24: =+'Flujo Neto'!Y37 | X24: =+'Flujo Neto'!Z37 | Y24: =+'Flujo Neto'!AA37 | Z24: =+'Flujo Neto'!AB37 | AA24: =+'Flujo Neto'!AC37 | ... AE24: =+'Flujo Neto'!AG37 | AF24: =SUM(T23:AE23) | AG24: =+SUM(S23,F23,AF23) | AI24: =+AG23-AH23 | AJ24: =IF(AI23<>0,AI23/AH23,0) | AK24: =AG23/$AG$36 | AN24: 25.3. Alquiler otros
A25: =+A23 | B25: =+B23 | C25: =+E24 | E25: 25.4. Reparación y conservación otros | S25: =SUM(G24:R24) | AF25: =SUM(T24:AE24) | AG25: =+SUM(S24,F24,AF24) | AI25: =+AG24-AH24 | AJ25: =IF(AI24<>0,AI24/AH24,0) | AK25: =AG24/$AG$36 | AN25: 25.4. Reparación y conservación otros
A26: =+A24 | B26: =+B24 | C26: =+E25 | E26: 25.5. Servicios profesionales auditorías | S26: =SUM(G25:R25) | AF26: =SUM(T25:AE25) | AG26: =+SUM(S25,F25,AF25) | AI26: =+AG25-AH25 | AJ26: =IF(AI25<>0,AI25/AH25,0) | AK26: =AG25/$AG$36 | AN26: 25.5. Servicios profesionales auditorías
A27: =+A25 | B27: =+B25 | C27: =+E26 | E27: 25.6. Servicios profesionales otros | G27: =+'Flujo Neto'!H23 | H27: =+'Flujo Neto'!I23 | I27: =+'Flujo Neto'!J23 | J27: =+'Flujo Neto'!K23 | K27: =+'Flujo Neto'!L23 | L27: =+'Flujo Neto'!M23 | M27: =+'Flujo Neto'!N23 | N27: =+'Flujo Neto'!O23 | ... R27: =+'Flujo Neto'!S23 | S27: =SUM(G26:R26) | T27: =+'Flujo Neto'!V23 | U27: =+'Flujo Neto'!W23 | V27: =+'Flujo Neto'!X23 | W27: =+'Flujo Neto'!Y23 | X27: =+'Flujo Neto'!Z23 | Y27: =+'Flujo Neto'!AA23 | Z27: =+'Flujo Neto'!AB23 | AA27: =+'Flujo Neto'!AC23 | ... AE27: =+'Flujo Neto'!AG23 | AF27: =SUM(T26:AE26) | AG27: =+SUM(S26,F26,AF26) | AI27: =+AG26-AH26 | AJ27: =IF(AI26<>0,AI26/AH26,0) | AK27: =AG26/$AG$36 | AN27: 25.6. Servicios profesionales otros
A28: =+A26 | B28: =+B26 | C28: =+E27 | E28: 25.7. Correo, mensajería, coste transporte equipos | G28: =+'Flujo Neto'!H12+SUM('Flujo Neto'!H42:H48) | H28: =+'Flujo Neto'!I12+SUM('Flujo Neto'!I42:I48) | I28: =+'Flujo Neto'!J12+SUM('Flujo Neto'!J42:J48) | J28: =+'Flujo Neto'!K12+SUM('Flujo Neto'!K42:K48) | K28: =+'Flujo Neto'!L12+SUM('Flujo Neto'!L42:L48) | L28: =+'Flujo Neto'!M12+SUM('Flujo Neto'!M42:M48) | M28: =+'Flujo Neto'!N12+SUM('Flujo Neto'!N42:N48) | N28: =+'Flujo Neto'!O12+SUM('Flujo Neto'!O42:O48) | ... R28: =+'Flujo Neto'!S12+SUM('Flujo Neto'!S42:S48) | S28: =SUM(G27:R27) | T28: =+'Flujo Neto'!V12+SUM('Flujo Neto'!V42:V48) | U28: =+'Flujo Neto'!W12+SUM('Flujo Neto'!W42:W48) | V28: =+'Flujo Neto'!X12+SUM('Flujo Neto'!X42:X48) | W28: =+'Flujo Neto'!Y12+SUM('Flujo Neto'!Y42:Y48) | X28: =+'Flujo Neto'!Z12+SUM('Flujo Neto'!Z42:Z48) | Y28: =+'Flujo Neto'!AA12+SUM('Flujo Neto'!AA42:AA48) | Z28: =+'Flujo Neto'!AB12+SUM('Flujo Neto'!AB42:AB48) | AA28: =+'Flujo Neto'!AC12+SUM('Flujo Neto'!AC42:AC48) | ... AE28: =+'Flujo Neto'!AG12+SUM('Flujo Neto'!AG42:AG48) | AF28: =SUM(T27:AE27) | AG28: =+SUM(S27,F27,AF27) | AI28: =+AG27-AH27 | AJ28: =IF(AI27<>0,AI27/AH27,0) | AK28: =AG27/$AG$36 | AN28: 25.7. Correo, mensajería, coste transporte equipos
A29: =+A27 | B29: =+B27 | C29: =+E28 | E29: 25.8. Seguros | S29: =SUM(G28:R28) | AF29: =SUM(T28:AE28) | AG29: =+SUM(S28,F28,AF28) | AI29: =+AG28-AH28 | AJ29: =IF(AI28<>0,AI28/AH28,0) | AK29: =AG28/$AG$36 | AN29: 25.8. Seguros
A30: =+A28 | B30: =+B28 | C30: =+E29 | E30: 25.9. Gastos y comisiones bancarias | S30: =SUM(G29:R29) | AF30: =SUM(T29:AE29) | AG30: =+SUM(S29,F29,AF29) | AI30: =+AG29-AH29 | AJ30: =IF(AI29<>0,AI29/AH29,0) | AK30: =AG29/$AG$36 | AN30: 25.9. Gastos y comisiones bancarias
A31: =+A29 | B31: =+B29 | C31: =+E30 | E31: 25.10. Publicidad | S31: =SUM(G30:R30) | AF31: =SUM(T30:AE30) | AG31: =+SUM(S30,F30,AF30) | AI31: =+AG30-AH30 | AJ31: =IF(AI30<>0,AI30/AH30,0) | AK31: =AG30/$AG$36 | AN31: 25.10. Publicidad
A32: =+A30 | B32: =+B30 | C32: =+E31 | E32: 25.11. Suministro de combustible para vehículos | G32: =+'Flujo Neto'!H53+'Flujo Neto'!H54+'Flujo Neto'!H60+'Flujo Neto'!H61 | H32: =+'Flujo Neto'!I53+'Flujo Neto'!I54+'Flujo Neto'!I60+'Flujo Neto'!I61 | I32: =+'Flujo Neto'!J53+'Flujo Neto'!J54+'Flujo Neto'!J60+'Flujo Neto'!J61 | J32: =+'Flujo Neto'!K53+'Flujo Neto'!K54+'Flujo Neto'!K60+'Flujo Neto'!K61 | K32: =+'Flujo Neto'!L53+'Flujo Neto'!L54+'Flujo Neto'!L60+'Flujo Neto'!L61 | L32: =+'Flujo Neto'!M53+'Flujo Neto'!M54+'Flujo Neto'!M60+'Flujo Neto'!M61 | M32: =+'Flujo Neto'!N53+'Flujo Neto'!N54+'Flujo Neto'!N60+'Flujo Neto'!N61 | N32: =+'Flujo Neto'!O53+'Flujo Neto'!O54+'Flujo Neto'!O60+'Flujo Neto'!O61 | ... R32: =+'Flujo Neto'!S53+'Flujo Neto'!S54+'Flujo Neto'!S60+'Flujo Neto'!S61 | S32: =SUM(G31:R31) | T32: =+'Flujo Neto'!V53+'Flujo Neto'!V54+'Flujo Neto'!V60+'Flujo Neto'!V61 | U32: =+'Flujo Neto'!W53+'Flujo Neto'!W54+'Flujo Neto'!W60+'Flujo Neto'!W61 | V32: =+'Flujo Neto'!X53+'Flujo Neto'!X54+'Flujo Neto'!X60+'Flujo Neto'!X61 | W32: =+'Flujo Neto'!Y53+'Flujo Neto'!Y54+'Flujo Neto'!Y60+'Flujo Neto'!Y61 | X32: =+'Flujo Neto'!Z53+'Flujo Neto'!Z54+'Flujo Neto'!Z60+'Flujo Neto'!Z61 | Y32: =+'Flujo Neto'!AA53+'Flujo Neto'!AA54+'Flujo Neto'!AA60+'Flujo Neto'!AA61 | Z32: =+'Flujo Neto'!AB53+'Flujo Neto'!AB54+'Flujo Neto'!AB60+'Flujo Neto'!AB61 | AA32: =+'Flujo Neto'!AC53+'Flujo Neto'!AC54+'Flujo Neto'!AC60+'Flujo Neto'!AC61 | ... AE32: =+'Flujo Neto'!AG53+'Flujo Neto'!AG54+'Flujo Neto'!AG60+'Flujo Neto'!AG61 | AF32: =SUM(T31:AE31) | AG32: =+SUM(S31,F31,AF31) | AI32: =+AG31-AH31 | AJ32: =IF(AI31<>0,AI31/AH31,0) | AK32: =AG31/$AG$36 | AN32: 25.11. Suministro de combustible para vehículos
A33: =+A31 | B33: =+B31 | C33: =+E32 | E33: 25.12. Suministro otros | S33: =SUM(G32:R32) | AF33: =SUM(T32:AE32) | AG33: =+SUM(S32,F32,AF32) | AI33: =+AG32-AH32 | AJ33: =IF(AI32<>0,AI32/AH32,0) | AK33: =AG32/$AG$36 | AN33: 25.12. Suministro otros
A34: =+A32 | B34: =+B32 | C34: =+E33 | E34: 25.13. Viajes (billetes, vuelos, hoteles, otros) | G34: =+'Flujo Neto'!H50+'Flujo Neto'!H51+'Flujo Neto'!H52+'Flujo Neto'!H55+'Flujo Neto'!H57+'Flujo Neto'!H58+'Flujo Neto'!H59+'Flujo Neto'!H62 | H34: =+'Flujo Neto'!I50+'Flujo Neto'!I51+'Flujo Neto'!I52+'Flujo Neto'!I55+'Flujo Neto'!I57+'Flujo Neto'!I58+'Flujo Neto'!I59+'Flujo Neto'!I62 | I34: =+'Flujo Neto'!J50+'Flujo Neto'!J51+'Flujo Neto'!J52+'Flujo Neto'!J55+'Flujo Neto'!J57+'Flujo Neto'!J58+'Flujo Neto'!J59+'Flujo Neto'!J62 | J34: =+'Flujo Neto'!K50+'Flujo Neto'!K51+'Flujo Neto'!K52+'Flujo Neto'!K55+'Flujo Neto'!K57+'Flujo Neto'!K58+'Flujo Neto'!K59+'Flujo Neto'!K62 | K34: =+'Flujo Neto'!L50+'Flujo Neto'!L51+'Flujo Neto'!L52+'Flujo Neto'!L55+'Flujo Neto'!L57+'Flujo Neto'!L58+'Flujo Neto'!L59+'Flujo Neto'!L62 | L34: =+'Flujo Neto'!M50+'Flujo Neto'!M51+'Flujo Neto'!M52+'Flujo Neto'!M55+'Flujo Neto'!M57+'Flujo Neto'!M58+'Flujo Neto'!M59+'Flujo Neto'!M62 | M34: =+'Flujo Neto'!N50+'Flujo Neto'!N51+'Flujo Neto'!N52+'Flujo Neto'!N55+'Flujo Neto'!N57+'Flujo Neto'!N58+'Flujo Neto'!N59+'Flujo Neto'!N62 | N34: =+'Flujo Neto'!O50+'Flujo Neto'!O51+'Flujo Neto'!O52+'Flujo Neto'!O55+'Flujo Neto'!O57+'Flujo Neto'!O58+'Flujo Neto'!O59+'Flujo Neto'!O62 | ... R34: =+'Flujo Neto'!S50+'Flujo Neto'!S51+'Flujo Neto'!S52+'Flujo Neto'!S55+'Flujo Neto'!S57+'Flujo Neto'!S58+'Flujo Neto'!S59+'Flujo Neto'!S62 | S34: =SUM(G33:R33) | T34: =+'Flujo Neto'!V50+'Flujo Neto'!V51+'Flujo Neto'!V52+'Flujo Neto'!V55+'Flujo Neto'!V57+'Flujo Neto'!V58+'Flujo Neto'!V59+'Flujo Neto'!V62 | U34: =+'Flujo Neto'!W50+'Flujo Neto'!W51+'Flujo Neto'!W52+'Flujo Neto'!W55+'Flujo Neto'!W57+'Flujo Neto'!W58+'Flujo Neto'!W59+'Flujo Neto'!W62 | V34: =+'Flujo Neto'!X50+'Flujo Neto'!X51+'Flujo Neto'!X52+'Flujo Neto'!X55+'Flujo Neto'!X57+'Flujo Neto'!X58+'Flujo Neto'!X59+'Flujo Neto'!X62 | W34: =+'Flujo Neto'!Y50+'Flujo Neto'!Y51+'Flujo Neto'!Y52+'Flujo Neto'!Y55+'Flujo Neto'!Y57+'Flujo Neto'!Y58+'Flujo Neto'!Y59+'Flujo Neto'!Y62 | X34: =+'Flujo Neto'!Z50+'Flujo Neto'!Z51+'Flujo Neto'!Z52+'Flujo Neto'!Z55+'Flujo Neto'!Z57+'Flujo Neto'!Z58+'Flujo Neto'!Z59+'Flujo Neto'!Z62 | Y34: =+'Flujo Neto'!AA50+'Flujo Neto'!AA51+'Flujo Neto'!AA52+'Flujo Neto'!AA55+'Flujo Neto'!AA57+'Flujo Neto'!AA58+'Flujo Neto'!AA59+'Flujo Neto'!AA62 | Z34: =+'Flujo Neto'!AB50+'Flujo Neto'!AB51+'Flujo Neto'!AB52+'Flujo Neto'!AB55+'Flujo Neto'!AB57+'Flujo Neto'!AB58+'Flujo Neto'!AB59+'Flujo Neto'!AB62 | AA34: =+'Flujo Neto'!AC50+'Flujo Neto'!AC51+'Flujo Neto'!AC52+'Flujo Neto'!AC55+'Flujo Neto'!AC57+'Flujo Neto'!AC58+'Flujo Neto'!AC59+'Flujo Neto'!AC62 | ... AE34: =+'Flujo Neto'!AG50+'Flujo Neto'!AG51+'Flujo Neto'!AG52+'Flujo Neto'!AG55+'Flujo Neto'!AG57+'Flujo Neto'!AG58+'Flujo Neto'!AG59+'Flujo Neto'!AG62 | AF34: =SUM(T33:AE33) | AG34: =+SUM(S33,F33,AF33) | AI34: =+AG33-AH33 | AJ34: =IF(AI33<>0,AI33/AH33,0) | AK34: =AG33/$AG$36 | AN34: 25.13. Viajes (billetes, vuelos, hoteles, otros)
A35: =+A33 | B35: =+B33 | C35: =+E34 | E35: 25.14. Otros servicios (resto) | G35: =+SUM('Flujo Neto'!H64:H68) | H35: =+SUM('Flujo Neto'!I64:I68) | I35: =+SUM('Flujo Neto'!J64:J68) | J35: =+SUM('Flujo Neto'!K64:K68) | K35: =+SUM('Flujo Neto'!L64:L68) | L35: =+SUM('Flujo Neto'!M64:M68) | M35: =+SUM('Flujo Neto'!N64:N68) | N35: =+SUM('Flujo Neto'!O64:O68) | ... R35: =+SUM('Flujo Neto'!S64:S68) | S35: =SUM(G34:R34) | T35: =+SUM('Flujo Neto'!V64:V68) | U35: =+SUM('Flujo Neto'!W64:W68) | V35: =+SUM('Flujo Neto'!X64:X68) | W35: =+SUM('Flujo Neto'!Y64:Y68) | X35: =+SUM('Flujo Neto'!Z64:Z68) | Y35: =+SUM('Flujo Neto'!AA64:AA68) | Z35: =+SUM('Flujo Neto'!AB64:AB68) | AA35: =+SUM('Flujo Neto'!AC64:AC68) | ... AE35: =+SUM('Flujo Neto'!AG64:AG68) | AF35: =SUM(T34:AE34) | AG35: =+SUM(S34,F34,AF34) | AI35: =+AG34-AH34 | AJ35: =IF(AI34<>0,AI34/AH34,0) | AK35: =AG34/$AG$36 | AN35: 25.14. Otros servicios (resto)
A36: =+A33 | B36: =+B33 | C36: =+E35 | E36: 25.15. Tributos y tasas | S36: =SUM(G35:R35) | AF36: =SUM(T35:AE35) | AG36: =+SUM(S35,F35,AF35) | AI36: =+AG35-AH35 | AJ36: =IF(AI35<>0,AI35/AH35,0) | AK36: =AG35/$AG$36 | AN36: 25.15. Tributos y tasas
A37: =+A35 | B37: =+E36 | C37: =+E36 | E37: D1) RESULTADO PROYECTOS BRUTO (20+21+22+23+24+25) | G37: =+SUM(G8,G11,G15,G18,G19,G20) | H37: =+SUM(H8,H11,H15,H18,H19,H20) | I37: =+SUM(I8,I11,I15,I18,I19,I20) | J37: =+SUM(J8,J11,J15,J18,J19,J20) | K37: =+SUM(K8,K11,K15,K18,K19,K20) | L37: =+SUM(L8,L11,L15,L18,L19,L20) | M37: =+SUM(M8,M11,M15,M18,M19,M20) | N37: =+SUM(N8,N11,N15,N18,N19,N20) | ... R37: =+SUM(R8,R11,R15,R18,R19,R20) | S37: =SUM(G36:R36) | T37: =+SUM(T8,T11,T15,T18,T19,T20) | U37: =+SUM(U8,U11,U15,U18,U19,U20) | V37: =+SUM(V8,V11,V15,V18,V19,V20) | W37: =+SUM(W8,W11,W15,W18,W19,W20) | X37: =+SUM(X8,X11,X15,X18,X19,X20) | Y37: =+SUM(Y8,Y11,Y15,Y18,Y19,Y20) | Z37: =+SUM(Z8,Z11,Z15,Z18,Z19,Z20) | AA37: =+SUM(AA8,AA11,AA15,AA18,AA19,AA20) | ... AG37: =+SUM(AG8,AG11,AG15,AG18,AG19,AG20) | AI37: =+SUM(AI8,AI11,AI15,AI18,AI19,AI20) | AJ37: =IF(AI36<>0,AI36/AH36,0) | AL37: =SUM(AL15:AL35)
A38: =+A36 | B38: =+E37 | C38: =+E37 | E38: 26. Activación de inversión de proyectos | G38: =SUM(G38:G39) | H38: =SUM(H38:H39) | I38: =SUM(I38:I39) | J38: =SUM(J38:J39) | K38: =SUM(K38:K39) | L38: =SUM(L38:L39) | M38: =SUM(M38:M39) | N38: =SUM(N38:N39) | ... R38: =SUM(R38:R39) | S38: =SUM(G37:R37) | T38: =SUM(T38:T39) | U38: =SUM(U38:U39) | V38: =SUM(V38:V39) | W38: =SUM(W38:W39) | X38: =SUM(X38:X39) | Y38: =SUM(Y38:Y39) | Z38: =SUM(Z38:Z39) | AA38: =SUM(AA38:AA39) | ... AE38: =SUM(AE38:AE39) | AF38: =SUM(T37:AE37) | AG38: =SUM(AG38:AG39) | AI38: =SUM(AI38:AI39) | AJ38: =IF(AI37<>0,AI37/AH37,0)
A39: =+A37 | B39: =+B37 | C39: =+E38 | E39: 26.1. Alta de activo (+) | G39: =-G11 | H39: =-H11 | I39: =-I11 | J39: =-J11 | K39: =-K11 | L39: =-L11 | M39: =-M11 | N39: =-N11 | ... R39: =-R11 | S39: =SUM(G38:R38) | T39: =-T11 | U39: =-U11 | V39: =-V11 | W39: =-W11 | X39: =-X11 | Y39: =-Y11 | Z39: =-Z11 | AA39: =-AA11 | ... AE39: =-AE11 | AF39: =SUM(T38:AE38) | AG39: =+SUM(S38,F38,AF38) | AI39: =+AG38-AH38 | AJ39: =IF(AI38<>0,AI38/AH38,0)
A40: =+A38 | B40: =+B38 | C40: =+E39 | E40: 26.2. Pérdidas por Baja de activo (-) | S40: =SUM(G39:R39) | AF40: =SUM(T39:AE39) | AG40: =+SUM(S39,F39,AF39) | AI40: =+AG39-AH39 | AJ40: =IF(AI39<>0,AI39/AH39,0)
A41: =+A39 | B41: =+E40 | C41: =+E40 | E41: 27. Alta de inventario de proyectos | G41: =SUM(G41:G42) | H41: =SUM(H41:H42) | I41: =SUM(I41:I42) | J41: =SUM(J41:J42) | K41: =SUM(K41:K42) | L41: =SUM(L41:L42) | M41: =SUM(M41:M42) | N41: =SUM(N41:N42) | ... R41: =SUM(R41:R42) | S41: =SUM(G40:R40) | T41: =SUM(T41:T42) | U41: =SUM(U41:U42) | V41: =SUM(V41:V42) | W41: =SUM(W41:W42) | X41: =SUM(X41:X42) | Y41: =SUM(Y41:Y42) | Z41: =SUM(Z41:Z42) | AA41: =SUM(AA41:AA42) | ... AE41: =SUM(AE41:AE42) | AF41: =SUM(T40:AE40) | AG41: =SUM(AG41:AG42) | AI41: =SUM(AI41:AI42) | AJ41: =IF(AI40<>0,AI40/AH40,0)
A42: =+A40 | B42: =+B40 | C42: =+E41 | E42: 27.1. Alta de existencias (+) | G42: =-G15 | H42: =-H15 | I42: =-I15 | J42: =-J15 | K42: =-K15 | L42: =-L15 | M42: =-M15 | N42: =-N15 | ... R42: =-R15 | S42: =SUM(G41:R41) | T42: =-T15 | U42: =-U15 | V42: =-V15 | W42: =-W15 | X42: =-X15 | Y42: =-Y15 | Z42: =-Z15 | AA42: =-AA15 | ... AE42: =-AE15 | AF42: =SUM(T41:AE41) | AG42: =+SUM(S41,F41,AF41) | AI42: =+AG41-AH41 | AJ42: =IF(AI41<>0,AI41/AH41,0)
A43: =+A41 | B43: =+B41 | C43: =+E42 | E43: 27.2. Baja de existencias (-) | S43: =SUM(G42:R42) | AF43: =SUM(T42:AE42) | AG43: =+SUM(S42,F42,AF42) | AI43: =+AG42-AH42 | AJ43: =IF(AI42<>0,AI42/AH42,0)
A44: =+A42 | B44: =+E43 | C44: =+E43 | E44: D) RESULTADO PROYECTOS NETO (20+21+22+23+24+25+26+27) | G44: =+SUM(G36,G37,G40) | H44: =+SUM(H36,H37,H40) | I44: =+SUM(I36,I37,I40) | J44: =+SUM(J36,J37,J40) | K44: =+SUM(K36,K37,K40) | L44: =+SUM(L36,L37,L40) | M44: =+SUM(M36,M37,M40) | N44: =+SUM(N36,N37,N40) | ... R44: =+SUM(R36,R37,R40) | S44: =SUM(G43:R43) | T44: =+SUM(T36,T37,T40) | U44: =+SUM(U36,U37,U40) | V44: =+SUM(V36,V37,V40) | W44: =+SUM(W36,W37,W40) | X44: =+SUM(X36,X37,X40) | Y44: =+SUM(Y36,Y37,Y40) | Z44: =+SUM(Z36,Z37,Z40) | AA44: =+SUM(AA36,AA37,AA40) | ... AE44: =+SUM(AE36,AE37,AE40) | AF44: =SUM(T43:AE43) | AG44: =+SUM(AG36,AG37,AG40) | AI44: =+SUM(AI36,AI37,AI40) | AJ44: =IF(AI43<>0,AI43/AH43,0)
O47: MONEDA: | P47: =#NAME? | Q47: PAÍS: | R47: =#NAME?
E48: * Desglosar para ver importes en EUR | O48: T/CAMBIO: | P48: =#NAME? | Q48: DATO: | R48: =#NAME? | AG48: =AG36/60
AG50: =+AG4 | AH50: =+AH3
E51: ANALÍTICA MENSUAL EUR CONSOLIDADA | F51: =+F5 | G51: =+G5 | S51: =+S5 | AF51: =+AF5 | AG51: =+AG5 | AH51: =+AH5 | AI51: =+AI5 | AJ51: =+AJ5
F52: =+F6 | G52: =+G6 | H52: =+H6 | I52: =+I6 | J52: =+J6 | K52: =+K6 | L52: =+L6 | M52: =+M6 | ... S52: =+S6 | AF52: =+AF6 | AG52: =+AG6 | AH52: =+AH6 | AI52: =+AI6 | AJ52: =+AJ6
A53: =+A7 | B53: =+B7 | C53: =+C7 | D53: =+D7 | E53: =+E7
A54: =+A8 | B54: =+B8 | C54: =+C8 | D54: =+D8 | E54: =+E8 | F54: =+F8*$P$47 | G54: =+G8*$P$47 | H54: =+H8*$P$47 | I54: =+I8*$P$47 | J54: =+J8*$P$47 | K54: =+K8*$P$47 | L54: =+L8*$P$47 | M54: =+M8*$P$47 | ... S54: =+S8*$P$47 | AF54: =+AF8*$P$47 | AG54: =+AG8*$P$47 | AH54: =+AH8*$P$47 | AI54: =+AI8*$P$47 | AJ54: =IF(AI53<>0,AI53/AH53,0)
A55: =+A9 | B55: =+B9 | C55: =+C9 | D55: =+D9 | E55: =+E9 | F55: =+F9*$P$47 | G55: =+G9*$P$47 | H55: =+H9*$P$47 | I55: =+I9*$P$47 | J55: =+J9*$P$47 | K55: =+K9*$P$47 | L55: =+L9*$P$47 | M55: =+M9*$P$47 | ... S55: =+S9*$P$47 | AF55: =+AF9*$P$47 | AG55: =+AG9*$P$47 | AH55: =+AH9*$P$47 | AI55: =+AI9*$P$47 | AJ55: =IF(AI54<>0,AI54/AH54,0)
A56: =+A10 | B56: =+B10 | C56: =+C10 | D56: =+D10 | E56: =+E10 | F56: =+F10*$P$47 | G56: =+G10*$P$47 | H56: =+H10*$P$47 | I56: =+I10*$P$47 | J56: =+J10*$P$47 | K56: =+K10*$P$47 | L56: =+L10*$P$47 | M56: =+M10*$P$47 | ... S56: =+S10*$P$47 | AF56: =+AF10*$P$47 | AG56: =+AG10*$P$47 | AH56: =+AH10*$P$47 | AI56: =+AI10*$P$47 | AJ56: =IF(AI55<>0,AI55/AH55,0)
A57: =+A11 | B57: =+B11 | C57: =+C11 | D57: =+D11 | E57: =+E11 | F57: =+F11*$P$47 | G57: =+G11*$P$47 | H57: =+H11*$P$47 | I57: =+I11*$P$47 | J57: =+J11*$P$47 | K57: =+K11*$P$47 | L57: =+L11*$P$47 | M57: =+M11*$P$47 | ... S57: =+S11*$P$47 | AF57: =+AF11*$P$47 | AG57: =+AG11*$P$47 | AH57: =+AH11*$P$47 | AI57: =+AI11*$P$47 | AJ57: =IF(AI56<>0,AI56/AH56,0)
A58: =+A12 | B58: =+B12 | C58: =+C12 | D58: =+D12 | E58: =+E12 | F58: =+F12*$P$47 | G58: =+G12*$P$47 | H58: =+H12*$P$47 | I58: =+I12*$P$47 | J58: =+J12*$P$47 | K58: =+K12*$P$47 | L58: =+L12*$P$47 | M58: =+M12*$P$47 | ... S58: =+S12*$P$47 | AF58: =+AF12*$P$47 | AG58: =+AG12*$P$47 | AH58: =+AH12*$P$47 | AI58: =+AI12*$P$47 | AJ58: =IF(AI57<>0,AI57/AH57,0)
A59: =+A13 | B59: =+B13 | C59: =+C13 | D59: =+D13 | E59: =+E13 | F59: =+F13*$P$47 | G59: =+G13*$P$47 | H59: =+H13*$P$47 | I59: =+I13*$P$47 | J59: =+J13*$P$47 | K59: =+K13*$P$47 | L59: =+L13*$P$47 | M59: =+M13*$P$47 | ... S59: =+S13*$P$47 | AF59: =+AF13*$P$47 | AG59: =+AG13*$P$47 | AH59: =+AH13*$P$47 | AI59: =+AI13*$P$47 | AJ59: =IF(AI58<>0,AI58/AH58,0)
A60: =+A14 | B60: =+B14 | C60: =+C14 | D60: =+D14 | E60: =+E14 | F60: =+F14*$P$47 | G60: =+G14*$P$47 | H60: =+H14*$P$47 | I60: =+I14*$P$47 | J60: =+J14*$P$47 | K60: =+K14*$P$47 | L60: =+L14*$P$47 | M60: =+M14*$P$47 | ... S60: =+S14*$P$47 | AF60: =+AF14*$P$47 | AG60: =+AG14*$P$47 | AH60: =+AH14*$P$47 | AI60: =+AI14*$P$47 | AJ60: =IF(AI59<>0,AI59/AH59,0)
A61: =+A15 | B61: =+B15 | C61: =+C15 | D61: =+D15 | E61: =+E15 | F61: =+F15*$P$47 | G61: =+G15*$P$47 | H61: =+H15*$P$47 | I61: =+I15*$P$47 | J61: =+J15*$P$47 | K61: =+K15*$P$47 | L61: =+L15*$P$47 | M61: =+M15*$P$47 | ... S61: =+S15*$P$47 | AF61: =+AF15*$P$47 | AG61: =+AG15*$P$47 | AH61: =+AH15*$P$47 | AI61: =+AI15*$P$47 | AJ61: =IF(AI60<>0,AI60/AH60,0)
A62: =+A16 | B62: =+B16 | C62: =+C16 | D62: =+D16 | E62: =+E16 | F62: =+F16*$P$47 | G62: =+G16*$P$47 | H62: =+H16*$P$47 | I62: =+I16*$P$47 | J62: =+J16*$P$47 | K62: =+K16*$P$47 | L62: =+L16*$P$47 | M62: =+M16*$P$47 | ... S62: =+S16*$P$47 | AF62: =+AF16*$P$47 | AG62: =+AG16*$P$47 | AH62: =+AH16*$P$47 | AI62: =+AI16*$P$47 | AJ62: =IF(AI61<>0,AI61/AH61,0)
A63: =+A17 | B63: =+B17 | C63: =+C17 | D63: =+D17 | E63: =+E17 | F63: =+F17*$P$47 | G63: =+G17*$P$47 | H63: =+H17*$P$47 | I63: =+I17*$P$47 | J63: =+J17*$P$47 | K63: =+K17*$P$47 | L63: =+L17*$P$47 | M63: =+M17*$P$47 | ... S63: =+S17*$P$47 | AF63: =+AF17*$P$47 | AG63: =+AG17*$P$47 | AH63: =+AH17*$P$47 | AI63: =+AI17*$P$47 | AJ63: =IF(AI62<>0,AI62/AH62,0)
A64: =+A18 | B64: =+B18 | C64: =+C18 | D64: =+D18 | E64: =+E18 | F64: =+F18*$P$47 | G64: =+G18*$P$47 | H64: =+H18*$P$47 | I64: =+I18*$P$47 | J64: =+J18*$P$47 | K64: =+K18*$P$47 | L64: =+L18*$P$47 | M64: =+M18*$P$47 | ... S64: =+S18*$P$47 | AF64: =+AF18*$P$47 | AG64: =+AG18*$P$47 | AH64: =+AH18*$P$47 | AI64: =+AI18*$P$47 | AJ64: =IF(AI63<>0,AI63/AH63,0)
A65: =+A19 | B65: =+B19 | C65: =+C19 | D65: =+D19 | E65: =+E19 | F65: =+F19*$P$47 | G65: =+G19*$P$47 | H65: =+H19*$P$47 | I65: =+I19*$P$47 | J65: =+J19*$P$47 | K65: =+K19*$P$47 | L65: =+L19*$P$47 | M65: =+M19*$P$47 | ... S65: =+S19*$P$47 | AF65: =+AF19*$P$47 | AG65: =+AG19*$P$47 | AH65: =+AH19*$P$47 | AI65: =+AI19*$P$47 | AJ65: =IF(AI64<>0,AI64/AH64,0)
... A89: =+A43 | B89: =+B43 | C89: =+C43 | D89: =+D43 | E89: =+E43 | F89: =+F43*$P$47 | G89: =+G43*$P$47 | H89: =+H43*$P$47 | I89: =+I43*$P$47 | J89: =+J43*$P$47 | K89: =+K43*$P$47 | L89: =+L43*$P$47 | M89: =+M43*$P$47 | ... S89: =+S43*$P$47 | AF89: =+AF43*$P$47 | AG89: =+AG43*$P$47 | AH89: =+AH43*$P$47 | AI89: =+AI43*$P$47 | AJ89: =IF(AI88<>0,AI88/AH88,0)

Sheet Tabla Calculo Sueldo
A1: CALCULADORA SERVICIOS PROFESIONALES — LUZ EN CASA
B2: CALCULADORA PROPUESTA — SERVICIOS PROFESIONALES
B3: 1) Parámetros editables de cálculo
C4: Parámetro | D4: Valor | E4: Comentario / uso
C5: Retención boleta honorarios 2026 | D5: 0.1525 | E5: Se usa cuando se acuerda un monto líquido con prestador a honorarios.
C6: IVA factura | D6: 0.19 | E6: Se usa solo para servicios profesionales facturados.
C7: SIS empleador | D7: 0.0188 | E7: Editable. Cargo empleador sobre remuneración imponible.
C8: Seguro cesantía indefinido empleador | D8: 0.024 | E8: Contrato indefinido: 2,4% empleador, editable.
C9: Seguro cesantía plazo/obra empleador | D9: 0.03 | E9: Contrato plazo/obra: 3,0% empleador, editable.
C10: Seguro social empleador | D10: 0.01 | E10: Cotización adicional empleador iniciada en 2025. Editable.
C11: Mutualidad / accidentes trabajo | D11: 0.0093 | E11: Tasa referencial. Reemplazar por tasa ACCIONA si aplica.
C12: Otros costos empresa ACCIONA | D12: 0 | E12: Campo libre para beneficios, provisiones u overhead interno.
C13: Descuento trabajador ref. para líquido contrato | D13: 0.2 | E13: Solo para simulación de sueldo líquido deseado; validar con RR.HH.
C14: Factor costo empresa contrato indefinido | D14: =1+D6+D7+D9+D10+D11 | E14: Sueldo bruto × factor = costo empresa mensual.
C15: Factor costo empresa contrato plazo/obra | D15: =1+D6+D8+D9+D10+D11 | E15: Sueldo bruto × factor = costo empresa mensual.
B17: 2) Tabla para definir el valor unitario a ingresar en Servicios Profesionales
B19: Nivel | C19: Ítem | D19: Modalidad | E19: Tipo contrato | F19: Tipo monto base | G19: Monto base ingresado | H19: Cant./meses/inst. | I19: Costo empresa unitario | J19: Valor NETO a ingresar en Supuestos | K19: IVA calculado | L19: Valor BRUTO / rendición | M19: Líquido estimado prestador/trabajador | N19: Forma pago sugerida | O19: Observación
B20: 4.1 | C20: Encargado de Logística y Bodega | D20: Boleta honorarios | E20: Plazo/obra | F20: Líquido deseado | G20: 850000 | H20: 1 | I20: =IF(D19="Boleta honorarios",IF(F19="Líquido deseado",G19/(1-$D$4),G19),IF(D19="Contrato ACCIONA",IF(F19="Sueldo bruto mensual",G19*IF(E19="Indefinido",$D$13,$D$14),IF(F19="Líquido deseado",(G19/(1-$D$12))*IF(E19="Indefinido",$D$13,$D$14),G19)),IF(D19="Factura",IF(F19="Total factura con IVA",G19,G19*(1+$D$5)),0))) | J20: =IF(D19="Factura",IF(F19="Total factura con IVA",G19/(1+$D$5),G19),I19) | K20: =IF(D19="Factura",J19*$D$5,0) | L20: =J19+K19 | M20: =IF(D19="Boleta honorarios",J19*(1-$D$4),IF(D19="Contrato ACCIONA",IF(F19="Líquido deseado",G19,IF(F19="Sueldo bruto mensual",G19*(1-$D$12),"")),L19)) | N20: =IF(D19="Boleta honorarios","Boleta Honorarios",IF(D19="Contrato ACCIONA","Costo Empresa","Factura")) | O20: Si se quiere que reciba líquido $1.000.000, la empresa debe presupuestar la boleta bruta.
B21: 4.2 | C21: Técnico pago por instalación - Plan A | D21: Boleta honorarios | E21: Plazo/obra | F21: Líquido deseado | G21: 125000 | H21: 1 | I21: =IF(D20="Boleta honorarios",IF(F20="Líquido deseado",G20/(1-$D$4),G20),IF(D20="Contrato ACCIONA",IF(F20="Sueldo bruto mensual",G20*IF(E20="Indefinido",$D$13,$D$14),IF(F20="Líquido deseado",(G20/(1-$D$12))*IF(E20="Indefinido",$D$13,$D$14),G20)),IF(D20="Factura",IF(F20="Total factura con IVA",G20,G20*(1+$D$5)),0))) | J21: =IF(D20="Factura",IF(F20="Total factura con IVA",G20/(1+$D$5),G20),I20) | K21: =IF(D20="Factura",J20*$D$5,0) | L21: =J20+K20 | M21: =IF(D20="Boleta honorarios",J20*(1-$D$4),IF(D20="Contrato ACCIONA",IF(F20="Líquido deseado",G20,IF(F20="Sueldo bruto mensual",G20*(1-$D$12),"")),L20)) | N21: =IF(D20="Boleta honorarios","Boleta Honorarios",IF(D20="Contrato ACCIONA","Costo Empresa","Factura")) | O21: Útil para pago por instalación: convierte líquido pactado a costo empresa por boleta.
